Workbook

Sheet Read me
A1: Marketplace import arbitrage calculator
A2: China factory (FOB) → Australia → sold new on Facebook Marketplace (local pickup). Data as at 9 October 2026.
A4: What it does
A5: Calculates landed cost per unit, gross profit (GP), GP % and the cash needed for the 19 products verified in our research (18 shortlisted SKUs plus the recovery-kit + tracks bundle variant) – including the ones that failed verification, with their verdict and revised score so you can see why. Each row is pre-filled with the verify note's recommended first order (shipping mode, quantity and price), so the numbers reconcile with the notes until you overwrite them.
A6: How to use it
A7: 1. Blue cells are inputs – overwrite them. Black cells are formulas, green cells link from another sheet, grey italic cells are reference figures copied from the notes (not inputs).
A8: 2. Assumptions – global inputs: FX, freight per CBM for LCL / 20GP / 40HQ, container weight caps, duty with the ChAFTA Certificate-of-Origin toggle, GST, inspection, defect allowance, storage, Marketplace fee and the pricing rule.
A9: 3. Products – as supplier quotes arrive, overwrite FOB (and its unit: per piece / pair / kg), MOQ, carton CBM / kg and compliance costs; pick the shipping mode from the dropdown and set the order quantity. Flags warn about MOQ, extra boxes, a cheaper freight mode, prices that break the 10–20%-below rule, missing data and losses.
A10: 4. Mixed container – combine SKUs in one 20GP or 40HQ (pre-filled with the gym and outdoor mixes from the notes) and check CBM and weight utilisation, cash, GP and GP %.
A11: 5. Sensitivity – GP per unit for the top-scored SKUs under FX, freight, duty, sale-price and FOB shocks. 6. Sources – the URLs behind every price, supplier and compliance figure, copied from the notes.
A12: Read before relying on it
A13: • Factory prices are PUBLIC LISTING PRICES (mostly Made-in-China.com tiers), NOT QUOTES – no RFQ was sent, Incoterms are mostly unstated and several cartons / weights are estimates (see the notes columns on Products). Replace them with real quotes before committing cash.
... A16: • Assumes a GST-registered seller: net revenue = price ÷ 1.1 and import GST is a reclaimable cash float. Product-liability insurance, returns / warranty and your time are not costed except where a note includes them (e.g. the recovery kit).
B18: Colour key | C18: Input (overwrite) | D18: Formula | F18: Link from another sheet | I18: Reference figure from the notes | K18: Loss / overfill / BROKEN
A20: Reconciliation – workbook GP per unit vs the verify notes (pre-filled base case)
A21: Same scenario as the note (mode, quantity, price, FOB, carton, compliance). Differences come only from small convention differences between the five notes; every SKU agrees within A$0.50 per unit. The comparison updates live, so it will drift once you overwrite inputs.
A22: # | B22: SKU | C22: Pre-filled scenario (from the note) | D22: Notes GP (A$/unit) | E22: Workbook GP (A$/unit) | F22: Difference (A$) | G22: Notes GP % | H22: Workbook GP % | I22: Within A$3? | J22: Reason for any difference | K22: Source note
A23: 1 | B23: Trampoline 14ft + enclosure | C23: 20GP, 128 units, A$349 | D23: 97.07 | E23: =Products!BE5 -> 97.064391 | F23: =IF(ISNUMBER(D23),E23-D23,"") -> -0.0056090269 | G23: 0.306 | H23: =Products!BF5 -> 0.30593361 | I23: =IF(ISNUMBER(F23),IF(ABS(F23)<=3,"Yes","No"),"") -> Yes | J23: Same method as the note; only FX rounding (A$1.4376 vs 1 ÷ 0.6956). | K23: verify_kids.md Q1
A24: 2 | B24: Kids 24V 2-seat UTV | C24: 20GP, 98 units, A$299 | D24: -19.57 | E24: =Products!BE6 -> -19.567238 | F24: =IF(ISNUMBER(D24),E24-D24,"") -> 0.0027623389 | G24: -0.072 | H24: =Products!BF6 -> -0.071986493 | I24: =IF(ISNUMBER(F24),IF(ABS(F24)<=3,"Yes","No"),"") -> Yes | J24: Same method as the note. | K24: verify_kids.md Q2
A25: 3 | B25: Timber cubby house | C25: 40HQ (part-filled), 300 units, A$299 | D25: 67.89 | E25: =Products!BE7 -> 67.887172 | F25: =IF(ISNUMBER(D25),E25-D25,"") -> -0.0028283601 | G25: 0.25 | H25: =Products!BF7 -> 0.24975214 | I25: =IF(ISNUMBER(F25),IF(ABS(F25)<=3,"Yes","No"),"") -> Yes | J25: Same method as the note (part-filled 40HQ costs the whole box). | K25: verify_kids.md Q3
A26: 4 | B26: 3-in-1 high chair | C26: LCL, 150 units, A$79 | D26: -28.67 | E26: =Products!BE8 -> -28.660289 | F26: =IF(ISNUMBER(D26),E26-D26,"") -> 0.0097111523 | G26: -0.399 | H26: =Products!BF8 -> -0.39906731 | I26: =IF(ISNUMBER(F26),IF(ABS(F26)<=3,"Yes","No"),"") -> Yes | J26: Same method as the note (flat A$5 handling). | K26: verify_kids.md Q4
A27: 5 | B27: Dual-motor standing desk | C27: LCL, 100 units, A$299 | D27: 46.96 | E27: =Products!BE9 -> 47.059159 | F27: =IF(ISNUMBER(D27),E27-D27,"") -> 0.099159298 | G27: 0.173 | H27: =Products!BF9 -> 0.17312734 | I27: =IF(ISNUMBER(F27),IF(ABS(F27)<=3,"Yes","No"),"") -> Yes | J27: verify_furniture.md applies the 3% defect allowance to storage too; the workbook applies it before storage (as the kids, outdoor and camping notes do). | K27: verify_furniture.md Q1
A28: 6 | B28: Manual fabric recliner | C28: 20GP, 84 units, A$139 | D28: -95.83 | E28: =Products!BE10 -> -95.502166 | F28: =IF(ISNUMBER(D28),E28-D28,"") -> 0.32783358 | G28: n/s | H28: =Products!BF10 -> -0.75577254 | I28: =IF(ISNUMBER(F28),IF(ABS(F28)<=3,"Yes","No"),"") -> Yes | J28: As SKU 5 (defect allowance on storage in the note). | K28: verify_furniture.md Q2
A29: 7 | B29: Fluted/LED TV unit 160cm | C29: LCL, 100 units, A$129 | D29: -15.33 | E29: =Products!BE11 -> -15.183395 | F29: =IF(ISNUMBER(D29),E29-D29,"") -> 0.14660479 | G29: n/s | H29: =Products!BF11 -> -0.12947081 | I29: =IF(ISNUMBER(F29),IF(ABS(F29)<=3,"Yes","No"),"") -> Yes | J29: As SKU 5 (defect allowance on storage in the note). | K29: verify_furniture.md Q3
A30: 8 | B30: Queen pocket-spring mattress | C30: LCL, 100 units, A$165 | D30: 2.7 | E30: =Products!BE12 -> 2.8454927 | F30: =IF(ISNUMBER(D30),E30-D30,"") -> 0.14549274 | G30: 0.018 | H30: =Products!BF12 -> 0.018969952 | I30: =IF(ISNUMBER(F30),IF(ABS(F30)<=3,"Yes","No"),"") -> Yes | J30: As SKU 5 (defect allowance on storage in the note). | K30: verify_furniture.md Q4
A31: 9 | B31: 100kg bumper plate set | C31: 20GP (weight-capped), 211 sets, A$339 | D31: 79.47 | E31: =Products!BE13 -> 79.893524 | F31: =IF(ISNUMBER(D31),E31-D31,"") -> 0.42352437 | G31: 0.258 | H31: =Products!BF13 -> 0.25924152 | I31: =IF(ISNUMBER(F31),IF(ABS(F31)<=3,"Yes","No"),"") -> Yes | J31: verify_gym_pets.md used A$5,964 per 20GP (vs A$211 × 28 = A$5,908 in the brief) and applied the 3% allowance to the A$5 handling. | K31: verify_gym_pets.md Q1
A32: 10 | B32: 2x40kg dial dumbbell pair | C32: 20GP (volume-limited), 215 pairs, A$379 | D32: 57.18 | E32: =Products!BE14 -> 57.600604 | F32: =IF(ISNUMBER(D32),E32-D32,"") -> 0.42060423 | G32: 0.166 | H32: =Products!BF14 -> 0.16717853 | I32: =IF(ISNUMBER(F32),IF(ABS(F32)<=3,"Yes","No"),"") -> Yes | J32: As SKU 9 (A$5,964 box and allowance on handling in the note). | K32: verify_gym_pets.md Q2
A33: 11 | B33: Kettlebell set 8/12/16kg | C33: 20GP (weight-capped), 581 sets, A$99 | D33: 9.6 | E33: =Products!BE15 -> 9.8493453 | F33: =IF(ISNUMBER(D33),E33-D33,"") -> 0.24934527 | G33: 0.107 | H33: =Products!BF15 -> 0.10943717 | I33: =IF(ISNUMBER(F33),IF(ABS(F33)<=3,"Yes","No"),"") -> Yes | J33: As SKU 9 (A$5,964 box and allowance on handling in the note). | K33: verify_gym_pets.md Q3
A34: 12 | B34: 48in steel dog crate | C34: 20GP (volume-limited), 288 crates, A$85 | D34: 7.16 | E34: =Products!BE16 -> 7.5118886 | F34: =IF(ISNUMBER(D34),E34-D34,"") -> 0.35188859 | G34: 0.093 | H34: =Products!BF16 -> 0.097212676 | I34: =IF(ISNUMBER(F34),IF(ABS(F34)<=3,"Yes","No"),"") -> Yes | J34: As SKU 9 (A$5,964 box and allowance on handling in the note). | K34: verify_gym_pets.md Q4
A35: 13 | B35: Wood/pellet pizza oven | C35: LCL, 200 units, A$125 | D35: 13.77 | E35: =Products!BE17 -> 13.771121 | F35: =IF(ISNUMBER(D35),E35-D35,"") -> 0.0011208598 | G35: 0.12 | H35: =Products!BF17 -> 0.12118586 | I35: =IF(ISNUMBER(F35),IF(ABS(F35)<=3,"Yes","No"),"") -> Yes | J35: Same method as the note (exact carton 0.077826 CBM). | K35: verify_outdoor.md Q1
A36: 14 | B36: Double hammock + steel stand | C36: LCL, 200 units, A$95 | D36: 28.58 | E36: =Products!BE18 -> 28.584148 | F36: =IF(ISNUMBER(D36),E36-D36,"") -> 0.0041478443 | G36: 0.33 | H36: =Products!BF18 -> 0.33097434 | I36: =IF(ISNUMBER(F36),IF(ABS(F36)<=3,"Yes","No"),"") -> Yes | J36: Same method as the note (exact carton 0.061248 CBM). | K36: verify_outdoor.md Q2
A37: 15 | B37: Foldable hanging egg chair | C37: 20GP, 196 units, A$159 | D37: 30.03 | E37: =Products!BE19 -> 30.026117 | F37: =IF(ISNUMBER(D37),E37-D37,"") -> -0.0038829086 | G37: 0.21 | H37: =Products!BF19 -> 0.20772785 | I37: =IF(ISNUMBER(F37),IF(ABS(F37)<=3,"Yes","No"),"") -> Yes | J37: Same method; carton entered as 0.1426 CBM (115×62×20 cm) so 196 chairs fit one 20GP as in the note (the note rounds to 0.143). | K37: verify_outdoor.md Q3
A38: 16 | B38: 4WD recovery kit | C38: LCL, 200 kits, A$119 | D38: 16.3 | E38: =Products!BE20 -> 16.29732 | F38: =IF(ISNUMBER(D38),E38-D38,"") -> -0.0026798055 | G38: 0.151 | H38: =Products!BF20 -> 0.1506475 | I38: =IF(ISNUMBER(F38),IF(ABS(F38)<=3,"Yes","No"),"") -> Yes | J38: Same method as the note (A$4,000 fixed compliance, US$1 labels, A$5 handling). | K38: verify_camping_appliance.md Q2–Q3
A39: 17 | B39: Alu camp kitchen + cupboards | C39: 20GP, 500 units, A$99 | D39: 28.32 | E39: =Products!BE21 -> 28.323806 | F39: =IF(ISNUMBER(D39),E39-D39,"") -> 0.0038063715 | G39: 0.315 | H39: =Products!BF21 -> 0.31470896 | I39: =IF(ISNUMBER(F39),IF(ABS(F39)<=3,"Yes","No"),"") -> Yes | J39: Same method as the note. | K39: verify_camping_appliance.md Q4
A40: 18 | B40: 2000W pressure washer | C40: LCL, 500 units, A$99 (Scenario A) | D40: 22.4 | E40: =Products!BE22 -> 22.401779 | F40: =IF(ISNUMBER(D40),E40-D40,"") -> 0.0017785934 | G40: 0.249 | H40: =Products!BF22 -> 0.24890865 | I40: =IF(ISNUMBER(F40),IF(ABS(F40)<=3,"Yes","No"),"") -> Yes | J40: Same method as the note (5% defect allowance for electricals). | K40: verify_camping_appliance.md Q5–Q6
A41: 19 | B41: Recovery kit + tracks bundle | C41: LCL, 100 bundles, A$179 | D41: =G41*Products!BD23 -> -1.6272727 | E41: =Products!BE23 -> -1.5547655 | F41: =IF(ISNUMBER(D41),E41-D41,"") -> 0.07250718 | G41: -0.01 | H41: =Products!BF23 -> -0.0095544252 | I41: =IF(ISNUMBER(F41),IF(ABS(F41)<=3,"Yes","No"),"") -> Yes | J41: Note gives GP % only (−1.0% at A$179, 100 bundles); the A$ comparison uses that % × net revenue. | K41: verify_camping_appliance.md Q2 & Q7
A42: Mix 1 | B42: Gym 20GP: 150 bumper + 70 dial pairs | C42: Total GP for the container (A$) – see Mixed container | D42: 15751 | E42: ='Mixed container'!N9 -> 15841.102 | F42: =E42-D42 -> 90.102412 | G42: 0.224 | H42: ='Mixed container'!O9 -> 0.22519014 | I42: =IF(ABS(F42)<=0.01*ABS(D42),"Yes (<1%)","No") -> Yes (<1%) | J42: verify_gym_pets.md priced the 20GP at A$5,964 (vs A$5,908) and applied the allowance to the A$5 handling (~A$0.40/unit × 220 units). | K42: verify_gym_pets.md Q5 (M4)
A43: Mix 2 | B43: Outdoor 40HQ: 250 ovens + 300 hammocks + 200 egg chairs | C43: Total GP for the container (A$) – see Mixed container | D43: 25119 | E43: ='Mixed container'!N28 -> 25118.587 | F43: =E43-D43 -> -0.4132867 | H43: ='Mixed container'!O28 -> 0.30180716 | I43: =IF(ABS(F43)<=0.01*ABS(D43),"Yes (<1%)","No") -> Yes (<1%) | J43: Same method: every line is volume-bound, so the chargeable-share allocation equals the note's A$151.68 per loaded CBM; consolidation A$800 per leg (estimate) included. | K43: verify_outdoor.md Q4
A45: Cash: as specified, the workbook shows cash = landed cost × quantity (which includes the defect allowance and 3 months' storage / handling) plus the import-GST float. The notes define cash differently – kids and furniture use landed × qty; gym uses the pre-allowance subtotal × qty; outdoor and camping use FOB + freight + inspection + compliance – so cash figures will not match the notes exactly even where GP does.
A46: GST float: the workbook uses GST × (FOB + duty + 60% of door-delivered freight), following verify_gym_pets.md; verify_outdoor.md used 10% × (FOB + freight). Recovery-kit total landed cost is not stated in its note, and the kit + tracks bundle's note gives GP % only. Notes GP % 'n/s' = not stated in the note.
A47: Not modelled (as in the notes): product-liability insurance (except the recovery kit's A$1,500), returns / warranty, China inland consolidation for single-SKU orders, FOB price-tier changes when you change quantity (overwrite FOB yourself), Facebook Marketplace sell-through.

Sheet Assumptions
A1: Assumptions – global inputs
A2: Blue cells are inputs. Base values are the shared base used by all five verify_*.md notes (data as at 9 Oct 2026), so results reconcile with the notes. Every formula in the workbook refers to these cells by name.
A4: Group | B4: Input | C4: Value | D4: Unit | E4: Source / note
A5: FX | B5: AUD/USD exchange rate (US$ per A$1) | C5: 0.6956 | D5: US$ per A$ | E5: RBA F11.1, 8 Oct 2026 (US$1 = A$1.4376) – the FX used in every verify note. Lower AUD/USD = dearer imports.
A6: FX | B6: US$1 in A$ (calculated) | C6: =1/FX_AUDUSD -> 1.4376078 | D6: A$ per US$ | E6: Converts FOB and US$ per-unit costs to A$.
A7: Freight | B7: 40HQ door-delivered rate | C7: 148 | D7: A$ per CBM | E7: Coordinator's shared base (all five verify notes), door-delivered and assumed to cover ocean, destination charges, broker, IPC/DAFF and delivery (verify_furniture.md). Not a forwarder quote.
A8: Freight | B8: 40HQ usable volume | C8: 68 | D8: CBM | E8: Shared base.
A9: Freight | B9: 40HQ cost per box (calculated) | C9: =RATE_40HQ*CBM_40HQ -> 10064 | D9: A$ per box | E9: A$10,064 at base. A part-filled box still costs the whole box (verify_kids.md).
A10: Freight | B10: 40HQ cargo weight cap | C10: 22000 | D10: kg | E10: Road limits vary by state (ICE Cargo guide): 40ft HC 22.5 t NSW / 22.0 t VIC / 20.0 t QLD-SA-WA-TAS. 22.0 t matches verify_furniture.md (571-desk, weight-limited 40HQ). Set your own state's limit.
A11: Freight | B11: 20GP door-delivered rate | C11: 211 | D11: A$ per CBM | E11: Shared base. Note: verify_gym_pets.md priced the 20GP at A$5,964 (≈A$213/CBM); the other notes use A$211 × 28 = A$5,908.
A12: Freight | B12: 20GP usable volume | C12: 28 | D12: CBM | E12: Shared base.
A13: Freight | B13: 20GP cost per box (calculated) | C13: =RATE_20GP*CBM_20GP -> 5908 | D13: A$ per box | E13: A$5,908 at base.
A14: Freight | B14: 20GP cargo weight cap | C14: 21800 | D14: kg | E14: 21.8 t = QLD/SA/WA/TAS limit (NSW 24.3 t, VIC 23.8 t) per ICE Cargo, as used in verify_gym_pets.md and verify_kids.md.
A15: Freight | B15: LCL rate | C15: 244 | D15: A$ per W/M | E15: Shared base. W/M = the greater of the shipment's CBM or tonnes.
A16: Freight | B16: LCL fixed charge | C16: 900 | D16: A$ per shipment | E16: Shared base; spread over the order quantity.
A17: Freight | B17: Other fixed costs per order not in the freight rate | C17: 0 | D17: A$ per order | E17: Optional (0 in all notes). The door rates above are all-in; add e.g. ABF IPC A$50 (<A$10k) / A$152 (≥A$10k) + DAFF FID charge A$71 if a forwarder quote excludes them.
A18: Duty | B18: General tariff rate (no Certificate of Origin) | C18: 0.05 | D18: % of FOB | E18: Most shortlisted lines are 5% general; some are Free (set per SKU on Products). Duty is charged on the FOB-based customs value (au_landed_cost_compliance.md §2).
A19: Duty | B19: ChAFTA preferential rate (with CoO) | C19: 0 | D19: % of FOB | E19: ChAFTA: tariffs eliminated since 1 Jan 2019, but only with a valid Certificate of Origin held at import (DFAT; ACN 2026/24).
A20: Duty | B20: ChAFTA Certificate of Origin held? | C20: Yes | D20: Yes / No | E20: Toggle. Yes = ChAFTA rate (0%); No = general rate on dutiable SKUs. Make the CoO a purchase-order term.
A21: Duty | B21: Duty rate applied to dutiable SKUs (calculated) | C21: =IF(COO_HELD="Yes",DUTY_CHAFTA,DUTY_GENERAL) -> 0 | D21: % of FOB | E21: Used by every SKU not marked duty-free at the general rate.
A22: Tax | B22: GST rate | C22: 0.1 | D22: % | E22: Net revenue = price ÷ (1 + GST). Assumes a GST-registered seller, so import GST is a reclaimable float, not a cost.
A23: Tax | B23: Share of door-delivered freight counted as transport & insurance for import GST | C23: 0.6 | D23: % of freight | E23: Import GST = 10% × (customs value + duty + international transport & insurance). Door rates include local charges, so only part counts; 60% is verify_gym_pets.md's estimate.
A24: Costs | B24: Pre-shipment inspection | C24: 400 | D24: A$ per factory per order | E24: Shared base.
A25: Costs | B25: Defect / damage allowance | C25: 0.03 | D25: % of subtotal | E25: Shared base: % of FOB + freight + duty + inspection + compliance + extras (before storage). verify_camping_appliance.md used 5% for the pressure washer (override per SKU on Products).
A26: Costs | B26: Storage rate | C26: 11 | D26: A$ per CBM per month | E26: Shared base.
A27: Costs | B27: Months held | C27: 3 | D27: months | E27: Shared base.
A28: Costs | B28: Storage per CBM over the holding period (calculated) | C28: =STORAGE_RATE*STORAGE_MONTHS -> 33 | D28: A$ per CBM | E28: A$33 per CBM at base; used by SKUs on the 'Per CBM' storage basis.
A29: Costs | B29: Flat handling charge (SKUs set to 'Flat') | C29: 5 | D29: A$ per unit | E29: Used instead of per-CBM storage by verify_gym_pets.md, verify_camping_appliance.md and for the high chair in verify_kids.md.
A30: Selling | B30: Facebook Marketplace selling fee | C30: 0 | D30: % of price | E30: 0% for local pickup. Shipped sales via checkout reportedly 10% (min $1) – not confirmed for Australia (au_landed_cost_compliance.md §8).
A31: Selling | B31: Target discount below price to beat | C31: 0.1 | D31: % | E31: Research pricing rule: sell 10–20% below the cheapest comparable new item. Drives the rule price and the 'discount below target' flag.
A32: Selling | B32: Pricing basis | C32: Manual | D32: Manual / Rule | E32: Manual = use each SKU's 'Target Marketplace price' (pre-filled with the verify notes' prices). Rule = price to beat × (1 − target discount).
A34: Reference only – landed-cost structure from au_landed_cost_compliance.md (not used in formulas: the door-delivered rates above are assumed to include these)
A35: Ocean freight | B35: China → Sydney/Melbourne/Brisbane FCL: 20ft USD 1,500–1,800, 40ft USD 2,900–3,600 (ExFreight, Jun 2026) plus ~USD 1,000/TEU of GRIs announced for Sept 2026 (KLN). LCL USD 60–280 per CBM. LCL and a 20ft cost about the same at ~14–15 CBM.
A36: Destination | B36: Maersk DHC from 1 Oct 2026: Sydney A$600 (20') / A$855 (40'). Terminal landside/infrastructure levies ~A$225–235 per box + vehicle booking ~A$50 + side-loader ~A$90–100. 20ft Sydney landside budget ≈ A$2,150–3,000 per box excluding ocean freight.
A37: Government | B37: ABF Import Processing Charge (electronic): A$50 for consignments A$1,000–<A$10,000; A$152 at A$10,000+. DAFF biosecurity charge on the Full Import Declaration: A$71 (sea) from 1 Jul 2026.
A38: Duty & GST | B38: Duty on the FOB-based customs value: general rate commonly 5% (some lines Free); ChAFTA 0% with a valid CoO. Import GST = 10% × (customs value + duty + transport & insurance); reclaimable for GST-registered importers.
A39: EESS (electrical) | B39: From 1 Jul 2026: Responsible Supplier registration A$239.74/yr; Level 2/3 equipment registration A$89.85 (1 yr). Level 3 items also need an AU/NZ Certificate of Conformity.
A40: Transit | B40: Port-to-port Shanghai/Ningbo → Sydney ~24–25 days (worst case 35–37); Qingdao 28–30 days (KLN, Sept 2026).
A41: Container limits | B41: ICE Cargo guide: 20ft GP 24.3 t NSW / 23.8 t VIC / 21.8 t QLD-SA-WA-TAS; 40ft HC 22.5 / 22.0 / 20.0 t.

Sheet Products
A1: Products – landed cost and Facebook Marketplace GP per verified SKU
A2: Blue cells are inputs: overwrite FOB, MOQ, carton CBM / kg and compliance costs as supplier quotes arrive, and pick the shipping mode and quantity. Black cells are formulas. Each row is pre-filled with the verify note's recommended first order (data as at 9 Oct 2026; FOBs are public listing prices, not quotes). A blank blue cell means the value is missing from the notes (see Flags).
A3: SKU & research verdict | H3: Price (A$ incl. GST) | O3: Supplier – overwrite as quotes arrive | R3: FOB & carton | Y3: Compliance & cost inputs | AG3: Order | AI3: Landed cost build-up (A$ per unit unless stated) | BD3: Results | BR3: Freight-mode check & flags | BW3: Notes from the verify files
A4: # | B4: Category | C4: SKU | D4: SKU spec | E4: Verdict (verify notes, 9 Oct 2026) | F4: Score – original | G4: Score – revised | H4: Price to beat (A$) | I4: Price-to-beat retailer / listing | J4: Price date / basis | K4: Target Marketplace price (A$, incl. GST) | L4: Rule price (A$) = price to beat × (1 − target discount) | M4: Sale price used (A$) | N4: Discount vs price to beat | O4: Supplier name | P4: Supplier type (as shown on listing) | Q4: Listing URL | R4: FOB as listed (US$) | S4: Listed per … (piece / pair / kg / set) | T4: Listed units per sellable unit (e.g. 2 pieces per pair) | U4: FOB per sellable unit (US$) | V4: MOQ (sellable units) | W4: Carton CBM per sellable unit | X4: Carton gross kg per sellable unit | Y4: First-order compliance / testing (A$ one-off per order) | Z4: Per-unit compliance / labels (A$ per unit) | AA4: Per-unit compliance / labels (US$ per unit) | AB4: Per-shipment extras, e.g. biosecurity (A$ per order) | AC4: Duty-free at the general rate? (Yes / No) | AD4: Storage basis (Per CBM / Flat) | AE4: Defect % override (blank = global) | AF4: Factories to inspect | AG4: Shipping mode (LCL / 20GP / 40HQ) | AH4: Order quantity (sellable units) | AI4: FOB (A$ per unit) | AJ4: Units per 20GP (lesser of volume / weight) | AK4: Units per 40HQ (lesser of volume / weight) | AL4: Units per container – selected mode | AM4: Containers needed | AN4: Box fill % (FCL) | AO4: Order CBM | AP4: Order tonnes | AQ4: Freight for the order (A$) | AR4: Freight (A$ per unit) | AS4: Freight if every box were full (A$/unit) = box cost ÷ units that fit | AT4: Duty rate applied | AU4: Duty (A$ per unit) | AV4: Inspection (A$ per unit) | AW4: Compliance (A$ per unit) | AX4: Per-shipment extras (A$ per unit) | AY4: Subtotal before allowances (A$ per unit) | AZ4: Defect % applied | BA4: Defect allowance (A$ per unit) | BB4: Storage / handling (A$ per unit) | BC4: Landed cost (A$ per unit, ex-GST) | BD4: Net revenue (A$ per unit) = price ÷ 1.1 | BE4: GP (A$ per unit) | BF4: GP % | BG4: Total GP for the order (A$) | BH4: Cash required ex-GST (A$) = landed × qty | BI4: Import-GST float (A$, reclaimable) | BJ4: Cash incl. GST float (A$) | BK4: Break-even FOB (US$ per sellable unit) | BL4: Break-even FOB (US$ per listed unit) | BM4: Break-even sale price (A$ incl. GST) | BN4: Fixed costs per order (A$) | BO4: Contribution per unit before fixed costs (A$) | BP4: Units to pay back fixed costs | BQ4: Units to sell to recover the cash outlay | BR4: Freight if LCL (A$) | BS4: Freight if 20GP (A$) | BT4: Freight if 40HQ (A$) | BU4: Cheapest mode at this qty | BV4: Flags | BW4: Why this verdict (verify notes) | BX4: FOB basis and price ladder | BY4: Carton data source | BZ4: Compliance and extras basis | CA4: Other price floors | CB4: Source note
A5: 1 | B5: Kids | C5: Trampoline 14ft + enclosure | D5: 14ft (4.27 m) round spring trampoline with safety enclosure; 150 kg max user; ships as one carton | E5: CONFIRMED | F5: 7 | G5: 7 | H5: 385.95 | I5: Amazon AU – Everfit 14FT trampoline (B08FWVCRG1), '3 offers from' | J5: 9 Oct 2026 (Best Sellers; delivery fee not visible) | K5: 349 | L5: =IF(H5>0,H5*(1-TARGET_DISC),"") -> 347.355 | M5: =IF(AND(PRICE_MODE="Rule",ISNUMBER(L5)),L5,K5) -> 349 | N5: =IF(AND(H5>0,M5>0),1-M5/H5,"") -> 0.09573779 | O5: Zhejiang Lingsha Technology (Funjump), Lishui | P5: Manufacturer & trading | Q5: https://lsfunjump.en.made-in-china.com/product/uphRrGWYIgci/China-Funjump-14FT-Outdoor-Indoor-Fitness-Kid-Child-Mini-Bungee-Jumping-Trampoline-with-Safety-Enclosure.html | R5: 96 | S5: per set (100–499 pcs tier) | T5: 1 | U5: =R5*T5 -> 96 | V5: 100 | W5: 0.2176 | X5: 62 | Y5: 2500 | Z5: 0 | AA5: 0 | AB5: 0 | AC5: No | AD5: Per CBM | AF5: 1 | AG5: 20GP | AH5: 128 | AI5: =U5*USD_TO_AUD -> 138.01035 | AJ5: =IF(W5>0,IF(X5>0,MIN(INT(CBM_20GP/W5+0.000001),INT(KG_20GP/X5+0.000001)),INT(CBM_20GP/W5+0.000001)),0) -> 128 | AK5: =IF(W5>0,IF(X5>0,MIN(INT(CBM_40HQ/W5+0.000001),INT(KG_40HQ/X5+0.000001)),INT(CBM_40HQ/W5+0.000001)),0) -> 312 | AL5: =IF(AG5="20GP",AJ5,IF(AG5="40HQ",AK5,"LCL")) -> 128 | AM5: =IF(AH5<=0,0,IF(AG5="20GP",IF(AJ5>0,ROUNDUP(AH5/AJ5,0),0),IF(AG5="40HQ",IF(AK5>0,ROUNDUP(AH5/AK5,0),0),0))) -> 1 | AN5: =IF(OR(AG5="LCL",AM5=0),"",AH5/(AM5*AL5)) -> 1 | AO5: =AH5*W5 -> 27.8528 | AP5: =AH5*X5/1000 -> 7.936 | AQ5: =IF(AH5<=0,0,IF(AG5="LCL",LCL_RATE*MAX(AO5,AP5)+LCL_FIXED,AM5*IF(AG5="20GP",COST_20GP,COST_40HQ))) -> 5908 | AR5: =IF(AH5>0,AQ5/AH5,0) -> 46.15625 | AS5: =IF(AG5="20GP",IF(AJ5>0,COST_20GP/AJ5,0),IF(AG5="40HQ",IF(AK5>0,COST_40HQ/AK5,0),AR5)) -> 46.15625 | AT5: =IF(AC5="Yes",0,DUTY_APPLIED) -> 0 | AU5: =AI5*AT5 -> 0 | AV5: =IF(AH5>0,INSPECTION*AF5/AH5,0) -> 3.125 | AW5: =IF(AH5>0,Y5/AH5,0)+Z5+AA5*USD_TO_AUD -> 19.53125 | AX5: =IF(AH5>0,(AB5+OTHER_FIXED)/AH5,0) -> 0 | AY5: =AI5+AR5+AU5+AV5+AW5+AX5 -> 206.82285 | AZ5: =IF(ISNUMBER(AE5),AE5,DEFECT_PCT) -> 0.03 | BA5: =AY5*AZ5 -> 6.2046855 | BB5: =IF(AD5="Flat",HANDLING_FLAT,STORAGE_PER_CBM*W5) -> 7.1808 | BC5: =AY5+BA5+BB5 -> 220.20834 | BD5: =M5/(1+GST_RATE)*(1-MP_FEE) -> 317.27273 | BE5: =BD5-BC5 -> 97.064391 | BF5: =IF(BD5<>0,BE5/BD5,0) -> 0.30593361 | BG5: =BE5*AH5 -> 12424.242 | BH5: =BC5*AH5 -> 28186.667 | BI5: =GST_RATE*(AI5+AU5+GST_TI_SHARE*AR5)*AH5 -> 2121.0125 | BJ5: =BH5+BI5 -> 30307.68 | BK5: =((BD5-BB5)/(1+AZ5)-(AR5+AV5+AW5+AX5))/(1+AT5)*FX_AUDUSD -> 161.55145 | BL5: =IF(T5>0,BK5/T5,0) -> 161.55145 | BM5: =BC5*(1+GST_RATE)/(1-MP_FEE) -> 242.22917 | BN5: =IF(AH5<=0,0,INSPECTION*AF5+Y5+AB5+OTHER_FIXED+IF(AG5="LCL",LCL_FIXED,AQ5)) -> 8808 | BO5: =BD5-((AI5+AU5+Z5+AA5*USD_TO_AUD+IF(AND(AG5="LCL",AH5>0),LCL_RATE*MAX(AO5,AP5)/AH5,0))*(1+AZ5)+BB5) -> 167.94127 | BP5: =IF(AH5<=0,"",IF(BO5>0,ROUNDUP(BN5*(1+AZ5)/BO5,0),"Never")) -> 55 | BQ5: =IF(AH5<=0,"",IF(BD5>0,ROUNDUP(BH5/BD5,0),"Never")) -> 89 | BR5: =IF(AH5>0,LCL_RATE*MAX(AO5,AP5)+LCL_FIXED,0) -> 7696.0832 | BS5: =IF(AND(AH5>0,AJ5>0),ROUNDUP(AH5/AJ5,0)*COST_20GP,0) -> 5908 | BT5: =IF(AND(AH5>0,AK5>0),ROUNDUP(AH5/AK5,0)*COST_40HQ,0) -> 10064 | BU5: =IF(AH5<=0,"",IF(BR5<=MIN(BS5,BT5),"LCL",IF(BS5<=BT5,"20GP","40HQ"))) -> 20GP | BV5: =TRIM(IF(AH5<V5,"Below MOQ. ","")&IF(AM5>1,"Needs "&AM5&" containers. ","")&IF(ISNUMBER(AN5),IF(AN5<0.85,"Box only "&TEXT(AN5,"0%")&" full – whole box charged. ",""),"")&IF(AND(BU5<>"",BU5<>AG5),"Cheaper freight at this qty: "&BU5&". ","")&IF(ISNUMBER(N5),IF(N5<0,"Price above price to beat. ",IF(N5<TARGET_DISC-0.0005,"Discount below target. ","")),"")&IF(U5<=0,"FOB missing. ","")&IF(N(X5)=0,"Carton kg missing. ","")&IF(BE5<0,"Loss-making. ","")&IF(ISNUMBER(BQ5),IF(BQ5>AH5,"Cash not recovered even if all units sell. ",""),"")) -> Discount below target. | BW5: Margin holds at 20GP scale: A$349 is 9.6% below Amazon's cheapest 14ft (marginally outside the 10–20% band; A$339 keeps it inside) and is the cheapest per m² of mat. Kmart's 12ft A$299 / 10ft A$199 anchor the low end; Nov–Dec seasonal; needs an AS 4989 / EN 71-14 test plus liability cover. | BX5: Lingsha 14FT ladder US$96 (100–499) / US$93 (500–999) / US$89 (1,000+); FAQ: MOQ 50 per size, a 20GP can mix 3–4 sizes. Alt: Yongkang Nanjian 14FT US$79–129 (MOQ 100, 59 kg); Beijing Set Sail US$119 (probable trader). | BY5: 172×55×23 cm = 0.2176 CBM, 62 kg gross (Lingsha packing table, cited). | BZ5: AS 4989 / EN 71-14 test of the exact build A$2,500 one-off (ESTIMATE – no lab quote). No mandatory standard. HS 9506.91: 5% general, Free with a ChAFTA CoO. | CA5: Toys"R"Us Bestway 14ft A$443.99; Kmart 12ft springless A$299 (snippet); Amazon delivery on big trampolines ~A$120 (OzBargain). | CB5: verify_kids.md Q1
A6: 2 | B6: Kids | C6: Kids 24V 2-seat UTV | D6: 24V 2-seat ride-on UTV with parental remote; lead-acid 24V 7Ah; 4 × 555 motors (Zhehua 110-E1) | E6: BROKEN | F6: 6 | G6: 3 | H6: 339.95 | I6: Amazon AU – HONEY JOY 24V 2-seater ride-on truck with remote (B0HJ1KPG9Q), '1 offer from' | J6: 9 Oct 2026 (carousel price; delivery not visible) | K6: 299 | L6: =IF(H6>0,H6*(1-TARGET_DISC),"") -> 305.955 | M6: =IF(AND(PRICE_MODE="Rule",ISNUMBER(L6)),L6,K6) -> 299 | N6: =IF(AND(H6>0,M6>0),1-M6/H6,"") -> 0.12045889 | O6: Shenzhen Zhehua Technology | P6: Unknown – not stated (office address; probable trader) | Q6: https://zhehuatoys.en.made-in-china.com/product/ZYnrUyqDrdWv/China-24V-Electric-Kids-Car-UTV-2-Seats-Children-Battery-Ride-on-Car.html | R6: 117 | S6: per unit (20–269 tier) | T6: 1 | U6: =R6*T6 -> 117 | V6: 20 | W6: 0.2557 | X6: 31 | Y6: 4129.59 | Z6: 0 | AA6: 0 | AB6: 0 | AC6: Yes | AD6: Per CBM | AF6: 1 | AG6: 20GP | AH6: 98 | AI6: =U6*USD_TO_AUD -> 168.20012 | AJ6: =IF(W6>0,IF(X6>0,MIN(INT(CBM_20GP/W6+0.000001),INT(KG_20GP/X6+0.000001)),INT(CBM_20GP/W6+0.000001)),0) -> 109 | AK6: =IF(W6>0,IF(X6>0,MIN(INT(CBM_40HQ/W6+0.000001),INT(KG_40HQ/X6+0.000001)),INT(CBM_40HQ/W6+0.000001)),0) -> 265 | AL6: =IF(AG6="20GP",AJ6,IF(AG6="40HQ",AK6,"LCL")) -> 109 | AM6: =IF(AH6<=0,0,IF(AG6="20GP",IF(AJ6>0,ROUNDUP(AH6/AJ6,0),0),IF(AG6="40HQ",IF(AK6>0,ROUNDUP(AH6/AK6,0),0),0))) -> 1 | AN6: =IF(OR(AG6="LCL",AM6=0),"",AH6/(AM6*AL6)) -> 0.89908257 | AO6: =AH6*W6 -> 25.0586 | AP6: =AH6*X6/1000 -> 3.038 | AQ6: =IF(AH6<=0,0,IF(AG6="LCL",LCL_RATE*MAX(AO6,AP6)+LCL_FIXED,AM6*IF(AG6="20GP",COST_20GP,COST_40HQ))) -> 5908 | AR6: =IF(AH6>0,AQ6/AH6,0) -> 60.285714 | AS6: =IF(AG6="20GP",IF(AJ6>0,COST_20GP/AJ6,0),IF(AG6="40HQ",IF(AK6>0,COST_40HQ/AK6,0),AR6)) -> 54.201835 | AT6: =IF(AC6="Yes",0,DUTY_APPLIED) -> 0 | AU6: =AI6*AT6 -> 0 | AV6: =IF(AH6>0,INSPECTION*AF6/AH6,0) -> 4.0816327 | AW6: =IF(AH6>0,Y6/AH6,0)+Z6+AA6*USD_TO_AUD -> 42.138673 | AX6: =IF(AH6>0,(AB6+OTHER_FIXED)/AH6,0) -> 0 | AY6: =AI6+AR6+AU6+AV6+AW6+AX6 -> 274.70614 | AZ6: =IF(ISNUMBER(AE6),AE6,DEFECT_PCT) -> 0.03 | BA6: =AY6*AZ6 -> 8.2411841 | BB6: =IF(AD6="Flat",HANDLING_FLAT,STORAGE_PER_CBM*W6) -> 8.4381 | BC6: =AY6+BA6+BB6 -> 291.38542 | BD6: =M6/(1+GST_RATE)*(1-MP_FEE) -> 271.81818 | BE6: =BD6-BC6 -> -19.567238 | BF6: =IF(BD6<>0,BE6/BD6,0) -> -0.071986493 | BG6: =BE6*AH6 -> -1917.5893 | BH6: =BC6*AH6 -> 28555.771 | BI6: =GST_RATE*(AI6+AU6+GST_TI_SHARE*AR6)*AH6 -> 2002.8411 | BJ6: =BH6+BI6 -> 30558.612 | BK6: =((BD6-BB6)/(1+AZ6)-(AR6+AV6+AW6+AX6))/(1+AT6)*FX_AUDUSD -> 103.78547 | BL6: =IF(T6>0,BK6/T6,0) -> 103.78547 | BM6: =BC6*(1+GST_RATE)/(1-MP_FEE) -> 320.52396 | BN6: =IF(AH6<=0,0,INSPECTION*AF6+Y6+AB6+OTHER_FIXED+IF(AG6="LCL",LCL_FIXED,AQ6)) -> 10437.59 | BO6: =BD6-((AI6+AU6+Z6+AA6*USD_TO_AUD+IF(AND(AG6="LCL",AH6>0),LCL_RATE*MAX(AO6,AP6)/AH6,0))*(1+AZ6)+BB6) -> 90.133963 | BP6: =IF(AH6<=0,"",IF(BO6>0,ROUNDUP(BN6*(1+AZ6)/BO6,0),"Never")) -> 120 | BQ6: =IF(AH6<=0,"",IF(BD6>0,ROUNDUP(BH6/BD6,0),"Never")) -> 106 | BR6: =IF(AH6>0,LCL_RATE*MAX(AO6,AP6)+LCL_FIXED,0) -> 7014.2984 | BS6: =IF(AND(AH6>0,AJ6>0),ROUNDUP(AH6/AJ6,0)*COST_20GP,0) -> 5908 | BT6: =IF(AND(AH6>0,AK6>0),ROUNDUP(AH6/AK6,0)*COST_40HQ,0) -> 10064 | BU6: =IF(AH6<=0,"",IF(BR6<=MIN(BS6,BT6),"LCL",IF(BS6<=BT6,"20GP","40HQ"))) -> 20GP | BV6: =TRIM(IF(AH6<V6,"Below MOQ. ","")&IF(AM6>1,"Needs "&AM6&" containers. ","")&IF(ISNUMBER(AN6),IF(AN6<0.85,"Box only "&TEXT(AN6,"0%")&" full – whole box charged. ",""),"")&IF(AND(BU6<>"",BU6<>AG6),"Cheaper freight at this qty: "&BU6&". ","")&IF(ISNUMBER(N6),IF(N6<0,"Price above price to beat. ",IF(N6<TARGET_DISC-0.0005,"Discount below target. ","")),"")&IF(U6<=0,"FOB missing. ","")&IF(N(X6)=0,"Carton kg missing. ","")&IF(BE6<0,"Loss-making. ","")&IF(ISNUMBER(BQ6),IF(BQ6>AH6,"Cash not recovered even if all units sell. ",""),"")) -> Loss-making. Cash not recovered even if all units sell. | BW6: Amazon already sells a 24V 2-seater with remote at A$339.95, so the 10–20% rule caps price at ~A$272–306. At A$299 the first 20GP order loses ~A$20/unit; only a full 40HQ makes ~12%. Genuine Hebei/Jiaxing makers (US$150–178, bigger cartons) lose money at any price up to A$349. | BX6: Zhehua 110-E1 US$117 (20–269) / US$109 (270+). Genuine makers: Hebei Boyi BY-MG2039 US$150 (0.398 CBM), Pinghu United A032 US$178 (0.50 CBM). | BY6: 111×64×36 cm = 0.2557 CBM, 31 kg gross (cited). Supplier states 98 per 20ft / 270 per 40HQ; the volume formula allows 109 per 20GP. | BZ6: A$4,129.59 one-off = toy / electric-toy / EN62115-type testing A$3,000 (EST) + EESS Responsible Supplier A$239.74 + Level 3 charger registration A$89.85 + charger CoC A$800 (EST). HS 9503.00.10 Free at the general rate. Button-battery remote rules; SP 238 SLA battery statement. | CA6: HONEY JOY 24V 2-seat quad A$309.95; HONEY JOY 24V dump truck A$399.95; ANPABO 24V 4WD A$469.99. | CB6: verify_kids.md Q2
A7: 3 | B7: Kids | C7: Timber cubby house | D7: Chinese-fir cubby / cabin with pretend kitchen sink, 107.5×113.5×145.5 cm (Zhongran model 91024) | E7: REVISED | F7: 6 | G7: 5 | H7: 349.97 | I7: Kmart Marketplace – AUSWAY timber cubby 123×106×125 cm (Amazon AU floor not observable) | J7: Undated search snippet (Kmart returned 403) | K7: 299 | L7: =IF(H7>0,H7*(1-TARGET_DISC),"") -> 314.973 | M7: =IF(AND(PRICE_MODE="Rule",ISNUMBER(L7)),L7,K7) -> 299 | N7: =IF(AND(H7>0,M7>0),1-M7/H7,"") -> 0.14564105 | O7: Heze Zhongran Woodware (Shandong) | P7: Manufacturer & trading (self-described) | Q7: https://chinakidstoy.en.made-in-china.com/product/EGLUuvndOCYI/China-Backyard-Garden-Wooden-Kids-Play-Cabin-Children-Outdoor-Playhouse-with-Pretend-Kitchen-Sink-for-Home-Yard-Game.html | R7: 106.12 | S7: per set (MOQ 300 sets) | T7: 1 | U7: =R7*T7 -> 106.12 | V7: 300 | W7: 0.1733 | X7: 31.3 | Y7: 1000 | Z7: 0 | AA7: 0 | AB7: 500 | AC7: No | AD7: Per CBM | AF7: 1 | AG7: 40HQ | AH7: 300 | AI7: =U7*USD_TO_AUD -> 152.55894 | AJ7: =IF(W7>0,IF(X7>0,MIN(INT(CBM_20GP/W7+0.000001),INT(KG_20GP/X7+0.000001)),INT(CBM_20GP/W7+0.000001)),0) -> 161 | AK7: =IF(W7>0,IF(X7>0,MIN(INT(CBM_40HQ/W7+0.000001),INT(KG_40HQ/X7+0.000001)),INT(CBM_40HQ/W7+0.000001)),0) -> 392 | AL7: =IF(AG7="20GP",AJ7,IF(AG7="40HQ",AK7,"LCL")) -> 392 | AM7: =IF(AH7<=0,0,IF(AG7="20GP",IF(AJ7>0,ROUNDUP(AH7/AJ7,0),0),IF(AG7="40HQ",IF(AK7>0,ROUNDUP(AH7/AK7,0),0),0))) -> 1 | AN7: =IF(OR(AG7="LCL",AM7=0),"",AH7/(AM7*AL7)) -> 0.76530612 | AO7: =AH7*W7 -> 51.99 | AP7: =AH7*X7/1000 -> 9.39 | AQ7: =IF(AH7<=0,0,IF(AG7="LCL",LCL_RATE*MAX(AO7,AP7)+LCL_FIXED,AM7*IF(AG7="20GP",COST_20GP,COST_40HQ))) -> 10064 | AR7: =IF(AH7>0,AQ7/AH7,0) -> 33.546667 | AS7: =IF(AG7="20GP",IF(AJ7>0,COST_20GP/AJ7,0),IF(AG7="40HQ",IF(AK7>0,COST_40HQ/AK7,0),AR7)) -> 25.673469 | AT7: =IF(AC7="Yes",0,DUTY_APPLIED) -> 0 | AU7: =AI7*AT7 -> 0 | AV7: =IF(AH7>0,INSPECTION*AF7/AH7,0) -> 1.3333333 | AW7: =IF(AH7>0,Y7/AH7,0)+Z7+AA7*USD_TO_AUD -> 3.3333333 | AX7: =IF(AH7>0,(AB7+OTHER_FIXED)/AH7,0) -> 1.6666667 | AY7: =AI7+AR7+AU7+AV7+AW7+AX7 -> 192.43894 | AZ7: =IF(ISNUMBER(AE7),AE7,DEFECT_PCT) -> 0.03 | BA7: =AY7*AZ7 -> 5.7731683 | BB7: =IF(AD7="Flat",HANDLING_FLAT,STORAGE_PER_CBM*W7) -> 5.7189 | BC7: =AY7+BA7+BB7 -> 203.93101 | BD7: =M7/(1+GST_RATE)*(1-MP_FEE) -> 271.81818 | BE7: =BD7-BC7 -> 67.887172 | BF7: =IF(BD7<>0,BE7/BD7,0) -> 0.24975214 | BG7: =BE7*AH7 -> 20366.151 | BH7: =BC7*AH7 -> 61179.303 | BI7: =GST_RATE*(AI7+AU7+GST_TI_SHARE*AR7)*AH7 -> 5180.6083 | BJ7: =BH7+BI7 -> 66359.911 | BK7: =((BD7-BB7)/(1+AZ7)-(AR7+AV7+AW7+AX7))/(1+AT7)*FX_AUDUSD -> 151.96691 | BL7: =IF(T7>0,BK7/T7,0) -> 151.96691 | BM7: =BC7*(1+GST_RATE)/(1-MP_FEE) -> 224.32411 | BN7: =IF(AH7<=0,0,INSPECTION*AF7+Y7+AB7+OTHER_FIXED+IF(AG7="LCL",LCL_FIXED,AQ7)) -> 11964 | BO7: =BD7-((AI7+AU7+Z7+AA7*USD_TO_AUD+IF(AND(AG7="LCL",AH7>0),LCL_RATE*MAX(AO7,AP7)/AH7,0))*(1+AZ7)+BB7) -> 108.96357 | BP7: =IF(AH7<=0,"",IF(BO7>0,ROUNDUP(BN7*(1+AZ7)/BO7,0),"Never")) -> 114 | BQ7: =IF(AH7<=0,"",IF(BD7>0,ROUNDUP(BH7/BD7,0),"Never")) -> 226 | BR7: =IF(AH7>0,LCL_RATE*MAX(AO7,AP7)+LCL_FIXED,0) -> 13585.56 | BS7: =IF(AND(AH7>0,AJ7>0),ROUNDUP(AH7/AJ7,0)*COST_20GP,0) -> 11816 | BT7: =IF(AND(AH7>0,AK7>0),ROUNDUP(AH7/AK7,0)*COST_40HQ,0) -> 10064 | BU7: =IF(AH7<=0,"",IF(BR7<=MIN(BS7,BT7),"LCL",IF(BS7<=BT7,"20GP","40HQ"))) -> 40HQ | BV7: =TRIM(IF(AH7<V7,"Below MOQ. ","")&IF(AM7>1,"Needs "&AM7&" containers. ","")&IF(ISNUMBER(AN7),IF(AN7<0.85,"Box only "&TEXT(AN7,"0%")&" full – whole box charged. ",""),"")&IF(AND(BU7<>"",BU7<>AG7),"Cheaper freight at this qty: "&BU7&". ","")&IF(ISNUMBER(N7),IF(N7<0,"Price above price to beat. ",IF(N7<TARGET_DISC-0.0005,"Discount below target. ","")),"")&IF(U7<=0,"FOB missing. ","")&IF(N(X7)=0,"Carton kg missing. ","")&IF(BE7<0,"Loss-making. ","")&IF(ISNUMBER(BQ7),IF(BQ7>AH7,"Cash not recovered even if all units sell. ",""),"")) -> Box only 77% full – whole box charged. | BW7: A$299 is ~15% under Kmart Marketplace's A$349.97–399 timber cubbies, but Kmart's own Activo cubby has a A$169 RRP (seen at A$99 clearance). Zhongran's MOQ 300 forces a ~40HQ first order (~A$61k cash); needs a timber treatment certificate and storage declaration. | BX7: Zhongran 91024 US$106.12, MOQ 300 (its other playhouses US$87–325). Alt: Ningbo Dreamgo playhouse US$103.88 (50–499) / US$86.57 (500+), 0.134 CBM, 24 kg → 200 units in a 20GP: GP A$73.36 (27.0%) per the notes. | BY7: 103×51×33 cm = 0.1733 CBM, 31.3 kg gross (cited). | BZ7: Optional EN71-3 coating + sharp-edge check A$1,000 one-off (EST). Biosecurity A$500 per shipment (EST): offshore heat/fumigation certificate, storage declaration, inspection contingency. 5% general / Free with CoO. | CA7: Kmart Marketplace Rovo A$399; Kmart own Activo cubby RRP A$169; Bunnings Sweetwater cedar A$549; Lifespan cubbies A$629.99+. | CB7: verify_kids.md Q3
A8: 4 | B8: Kids | C8: 3-in-1 high chair | D8: 3-in-1 convertible high chair (plastic): high chair / booster / toddler chair | E8: BROKEN | F8: 5 | G8: 2 | H8: 89.95 | I8: Amazon AU – BABY JOY 5-in-1 convertible highchair (B0H8CNJ56Q); cheapest convertible A$55.95 | J8: 9 Oct 2026 (Best Sellers; delivery not visible) | K8: 79 | L8: =IF(H8>0,H8*(1-TARGET_DISC),"") -> 80.955 | M8: =IF(AND(PRICE_MODE="Rule",ISNUMBER(L8)),L8,K8) -> 79 | N8: =IF(AND(H8>0,M8>0),1-M8/H8,"") -> 0.1217343 | O8: Hebei Biwei Import & Export Trade | P8: Trading company | Q8: https://hebeibiwei.en.made-in-china.com/product/zUdYeEiPEZcF/China-3-in-1-Baby-Dining-Chair-Multi-Functional-Portable-Baby-High-Chair-Adjustable-Baby-Infant-Dining-Seat-Eating-Feeding-Chair.html | R8: 33.8 | S8: per unit (50–499 tier) | T8: 1 | U8: =R8*T8 -> 33.8 | V8: 50 | W8: 0.0906 | Y8: 2000 | Z8: 0 | AA8: 0 | AB8: 0 | AC8: No | AD8: Flat | AF8: 1 | AG8: LCL | AH8: 150 | AI8: =U8*USD_TO_AUD -> 48.591144 | AJ8: =IF(W8>0,IF(X8>0,MIN(INT(CBM_20GP/W8+0.000001),INT(KG_20GP/X8+0.000001)),INT(CBM_20GP/W8+0.000001)),0) -> 309 | AK8: =IF(W8>0,IF(X8>0,MIN(INT(CBM_40HQ/W8+0.000001),INT(KG_40HQ/X8+0.000001)),INT(CBM_40HQ/W8+0.000001)),0) -> 750 | AL8: =IF(AG8="20GP",AJ8,IF(AG8="40HQ",AK8,"LCL")) -> LCL | AM8: =IF(AH8<=0,0,IF(AG8="20GP",IF(AJ8>0,ROUNDUP(AH8/AJ8,0),0),IF(AG8="40HQ",IF(AK8>0,ROUNDUP(AH8/AK8,0),0),0))) -> 0 | AN8: =IF(OR(AG8="LCL",AM8=0),"",AH8/(AM8*AL8)) | AO8: =AH8*W8 -> 13.59 | AP8: =AH8*X8/1000 -> 0 | AQ8: =IF(AH8<=0,0,IF(AG8="LCL",LCL_RATE*MAX(AO8,AP8)+LCL_FIXED,AM8*IF(AG8="20GP",COST_20GP,COST_40HQ))) -> 4215.96 | AR8: =IF(AH8>0,AQ8/AH8,0) -> 28.1064 | AS8: =IF(AG8="20GP",IF(AJ8>0,COST_20GP/AJ8,0),IF(AG8="40HQ",IF(AK8>0,COST_40HQ/AK8,0),AR8)) -> 28.1064 | AT8: =IF(AC8="Yes",0,DUTY_APPLIED) -> 0 | AU8: =AI8*AT8 -> 0 | AV8: =IF(AH8>0,INSPECTION*AF8/AH8,0) -> 2.6666667 | AW8: =IF(AH8>0,Y8/AH8,0)+Z8+AA8*USD_TO_AUD -> 13.333333 | AX8: =IF(AH8>0,(AB8+OTHER_FIXED)/AH8,0) -> 0 | AY8: =AI8+AR8+AU8+AV8+AW8+AX8 -> 92.697544 | AZ8: =IF(ISNUMBER(AE8),AE8,DEFECT_PCT) -> 0.03 | BA8: =AY8*AZ8 -> 2.7809263 | BB8: =IF(AD8="Flat",HANDLING_FLAT,STORAGE_PER_CBM*W8) -> 5 | BC8: =AY8+BA8+BB8 -> 100.47847 | BD8: =M8/(1+GST_RATE)*(1-MP_FEE) -> 71.818182 | BE8: =BD8-BC8 -> -28.660289 | BF8: =IF(BD8<>0,BE8/BD8,0) -> -0.39906731 | BG8: =BE8*AH8 -> -4299.0433 | BH8: =BC8*AH8 -> 15071.771 | BI8: =GST_RATE*(AI8+AU8+GST_TI_SHARE*AR8)*AH8 -> 981.82477 | BJ8: =BH8+BI8 -> 16053.595 | BK8: =((BD8-BB8)/(1+AZ8)-(AR8+AV8+AW8+AX8))/(1+AT8)*FX_AUDUSD -> 14.444566 | BL8: =IF(T8>0,BK8/T8,0) -> 14.444566 | BM8: =BC8*(1+GST_RATE)/(1-MP_FEE) -> 110.52632 | BN8: =IF(AH8<=0,0,INSPECTION*AF8+Y8+AB8+OTHER_FIXED+IF(AG8="LCL",LCL_FIXED,AQ8)) -> 3300 | BO8: =BD8-((AI8+AU8+Z8+AA8*USD_TO_AUD+IF(AND(AG8="LCL",AH8>0),LCL_RATE*MAX(AO8,AP8)/AH8,0))*(1+AZ8)+BB8) -> -6.0002888 | BP8: =IF(AH8<=0,"",IF(BO8>0,ROUNDUP(BN8*(1+AZ8)/BO8,0),"Never")) -> Never | BQ8: =IF(AH8<=0,"",IF(BD8>0,ROUNDUP(BH8/BD8,0),"Never")) -> 210 | BR8: =IF(AH8>0,LCL_RATE*MAX(AO8,AP8)+LCL_FIXED,0) -> 4215.96 | BS8: =IF(AND(AH8>0,AJ8>0),ROUNDUP(AH8/AJ8,0)*COST_20GP,0) -> 5908 | BT8: =IF(AND(AH8>0,AK8>0),ROUNDUP(AH8/AK8,0)*COST_40HQ,0) -> 10064 | BU8: =IF(AH8<=0,"",IF(BR8<=MIN(BS8,BT8),"LCL",IF(BS8<=BT8,"20GP","40HQ"))) -> LCL | BV8: =TRIM(IF(AH8<V8,"Below MOQ. ","")&IF(AM8>1,"Needs "&AM8&" containers. ","")&IF(ISNUMBER(AN8),IF(AN8<0.85,"Box only "&TEXT(AN8,"0%")&" full – whole box charged. ",""),"")&IF(AND(BU8<>"",BU8<>AG8),"Cheaper freight at this qty: "&BU8&". ","")&IF(ISNUMBER(N8),IF(N8<0,"Price above price to beat. ",IF(N8<TARGET_DISC-0.0005,"Discount below target. ","")),"")&IF(U8<=0,"FOB missing. ","")&IF(N(X8)=0,"Carton kg missing. ","")&IF(BE8<0,"Loss-making. ","")&IF(ISNUMBER(BQ8),IF(BQ8>AH8,"Cash not recovered even if all units sell. ",""),"")) -> Carton kg missing. Loss-making. Cash not recovered even if all units sell. | BW8: Amazon has a dense floor of convertible chairs at A$55.95–89.95 and Kmart Group's Anko sells A$45–149, so the rule price is ~A$79. Landed cost is A$70–100/unit, so a first order loses ~A$29/unit and even a full 40HQ only breaks even. | BX8: Biwei US$33.80 (50–499) / US$32.80 (500–1,199) / US$31.30 (1,200–4,999) / US$30.00 (5,000+). Alt: Ningbo Jiangbei Ringlong US$38.99–40.00, MOQ 500. | BY8: Biwei carton not captured: CBM assumed = Ringlong carton 64×29.5×48 cm (0.0906 CBM), as in the verify note. Carton kg MISSING – left blank (Ringlong's carton is 8 kg). | BZ8: Voluntary AS 4684 / EN 14988 test A$2,000 one-off (EST). Flat A$5 handling (compact item). Infant Products Information Standard warnings apply if the seat reclines or is marketed under 12 months. 5% general. | CA8: BABY JOY 4-in-1 A$55.95; generic 3-in-1 A$79.99; BABY JOY 3-in-1 wooden A$82.95; Target Anko A$45–149. | CB8: verify_kids.md Q4
A9: 5 | B9: Furniture | C9: Dual-motor standing desk | D9: Dual-motor electric sit-stand desk: 3-stage frame (120 kg) + ~140×70 cm top | E9: REVISED | F9: 7 | G9: 6 | H9: 319.9 | I9: Advwin (brand-direct) dual-motor 140×60 desk; Amazon AU cheapest complete dual-motor A$439.99 (FLEXISPOT E3) | J9: 9 Oct 2026 (+ postcode-based delivery) | K9: 299 | L9: =IF(H9>0,H9*(1-TARGET_DISC),"") -> 287.91 | M9: =IF(AND(PRICE_MODE="Rule",ISNUMBER(L9)),L9,K9) -> 299 | N9: =IF(AND(H9>0,M9>0),1-M9/H9,"") -> 0.065332917 | O9: Zhejiang Prorials Advanced Materials (frame) | P9: Manufacturer & trading | Q9: https://chinapurui.en.made-in-china.com/product/JRbUSIKobqVf/China-Fast-Lift-Dual-Motor-Electric-Height-Adjustable-Standing-Office-Desk-Frame.html | R9: 100 | S9: per complete desk (frame US$76 listed + top US$24 est.) | T9: 1 | U9: =R9*T9 -> 100 | V9: 100 | W9: 0.102 | X9: 38.5 | Y9: 3329.59 | Z9: 0 | AA9: 0 | AB9: 0 | AC9: No | AD9: Per CBM | AF9: 1 | AG9: LCL | AH9: 100 | AI9: =U9*USD_TO_AUD -> 143.76078 | AJ9: =IF(W9>0,IF(X9>0,MIN(INT(CBM_20GP/W9+0.000001),INT(KG_20GP/X9+0.000001)),INT(CBM_20GP/W9+0.000001)),0) -> 274 | AK9: =IF(W9>0,IF(X9>0,MIN(INT(CBM_40HQ/W9+0.000001),INT(KG_40HQ/X9+0.000001)),INT(CBM_40HQ/W9+0.000001)),0) -> 571 | AL9: =IF(AG9="20GP",AJ9,IF(AG9="40HQ",AK9,"LCL")) -> LCL | AM9: =IF(AH9<=0,0,IF(AG9="20GP",IF(AJ9>0,ROUNDUP(AH9/AJ9,0),0),IF(AG9="40HQ",IF(AK9>0,ROUNDUP(AH9/AK9,0),0),0))) -> 0 | AN9: =IF(OR(AG9="LCL",AM9=0),"",AH9/(AM9*AL9)) | AO9: =AH9*W9 -> 10.2 | AP9: =AH9*X9/1000 -> 3.85 | AQ9: =IF(AH9<=0,0,IF(AG9="LCL",LCL_RATE*MAX(AO9,AP9)+LCL_FIXED,AM9*IF(AG9="20GP",COST_20GP,COST_40HQ))) -> 3388.8 | AR9: =IF(AH9>0,AQ9/AH9,0) -> 33.888 | AS9: =IF(AG9="20GP",IF(AJ9>0,COST_20GP/AJ9,0),IF(AG9="40HQ",IF(AK9>0,COST_40HQ/AK9,0),AR9)) -> 33.888 | AT9: =IF(AC9="Yes",0,DUTY_APPLIED) -> 0 | AU9: =AI9*AT9 -> 0 | AV9: =IF(AH9>0,INSPECTION*AF9/AH9,0) -> 4 | AW9: =IF(AH9>0,Y9/AH9,0)+Z9+AA9*USD_TO_AUD -> 33.2959 | AX9: =IF(AH9>0,(AB9+OTHER_FIXED)/AH9,0) -> 0 | AY9: =AI9+AR9+AU9+AV9+AW9+AX9 -> 214.94468 | AZ9: =IF(ISNUMBER(AE9),AE9,DEFECT_PCT) -> 0.03 | BA9: =AY9*AZ9 -> 6.4483405 | BB9: =IF(AD9="Flat",HANDLING_FLAT,STORAGE_PER_CBM*W9) -> 3.366 | BC9: =AY9+BA9+BB9 -> 224.75902 | BD9: =M9/(1+GST_RATE)*(1-MP_FEE) -> 271.81818 | BE9: =BD9-BC9 -> 47.059159 | BF9: =IF(BD9<>0,BE9/BD9,0) -> 0.17312734 | BG9: =BE9*AH9 -> 4705.9159 | BH9: =BC9*AH9 -> 22475.902 | BI9: =GST_RATE*(AI9+AU9+GST_TI_SHARE*AR9)*AH9 -> 1640.9358 | BJ9: =BH9+BI9 -> 24116.838 | BK9: =((BD9-BB9)/(1+AZ9)-(AR9+AV9+AW9+AX9))/(1+AT9)*FX_AUDUSD -> 131.78092 | BL9: =IF(T9>0,BK9/T9,0) -> 131.78092 | BM9: =BC9*(1+GST_RATE)/(1-MP_FEE) -> 247.23492 | BN9: =IF(AH9<=0,0,INSPECTION*AF9+Y9+AB9+OTHER_FIXED+IF(AG9="LCL",LCL_FIXED,AQ9)) -> 4629.59 | BO9: =BD9-((AI9+AU9+Z9+AA9*USD_TO_AUD+IF(AND(AG9="LCL",AH9>0),LCL_RATE*MAX(AO9,AP9)/AH9,0))*(1+AZ9)+BB9) -> 94.743936 | BP9: =IF(AH9<=0,"",IF(BO9>0,ROUNDUP(BN9*(1+AZ9)/BO9,0),"Never")) -> 51 | BQ9: =IF(AH9<=0,"",IF(BD9>0,ROUNDUP(BH9/BD9,0),"Never")) -> 83 | BR9: =IF(AH9>0,LCL_RATE*MAX(AO9,AP9)+LCL_FIXED,0) -> 3388.8 | BS9: =IF(AND(AH9>0,AJ9>0),ROUNDUP(AH9/AJ9,0)*COST_20GP,0) -> 5908 | BT9: =IF(AND(AH9>0,AK9>0),ROUNDUP(AH9/AK9,0)*COST_40HQ,0) -> 10064 | BU9: =IF(AH9<=0,"",IF(BR9<=MIN(BS9,BT9),"LCL",IF(BS9<=BT9,"20GP","40HQ"))) -> LCL | BV9: =TRIM(IF(AH9<V9,"Below MOQ. ","")&IF(AM9>1,"Needs "&AM9&" containers. ","")&IF(ISNUMBER(AN9),IF(AN9<0.85,"Box only "&TEXT(AN9,"0%")&" full – whole box charged. ",""),"")&IF(AND(BU9<>"",BU9<>AG9),"Cheaper freight at this qty: "&BU9&". ","")&IF(ISNUMBER(N9),IF(N9<0,"Price above price to beat. ",IF(N9<TARGET_DISC-0.0005,"Discount below target. ","")),"")&IF(U9<=0,"FOB missing. ","")&IF(N(X9)=0,"Carton kg missing. ","")&IF(BE9<0,"Loss-making. ","")&IF(ISNUMBER(BQ9),IF(BQ9>AH9,"Cash not recovered even if all units sell. ",""),"")) -> Discount below target. | BW9: A$299 is 32% under Amazon's cheapest complete dual-motor desk but only 6.5% under Advwin's A$319.90, so it is a ceiling. ~A$47/unit on a 100-desk LCL first order; A$84 on a full 20GP (274) and A$95 on a 40HQ (571). The EESS test cost is unverified. | BX9: US$100 = Prorials dual-motor frame US$76 (100–499; US$75 500–999; US$74 1,000+) + US$24 for a 140×70 particleboard top (ESTIMATE – no top FOB found). Cross-check: Lumi Legend complete dual-motor desk US$99–129 (MOQ 100). | BY9: 0.102 CBM = frame carton 0.057 (cited, 0.97×0.395×0.15 m) + top 0.045 (EST); 38.5 kg = 25 kg (cited) + 13.5 kg (EST). | BZ9: A$3,329.59 one-off = A$3,000 test/certification (EST) + EESS Responsible Supplier A$239.74 + equipment registration A$89.85. Prefer an integrated control box with IEC/CB reports. HS 9403.10 5% general. | CA9: Dual-motor frames from A$199.99 (Amazon); single-motor 140×70 desks A$199.95–259.99 delivered; FF/IKEA/Desky A$579–765. | CB9: verify_furniture.md Q1
A10: 6 | B10: Furniture | C10: Manual fabric recliner | D10: Full-size manual fabric recliner with footrest (Baoyi 'Dark Grey Fabric Manual Relax Recliner') | E10: BROKEN | F10: 6 | G10: 2 | H10: 160.95 | I10: Amazon AU – Artiss A4 fabric recliner with footrest (B07WRTRGB9), New (3) from | J10: 9 Oct 2026 (FREE delivery) | K10: 139 | L10: =IF(H10>0,H10*(1-TARGET_DISC),"") -> 144.855 | M10: =IF(AND(PRICE_MODE="Rule",ISNUMBER(L10)),L10,K10) -> 139 | N10: =IF(AND(H10>0,M10>0),1-M10/H10,"") -> 0.13637776 | O10: Anji Baoyi Information Technology | P10: Unknown – no manufacturer badge (Anhui origin; probable trader) | Q10: https://anjibaoyi.en.made-in-china.com/product/fLupXEDTmmkH/China-Home-Furniture-Dark-Grey-Fabric-Manual-Relax-Recliner.html | R10: 85 | S10: per unit (ladder US$63–93) | T10: 1 | U10: =R10*T10 -> 85 | V10: 30 | W10: 0.333 | X10: 33 | Y10: 300 | Z10: 0.3 | AA10: 0 | AB10: 300 | AC10: No | AD10: Per CBM | AF10: 1 | AG10: 20GP | AH10: 84 | AI10: =U10*USD_TO_AUD -> 122.19666 | AJ10: =IF(W10>0,IF(X10>0,MIN(INT(CBM_20GP/W10+0.000001),INT(KG_20GP/X10+0.000001)),INT(CBM_20GP/W10+0.000001)),0) -> 84 | AK10: =IF(W10>0,IF(X10>0,MIN(INT(CBM_40HQ/W10+0.000001),INT(KG_40HQ/X10+0.000001)),INT(CBM_40HQ/W10+0.000001)),0) -> 204 | AL10: =IF(AG10="20GP",AJ10,IF(AG10="40HQ",AK10,"LCL")) -> 84 | AM10: =IF(AH10<=0,0,IF(AG10="20GP",IF(AJ10>0,ROUNDUP(AH10/AJ10,0),0),IF(AG10="40HQ",IF(AK10>0,ROUNDUP(AH10/AK10,0),0),0))) -> 1 | AN10: =IF(OR(AG10="LCL",AM10=0),"",AH10/(AM10*AL10)) -> 1 | AO10: =AH10*W10 -> 27.972 | AP10: =AH10*X10/1000 -> 2.772 | AQ10: =IF(AH10<=0,0,IF(AG10="LCL",LCL_RATE*MAX(AO10,AP10)+LCL_FIXED,AM10*IF(AG10="20GP",COST_20GP,COST_40HQ))) -> 5908 | AR10: =IF(AH10>0,AQ10/AH10,0) -> 70.333333 | AS10: =IF(AG10="20GP",IF(AJ10>0,COST_20GP/AJ10,0),IF(AG10="40HQ",IF(AK10>0,COST_40HQ/AK10,0),AR10)) -> 70.333333 | AT10: =IF(AC10="Yes",0,DUTY_APPLIED) -> 0 | AU10: =AI10*AT10 -> 0 | AV10: =IF(AH10>0,INSPECTION*AF10/AH10,0) -> 4.7619048 | AW10: =IF(AH10>0,Y10/AH10,0)+Z10+AA10*USD_TO_AUD -> 3.8714286 | AX10: =IF(AH10>0,(AB10+OTHER_FIXED)/AH10,0) -> 3.5714286 | AY10: =AI10+AR10+AU10+AV10+AW10+AX10 -> 204.73476 | AZ10: =IF(ISNUMBER(AE10),AE10,DEFECT_PCT) -> 0.03 | BA10: =AY10*AZ10 -> 6.1420428 | BB10: =IF(AD10="Flat",HANDLING_FLAT,STORAGE_PER_CBM*W10) -> 10.989 | BC10: =AY10+BA10+BB10 -> 221.8658 | BD10: =M10/(1+GST_RATE)*(1-MP_FEE) -> 126.36364 | BE10: =BD10-BC10 -> -95.502166 | BF10: =IF(BD10<>0,BE10/BD10,0) -> -0.75577254 | BG10: =BE10*AH10 -> -8022.182 | BH10: =BC10*AH10 -> 18636.727 | BI10: =GST_RATE*(AI10+AU10+GST_TI_SHARE*AR10)*AH10 -> 1380.932 | BJ10: =BH10+BI10 -> 20017.659 | BK10: =((BD10-BB10)/(1+AZ10)-(AR10+AV10+AW10+AX10))/(1+AT10)*FX_AUDUSD -> 20.503585 | BL10: =IF(T10>0,BK10/T10,0) -> 20.503585 | BM10: =BC10*(1+GST_RATE)/(1-MP_FEE) -> 244.05238 | BN10: =IF(AH10<=0,0,INSPECTION*AF10+Y10+AB10+OTHER_FIXED+IF(AG10="LCL",LCL_FIXED,AQ10)) -> 6908 | BO10: =BD10-((AI10+AU10+Z10+AA10*USD_TO_AUD+IF(AND(AG10="LCL",AH10>0),LCL_RATE*MAX(AO10,AP10)/AH10,0))*(1+AZ10)+BB10) -> -10.796928 | BP10: =IF(AH10<=0,"",IF(BO10>0,ROUNDUP(BN10*(1+AZ10)/BO10,0),"Never")) -> Never | BQ10: =IF(AH10<=0,"",IF(BD10>0,ROUNDUP(BH10/BD10,0),"Never")) -> 148 | BR10: =IF(AH10>0,LCL_RATE*MAX(AO10,AP10)+LCL_FIXED,0) -> 7725.168 | BS10: =IF(AND(AH10>0,AJ10>0),ROUNDUP(AH10/AJ10,0)*COST_20GP,0) -> 5908 | BT10: =IF(AND(AH10>0,AK10>0),ROUNDUP(AH10/AK10,0)*COST_40HQ,0) -> 10064 | BU10: =IF(AH10<=0,"",IF(BR10<=MIN(BS10,BT10),"LCL",IF(BS10<=BT10,"20GP","40HQ"))) -> 20GP | BV10: =TRIM(IF(AH10<V10,"Below MOQ. ","")&IF(AM10>1,"Needs "&AM10&" containers. ","")&IF(ISNUMBER(AN10),IF(AN10<0.85,"Box only "&TEXT(AN10,"0%")&" full – whole box charged. ",""),"")&IF(AND(BU10<>"",BU10<>AG10),"Cheaper freight at this qty: "&BU10&". ","")&IF(ISNUMBER(N10),IF(N10<0,"Price above price to beat. ",IF(N10<TARGET_DISC-0.0005,"Discount below target. ","")),"")&IF(U10<=0,"FOB missing. ","")&IF(N(X10)=0,"Carton kg missing. ","")&IF(BE10<0,"Loss-making. ","")&IF(ISNUMBER(BQ10),IF(BQ10>AH10,"Cash not recovered even if all units sell. ",""),"")) -> Loss-making. Cash not recovered even if all units sell. | BW10: The original comparator was a swivel-rocker; a like-for-like Artiss A4 sells from A$160.95 delivered. At a rule-compliant A$139, landed cost of A$193–222 gives −A$67 to −A$96 per unit; the 0.33 CBM cube kills it. | BX10: Baoyi ladder US$63–93 (MOQ 30); verify base US$85. Rocker-swivel alt: Anji Jikeyuan 9151-1 US$85–125 (0.511 CBM, 50 kg). | BY10: 0.333 CBM inferred from the listing's '204 pieces/40HQ'; 33 kg ESTIMATE (no carton data listed). | BZ10: A$300 one-off + A$0.30/unit care label (EST); biosecurity contingency A$300 per shipment (EST; ICS untreated-wood question for 9401.61). 5% general. | CA10: Artiss A1 push-back A$159.95 + A$44.72 delivery; La Bella Shiloh A$229; original comparator Artiss A15 swivel-rocker A$389.95. | CB10: verify_furniture.md Q2
A11: 7 | B11: Furniture | C11: Fluted/LED TV unit 160cm | D11: Premium fluted / LED TV entertainment unit 160–190 cm; USB 5 V LED with IR remote (no mains adapter or AC outlets) | E11: BROKEN (as specified) | F11: 6 | G11: 3 | H11: 149.95 | I11: Amazon AU – Artiss 160 cm fluted TV unit (B0GJRDBT14) | J11: 9 Oct 2026 (FREE delivery; '−53%' promo price) | K11: 129 | L11: =IF(H11>0,H11*(1-TARGET_DISC),"") -> 134.955 | M11: =IF(AND(PRICE_MODE="Rule",ISNUMBER(L11)),L11,K11) -> 129 | N11: =IF(AND(H11>0,M11>0),1-M11/H11,"") -> 0.13971324 | O11: Shandong Sail Furniture | P11: Manufacturer & trading | Q11: https://sail-furniture.en.made-in-china.com/product/vaWUPEyJqLrk/China-Living-Room-Bedroom-Hotel-Modern-Contemporary-LED-Light-TV-Stands.html | R11: 45 | S11: per unit (verify base) | T11: 1 | U11: =R11*T11 -> 45 | V11: 100 | W11: 0.15 | X11: 38 | Y11: 800 | Z11: 1.5 | AA11: 0 | AB11: 0 | AC11: No | AD11: Per CBM | AF11: 1 | AG11: LCL | AH11: 100 | AI11: =U11*USD_TO_AUD -> 64.692352 | AJ11: =IF(W11>0,IF(X11>0,MIN(INT(CBM_20GP/W11+0.000001),INT(KG_20GP/X11+0.000001)),INT(CBM_20GP/W11+0.000001)),0) -> 186 | AK11: =IF(W11>0,IF(X11>0,MIN(INT(CBM_40HQ/W11+0.000001),INT(KG_40HQ/X11+0.000001)),INT(CBM_40HQ/W11+0.000001)),0) -> 453 | AL11: =IF(AG11="20GP",AJ11,IF(AG11="40HQ",AK11,"LCL")) -> LCL | AM11: =IF(AH11<=0,0,IF(AG11="20GP",IF(AJ11>0,ROUNDUP(AH11/AJ11,0),0),IF(AG11="40HQ",IF(AK11>0,ROUNDUP(AH11/AK11,0),0),0))) -> 0 | AN11: =IF(OR(AG11="LCL",AM11=0),"",AH11/(AM11*AL11)) | AO11: =AH11*W11 -> 15 | AP11: =AH11*X11/1000 -> 3.8 | AQ11: =IF(AH11<=0,0,IF(AG11="LCL",LCL_RATE*MAX(AO11,AP11)+LCL_FIXED,AM11*IF(AG11="20GP",COST_20GP,COST_40HQ))) -> 4560 | AR11: =IF(AH11>0,AQ11/AH11,0) -> 45.6 | AS11: =IF(AG11="20GP",IF(AJ11>0,COST_20GP/AJ11,0),IF(AG11="40HQ",IF(AK11>0,COST_40HQ/AK11,0),AR11)) -> 45.6 | AT11: =IF(AC11="Yes",0,DUTY_APPLIED) -> 0 | AU11: =AI11*AT11 -> 0 | AV11: =IF(AH11>0,INSPECTION*AF11/AH11,0) -> 4 | AW11: =IF(AH11>0,Y11/AH11,0)+Z11+AA11*USD_TO_AUD -> 9.5 | AX11: =IF(AH11>0,(AB11+OTHER_FIXED)/AH11,0) -> 0 | AY11: =AI11+AR11+AU11+AV11+AW11+AX11 -> 123.79235 | AZ11: =IF(ISNUMBER(AE11),AE11,DEFECT_PCT) -> 0.03 | BA11: =AY11*AZ11 -> 3.7137706 | BB11: =IF(AD11="Flat",HANDLING_FLAT,STORAGE_PER_CBM*W11) -> 4.95 | BC11: =AY11+BA11+BB11 -> 132.45612 | BD11: =M11/(1+GST_RATE)*(1-MP_FEE) -> 117.27273 | BE11: =BD11-BC11 -> -15.183395 | BF11: =IF(BD11<>0,BE11/BD11,0) -> -0.12947081 | BG11: =BE11*AH11 -> -1518.3395 | BH11: =BC11*AH11 -> 13245.612 | BI11: =GST_RATE*(AI11+AU11+GST_TI_SHARE*AR11)*AH11 -> 920.52352 | BJ11: =BH11+BI11 -> 14166.136 | BK11: =((BD11-BB11)/(1+AZ11)-(AR11+AV11+AW11+AX11))/(1+AT11)*FX_AUDUSD -> 34.746049 | BL11: =IF(T11>0,BK11/T11,0) -> 34.746049 | BM11: =BC11*(1+GST_RATE)/(1-MP_FEE) -> 145.70173 | BN11: =IF(AH11<=0,0,INSPECTION*AF11+Y11+AB11+OTHER_FIXED+IF(AG11="LCL",LCL_FIXED,AQ11)) -> 2100 | BO11: =BD11-((AI11+AU11+Z11+AA11*USD_TO_AUD+IF(AND(AG11="LCL",AH11>0),LCL_RATE*MAX(AO11,AP11)/AH11,0))*(1+AZ11)+BB11) -> 6.4466048 | BP11: =IF(AH11<=0,"",IF(BO11>0,ROUNDUP(BN11*(1+AZ11)/BO11,0),"Never")) -> 336 | BQ11: =IF(AH11<=0,"",IF(BD11>0,ROUNDUP(BH11/BD11,0),"Never")) -> 113 | BR11: =IF(AH11>0,LCL_RATE*MAX(AO11,AP11)+LCL_FIXED,0) -> 4560 | BS11: =IF(AND(AH11>0,AJ11>0),ROUNDUP(AH11/AJ11,0)*COST_20GP,0) -> 5908 | BT11: =IF(AND(AH11>0,AK11>0),ROUNDUP(AH11/AK11,0)*COST_40HQ,0) -> 10064 | BU11: =IF(AH11<=0,"",IF(BR11<=MIN(BS11,BT11),"LCL",IF(BS11<=BT11,"20GP","40HQ"))) -> LCL | BV11: =TRIM(IF(AH11<V11,"Below MOQ. ","")&IF(AM11>1,"Needs "&AM11&" containers. ","")&IF(ISNUMBER(AN11),IF(AN11<0.85,"Box only "&TEXT(AN11,"0%")&" full – whole box charged. ",""),"")&IF(AND(BU11<>"",BU11<>AG11),"Cheaper freight at this qty: "&BU11&". ","")&IF(ISNUMBER(N11),IF(N11<0,"Price above price to beat. ",IF(N11<TARGET_DISC-0.0005,"Discount below target. ","")),"")&IF(U11<=0,"FOB missing. ","")&IF(N(X11)=0,"Carton kg missing. ","")&IF(BE11<0,"Loss-making. ","")&IF(ISNUMBER(BQ11),IF(BQ11>AH11,"Cash not recovered even if all units sell. ",""),"")) -> Loss-making. Cash not recovered even if all units sell. | BW11: Fluted and LED looks are commodity on Amazon AU: Artiss 160 cm fluted is A$149.95 free-delivered and LED units start at A$117.80. At a rule-compliant A$129: −A$15 (LCL-100), +A$5 (20GP), +A$18 (40HQ). Toppling-furniture warnings apply to the listing itself. | BX11: US$45 = verify base between Sail / Feilu LED units (US$38–42, MOQ 100) and Jianmu Shijia fluted (US$43.80–49.80). Sail ladder US$42 (100–499) / US$40 / US$38 (1,000+). | BY11: 0.15 CBM / 38 kg ESTIMATES (no verified carton for a 160–190 cm unit; Sail's 160×50×75 cm package field is implausible). | BZ11: A$800 one-off = label artwork A$300 + EMC report review A$500 (EST) + A$1.50/unit for permanent toppling label, anchor kit and insert (EST). Toppling Furniture Information Standard 2024 (warning must appear in the Marketplace listing). 5% general. | CA11: Ufurniture 160 cm LED A$82.90 + A$34.90 delivery = A$117.80; ALFORDSON 180 cm fluted A$169.95; Advwin 160 cm RGB LED A$129.90 direct. | CB11: verify_furniture.md Q3
A12: 8 | B12: Furniture | C12: Queen pocket-spring mattress | D12: Queen pocket-spring mattress-in-a-box (roll-packed), ~22 cm, spec-matched to Giselle 22 cm | E12: REVISED | F12: 5 | G12: 5 | H12: 186.95 | I12: Amazon AU – Giselle Queen 22 cm pocket spring (B087TPK886), New (5) from | J12: 9 Oct 2026 (FREE delivery) | K12: 165 | L12: =IF(H12>0,H12*(1-TARGET_DISC),"") -> 168.255 | M12: =IF(AND(PRICE_MODE="Rule",ISNUMBER(L12)),L12,K12) -> 165 | N12: =IF(AND(H12>0,M12>0),1-M12/H12,"") -> 0.11741107 | O12: Foshan Aussie Hcl | P12: Manufacturer & trading | Q12: https://fsaussiehcl.en.made-in-china.com/product/qRFrxVCkrDhs/China-Queen-Size-Compressed-Vacuum-Pocket-Spring-Mattress-OEM-ODM-Home-Bedroom-Use.html | R12: 59 | S12: per unit (verify base; listing shows US$48) | T12: 1 | U12: =R12*T12 -> 59 | V12: 5 | W12: 0.144 | X12: 30 | Y12: 500 | Z12: 0.3 | AA12: 0 | AB12: 0 | AC12: Yes | AD12: Per CBM | AF12: 1 | AG12: LCL | AH12: 100 | AI12: =U12*USD_TO_AUD -> 84.818861 | AJ12: =IF(W12>0,IF(X12>0,MIN(INT(CBM_20GP/W12+0.000001),INT(KG_20GP/X12+0.000001)),INT(CBM_20GP/W12+0.000001)),0) -> 194 | AK12: =IF(W12>0,IF(X12>0,MIN(INT(CBM_40HQ/W12+0.000001),INT(KG_40HQ/X12+0.000001)),INT(CBM_40HQ/W12+0.000001)),0) -> 472 | AL12: =IF(AG12="20GP",AJ12,IF(AG12="40HQ",AK12,"LCL")) -> LCL | AM12: =IF(AH12<=0,0,IF(AG12="20GP",IF(AJ12>0,ROUNDUP(AH12/AJ12,0),0),IF(AG12="40HQ",IF(AK12>0,ROUNDUP(AH12/AK12,0),0),0))) -> 0 | AN12: =IF(OR(AG12="LCL",AM12=0),"",AH12/(AM12*AL12)) | AO12: =AH12*W12 -> 14.4 | AP12: =AH12*X12/1000 -> 3 | AQ12: =IF(AH12<=0,0,IF(AG12="LCL",LCL_RATE*MAX(AO12,AP12)+LCL_FIXED,AM12*IF(AG12="20GP",COST_20GP,COST_40HQ))) -> 4413.6 | AR12: =IF(AH12>0,AQ12/AH12,0) -> 44.136 | AS12: =IF(AG12="20GP",IF(AJ12>0,COST_20GP/AJ12,0),IF(AG12="40HQ",IF(AK12>0,COST_40HQ/AK12,0),AR12)) -> 44.136 | AT12: =IF(AC12="Yes",0,DUTY_APPLIED) -> 0 | AU12: =AI12*AT12 -> 0 | AV12: =IF(AH12>0,INSPECTION*AF12/AH12,0) -> 4 | AW12: =IF(AH12>0,Y12/AH12,0)+Z12+AA12*USD_TO_AUD -> 5.3 | AX12: =IF(AH12>0,(AB12+OTHER_FIXED)/AH12,0) -> 0 | AY12: =AI12+AR12+AU12+AV12+AW12+AX12 -> 138.25486 | AZ12: =IF(ISNUMBER(AE12),AE12,DEFECT_PCT) -> 0.03 | BA12: =AY12*AZ12 -> 4.1476458 | BB12: =IF(AD12="Flat",HANDLING_FLAT,STORAGE_PER_CBM*W12) -> 4.752 | BC12: =AY12+BA12+BB12 -> 147.15451 | BD12: =M12/(1+GST_RATE)*(1-MP_FEE) -> 150 | BE12: =BD12-BC12 -> 2.8454927 | BF12: =IF(BD12<>0,BE12/BD12,0) -> 0.018969952 | BG12: =BE12*AH12 -> 284.54927 | BH12: =BC12*AH12 -> 14715.451 | BI12: =GST_RATE*(AI12+AU12+GST_TI_SHARE*AR12)*AH12 -> 1113.0046 | BJ12: =BH12+BI12 -> 15828.455 | BK12: =((BD12-BB12)/(1+AZ12)-(AR12+AV12+AW12+AX12))/(1+AT12)*FX_AUDUSD -> 60.921675 | BL12: =IF(T12>0,BK12/T12,0) -> 60.921675 | BM12: =BC12*(1+GST_RATE)/(1-MP_FEE) -> 161.86996 | BN12: =IF(AH12<=0,0,INSPECTION*AF12+Y12+AB12+OTHER_FIXED+IF(AG12="LCL",LCL_FIXED,AQ12)) -> 1800 | BO12: =BD12-((AI12+AU12+Z12+AA12*USD_TO_AUD+IF(AND(AG12="LCL",AH12>0),LCL_RATE*MAX(AO12,AP12)/AH12,0))*(1+AZ12)+BB12) -> 21.385493 | BP12: =IF(AH12<=0,"",IF(BO12>0,ROUNDUP(BN12*(1+AZ12)/BO12,0),"Never")) -> 87 | BQ12: =IF(AH12<=0,"",IF(BD12>0,ROUNDUP(BH12/BD12,0),"Never")) -> 99 | BR12: =IF(AH12>0,LCL_RATE*MAX(AO12,AP12)+LCL_FIXED,0) -> 4413.6 | BS12: =IF(AND(AH12>0,AJ12>0),ROUNDUP(AH12/AJ12,0)*COST_20GP,0) -> 5908 | BT12: =IF(AND(AH12>0,AK12>0),ROUNDUP(AH12/AK12,0)*COST_40HQ,0) -> 10064 | BU12: =IF(AH12<=0,"",IF(BR12<=MIN(BS12,BT12),"LCL",IF(BS12<=BT12,"20GP","40HQ"))) -> LCL | BV12: =TRIM(IF(AH12<V12,"Below MOQ. ","")&IF(AM12>1,"Needs "&AM12&" containers. ","")&IF(ISNUMBER(AN12),IF(AN12<0.85,"Box only "&TEXT(AN12,"0%")&" full – whole box charged. ",""),"")&IF(AND(BU12<>"",BU12<>AG12),"Cheaper freight at this qty: "&BU12&". ","")&IF(ISNUMBER(N12),IF(N12<0,"Price above price to beat. ",IF(N12<TARGET_DISC-0.0005,"Discount below target. ","")),"")&IF(U12<=0,"FOB missing. ","")&IF(N(X12)=0,"Carton kg missing. ","")&IF(BE12<0,"Loss-making. ","")&IF(ISNUMBER(BQ12),IF(BQ12>AH12,"Cash not recovered even if all units sell. ",""),"")) | BW12: Floor confirmed (Giselle A$186.95 free-delivered; A$165 is 11.7% below). Duty is Free and compliance light, but a 100-unit LCL first order only breaks even at US$59 FOB; ~A$21 on a full 20GP and ~A$34 on a 40HQ. At Aussie Hcl's listed US$48: A$19 / A$37 / A$50. | BX12: Verify base US$59 (the original's spec-matched FOB). Aussie Hcl lists a flat US$48 (MOQ 5) but its spec (height, coil count, comfort layers) is unknown. Break-even FOB US$61 (LCL-100) / US$73 (20GP) / US$82 (40HQ). | BY12: 30×30×160 cm roll = 0.144 CBM (Aussie Hcl loading table: 472 per 40HQ, 193 per 20GP), cited; 30 kg ESTIMATE. | BZ12: A$500 one-off + A$0.30/unit care label (EST; Care Labelling Information Standard 2023). HS 9404.21/.29 mattresses are Free at the general rate. | CA12: FF foam queen A$159; Zinus deal A$157.05 (Aug 2026); Kmart euro-top A$229–309; ALDI A$239 (Jul 2026). | CB12: verify_furniture.md Q4
A13: 9 | B13: Home gym | C13: 100kg bumper plate set | D13: 100 kg Olympic rubber bumper plate set (2×5, 2×10, 2×15, 2×20 kg) | E13: CONFIRMED | F13: 6 | G13: 6 | H13: 400 | I13: Amazon AU – BRIXX Classic 100 kg package (search snippet; page could not be opened) | J13: Undated search snippet; next verified floor CORTEX V3 100 kg A$464.09 (Lifespan, 9 Oct 2026) | K13: 339 | L13: =IF(H13>0,H13*(1-TARGET_DISC),"") -> 360 | M13: =IF(AND(PRICE_MODE="Rule",ISNUMBER(L13)),L13,K13) -> 339 | N13: =IF(AND(H13>0,M13>0),1-M13/H13,"") -> 0.1525 | O13: Nantong Tengtai Sporting Fitness Co., Ltd. | P13: Unknown – not shown on listing (verify note calls it a manufacturer) | Q13: https://tt-sports.en.made-in-china.com/product/mQlUwAIbaHVq/China-Gym-Fitness-Bumper-Plate-Rubber-Competition-Weight-Bumper-Plate.html | R13: 1.3 | S13: per kg (verify mid-band base) | T13: 100 | U13: =R13*T13 -> 130 | V13: 10 | W13: 0.1 | X13: 103 | Y13: 0 | Z13: 0 | AA13: 0 | AB13: 0 | AC13: No | AD13: Flat | AF13: 1 | AG13: 20GP | AH13: 211 | AI13: =U13*USD_TO_AUD -> 186.88902 | AJ13: =IF(W13>0,IF(X13>0,MIN(INT(CBM_20GP/W13+0.000001),INT(KG_20GP/X13+0.000001)),INT(CBM_20GP/W13+0.000001)),0) -> 211 | AK13: =IF(W13>0,IF(X13>0,MIN(INT(CBM_40HQ/W13+0.000001),INT(KG_40HQ/X13+0.000001)),INT(CBM_40HQ/W13+0.000001)),0) -> 213 | AL13: =IF(AG13="20GP",AJ13,IF(AG13="40HQ",AK13,"LCL")) -> 211 | AM13: =IF(AH13<=0,0,IF(AG13="20GP",IF(AJ13>0,ROUNDUP(AH13/AJ13,0),0),IF(AG13="40HQ",IF(AK13>0,ROUNDUP(AH13/AK13,0),0),0))) -> 1 | AN13: =IF(OR(AG13="LCL",AM13=0),"",AH13/(AM13*AL13)) -> 1 | AO13: =AH13*W13 -> 21.1 | AP13: =AH13*X13/1000 -> 21.733 | AQ13: =IF(AH13<=0,0,IF(AG13="LCL",LCL_RATE*MAX(AO13,AP13)+LCL_FIXED,AM13*IF(AG13="20GP",COST_20GP,COST_40HQ))) -> 5908 | AR13: =IF(AH13>0,AQ13/AH13,0) -> 28 | AS13: =IF(AG13="20GP",IF(AJ13>0,COST_20GP/AJ13,0),IF(AG13="40HQ",IF(AK13>0,COST_40HQ/AK13,0),AR13)) -> 28 | AT13: =IF(AC13="Yes",0,DUTY_APPLIED) -> 0 | AU13: =AI13*AT13 -> 0 | AV13: =IF(AH13>0,INSPECTION*AF13/AH13,0) -> 1.8957346 | AW13: =IF(AH13>0,Y13/AH13,0)+Z13+AA13*USD_TO_AUD -> 0 | AX13: =IF(AH13>0,(AB13+OTHER_FIXED)/AH13,0) -> 0 | AY13: =AI13+AR13+AU13+AV13+AW13+AX13 -> 216.78475 | AZ13: =IF(ISNUMBER(AE13),AE13,DEFECT_PCT) -> 0.03 | BA13: =AY13*AZ13 -> 6.5035425 | BB13: =IF(AD13="Flat",HANDLING_FLAT,STORAGE_PER_CBM*W13) -> 5 | BC13: =AY13+BA13+BB13 -> 228.28829 | BD13: =M13/(1+GST_RATE)*(1-MP_FEE) -> 308.18182 | BE13: =BD13-BC13 -> 79.893524 | BF13: =IF(BD13<>0,BE13/BD13,0) -> 0.25924152 | BG13: =BE13*AH13 -> 16857.534 | BH13: =BC13*AH13 -> 48168.83 | BI13: =GST_RATE*(AI13+AU13+GST_TI_SHARE*AR13)*AH13 -> 4297.8383 | BJ13: =BH13+BI13 -> 52466.668 | BK13: =((BD13-BB13)/(1+AZ13)-(AR13+AV13+AW13+AX13))/(1+AT13)*FX_AUDUSD -> 183.95528 | BL13: =IF(T13>0,BK13/T13,0) -> 1.8395528 | BM13: =BC13*(1+GST_RATE)/(1-MP_FEE) -> 251.11712 | BN13: =IF(AH13<=0,0,INSPECTION*AF13+Y13+AB13+OTHER_FIXED+IF(AG13="LCL",LCL_FIXED,AQ13)) -> 6308 | BO13: =BD13-((AI13+AU13+Z13+AA13*USD_TO_AUD+IF(AND(AG13="LCL",AH13>0),LCL_RATE*MAX(AO13,AP13)/AH13,0))*(1+AZ13)+BB13) -> 110.68613 | BP13: =IF(AH13<=0,"",IF(BO13>0,ROUNDUP(BN13*(1+AZ13)/BO13,0),"Never")) -> 59 | BQ13: =IF(AH13<=0,"",IF(BD13>0,ROUNDUP(BH13/BD13,0),"Never")) -> 157 | BR13: =IF(AH13>0,LCL_RATE*MAX(AO13,AP13)+LCL_FIXED,0) -> 6202.852 | BS13: =IF(AND(AH13>0,AJ13>0),ROUNDUP(AH13/AJ13,0)*COST_20GP,0) -> 5908 | BT13: =IF(AND(AH13>0,AK13>0),ROUNDUP(AH13/AK13,0)*COST_40HQ,0) -> 10064 | BU13: =IF(AH13<=0,"",IF(BR13<=MIN(BS13,BT13),"LCL",IF(BS13<=BT13,"20GP","40HQ"))) -> 20GP | BV13: =TRIM(IF(AH13<V13,"Below MOQ. ","")&IF(AM13>1,"Needs "&AM13&" containers. ","")&IF(ISNUMBER(AN13),IF(AN13<0.85,"Box only "&TEXT(AN13,"0%")&" full – whole box charged. ",""),"")&IF(AND(BU13<>"",BU13<>AG13),"Cheaper freight at this qty: "&BU13&". ","")&IF(ISNUMBER(N13),IF(N13<0,"Price above price to beat. ",IF(N13<TARGET_DISC-0.0005,"Discount below target. ","")),"")&IF(U13<=0,"FOB missing. ","")&IF(N(X13)=0,"Carton kg missing. ","")&IF(BE13<0,"Loss-making. ","")&IF(ISNUMBER(BQ13),IF(BQ13>AH13,"Cash not recovered even if all units sell. ",""),"")) | BW13: A$339 is 15% under the A$400 BRIXX snippet and 27% under the verified CORTEX A$464.09. FOB of US$1.00–1.50/kg holds across 8+ listings. ~A$79/set (26%) in a weight-capped 20GP of 211 sets; the risk is selling 100–200 heavy sets plus used-plate competition. | BX13: US$1.30/kg × 100 kg = US$130/set (verify mid-band of US$1.00–1.50/kg). Tengtai lists US$1.00/kg, MOQ 1,000 kg (= 10 sets) → GP ~A$124/set in a 20GP. Others: Nantong Ironman US$1.29–1.49; Dx Grandway US$1.20–1.40; Hebei Dili US$1.25–1.35; Dingzhou Yunlingyu US$1.10–1.20. | BY13: 0.10 CBM / 103 kg per set ESTIMATE (no supplier gives per-set carton data; Tengtai ships in plywood cases). | BZ13: No mandatory standard identified; no compliance cost. Flat A$5 handling. HS 9506.91 5% general / Free with CoO. Plywood cases are exempt from ISPM 15. | CA13: BRIXX PRO 100 kg A$575 (Bunnings Marketplace); Harvey Norman A$670–691; CORTEX 70 kg A$325.56 (Amazon). | CB13: verify_gym_pets.md Q1
A14: 10 | B14: Home gym | C14: 2x40kg dial dumbbell pair | D14: Pair of 40 kg dial / quick-adjust dumbbells (2 × 40 kg) | E14: REVISED | F14: 6 | G14: 4 | H14: 449.99 | I14: Amazon AU – Fitness Master 2×40 kg dial set (B0F4L17HT6), '1 offer from' (1 rating) | J14: 9 Oct 2026 (delivery not visible) | K14: 379 | L14: =IF(H14>0,H14*(1-TARGET_DISC),"") -> 404.991 | M14: =IF(AND(PRICE_MODE="Rule",ISNUMBER(L14)),L14,K14) -> 379 | N14: =IF(AND(H14>0,M14>0),1-M14/H14,"") -> 0.15775906 | O14: Yiwu Jiai E-Commerce Firm (compact carton) | P14: Trading / e-commerce (by name) | Q14: https://ja-pilatesreformer.en.made-in-china.com/product/jphryQLHXBcz/China-40kg-Adjustable-Cast-Iron-Body-Training-Equipment-Dumbbell-for-Body-Training.html | R14: 85 | S14: per piece (single dumbbell) | T14: 2 | U14: =R14*T14 -> 170 | V14: 1 | W14: 0.13 | X14: 90 | Y14: 0 | Z14: 0 | AA14: 0 | AB14: 0 | AC14: No | AD14: Flat | AF14: 1 | AG14: 20GP | AH14: 215 | AI14: =U14*USD_TO_AUD -> 244.39333 | AJ14: =IF(W14>0,IF(X14>0,MIN(INT(CBM_20GP/W14+0.000001),INT(KG_20GP/X14+0.000001)),INT(CBM_20GP/W14+0.000001)),0) -> 215 | AK14: =IF(W14>0,IF(X14>0,MIN(INT(CBM_40HQ/W14+0.000001),INT(KG_40HQ/X14+0.000001)),INT(CBM_40HQ/W14+0.000001)),0) -> 244 | AL14: =IF(AG14="20GP",AJ14,IF(AG14="40HQ",AK14,"LCL")) -> 215 | AM14: =IF(AH14<=0,0,IF(AG14="20GP",IF(AJ14>0,ROUNDUP(AH14/AJ14,0),0),IF(AG14="40HQ",IF(AK14>0,ROUNDUP(AH14/AK14,0),0),0))) -> 1 | AN14: =IF(OR(AG14="LCL",AM14=0),"",AH14/(AM14*AL14)) -> 1 | AO14: =AH14*W14 -> 27.95 | AP14: =AH14*X14/1000 -> 19.35 | AQ14: =IF(AH14<=0,0,IF(AG14="LCL",LCL_RATE*MAX(AO14,AP14)+LCL_FIXED,AM14*IF(AG14="20GP",COST_20GP,COST_40HQ))) -> 5908 | AR14: =IF(AH14>0,AQ14/AH14,0) -> 27.47907 | AS14: =IF(AG14="20GP",IF(AJ14>0,COST_20GP/AJ14,0),IF(AG14="40HQ",IF(AK14>0,COST_40HQ/AK14,0),AR14)) -> 27.47907 | AT14: =IF(AC14="Yes",0,DUTY_APPLIED) -> 0 | AU14: =AI14*AT14 -> 0 | AV14: =IF(AH14>0,INSPECTION*AF14/AH14,0) -> 1.8604651 | AW14: =IF(AH14>0,Y14/AH14,0)+Z14+AA14*USD_TO_AUD -> 0 | AX14: =IF(AH14>0,(AB14+OTHER_FIXED)/AH14,0) -> 0 | AY14: =AI14+AR14+AU14+AV14+AW14+AX14 -> 273.73286 | AZ14: =IF(ISNUMBER(AE14),AE14,DEFECT_PCT) -> 0.03 | BA14: =AY14*AZ14 -> 8.2119859 | BB14: =IF(AD14="Flat",HANDLING_FLAT,STORAGE_PER_CBM*W14) -> 5 | BC14: =AY14+BA14+BB14 -> 286.94485 | BD14: =M14/(1+GST_RATE)*(1-MP_FEE) -> 344.54545 | BE14: =BD14-BC14 -> 57.600604 | BF14: =IF(BD14<>0,BE14/BD14,0) -> 0.16717853 | BG14: =BE14*AH14 -> 12384.13 | BH14: =BC14*AH14 -> 61693.143 | BI14: =GST_RATE*(AI14+AU14+GST_TI_SHARE*AR14)*AH14 -> 5608.9366 | BJ14: =BH14+BI14 -> 67302.079 | BK14: =((BD14-BB14)/(1+AZ14)-(AR14+AV14+AW14+AX14))/(1+AT14)*FX_AUDUSD -> 208.89998 | BL14: =IF(T14>0,BK14/T14,0) -> 104.44999 | BM14: =BC14*(1+GST_RATE)/(1-MP_FEE) -> 315.63934 | BN14: =IF(AH14<=0,0,INSPECTION*AF14+Y14+AB14+OTHER_FIXED+IF(AG14="LCL",LCL_FIXED,AQ14)) -> 6308 | BO14: =BD14-((AI14+AU14+Z14+AA14*USD_TO_AUD+IF(AND(AG14="LCL",AH14>0),LCL_RATE*MAX(AO14,AP14)/AH14,0))*(1+AZ14)+BB14) -> 87.820325 | BP14: =IF(AH14<=0,"",IF(BO14>0,ROUNDUP(BN14*(1+AZ14)/BO14,0),"Never")) -> 74 | BQ14: =IF(AH14<=0,"",IF(BD14>0,ROUNDUP(BH14/BD14,0),"Never")) -> 180 | BR14: =IF(AH14>0,LCL_RATE*MAX(AO14,AP14)+LCL_FIXED,0) -> 7719.8 | BS14: =IF(AND(AH14>0,AJ14>0),ROUNDUP(AH14/AJ14,0)*COST_20GP,0) -> 5908 | BT14: =IF(AND(AH14>0,AK14>0),ROUNDUP(AH14/AK14,0)*COST_40HQ,0) -> 10064 | BU14: =IF(AH14<=0,"",IF(BR14<=MIN(BS14,BT14),"LCL",IF(BS14<=BT14,"20GP","40HQ"))) -> 20GP | BV14: =TRIM(IF(AH14<V14,"Below MOQ. ","")&IF(AM14>1,"Needs "&AM14&" containers. ","")&IF(ISNUMBER(AN14),IF(AN14<0.85,"Box only "&TEXT(AN14,"0%")&" full – whole box charged. ",""),"")&IF(AND(BU14<>"",BU14<>AG14),"Cheaper freight at this qty: "&BU14&". ","")&IF(ISNUMBER(N14),IF(N14<0,"Price above price to beat. ",IF(N14<TARGET_DISC-0.0005,"Discount below target. ","")),"")&IF(U14<=0,"FOB missing. ","")&IF(N(X14)=0,"Carton kg missing. ","")&IF(BE14<0,"Loss-making. ","")&IF(ISNUMBER(BQ14),IF(BQ14>AH14,"Cash not recovered even if all units sell. ",""),"")) | BW14: The price gap to Amazon holds, but every 40 kg listing is priced per SINGLE dumbbell (US$164–176 a pair) and cartons are bulkier than assumed. ~A$57/pair (17%) in a volume-limited 20GP; A$20–28 by LCL. Demand evidence is thin (the Amazon floor listing has 1 rating). | BX14: US$85/piece × 2 = verify base US$170/pair (midpoint of 40 kg listings). Jiai US$88.00 (1–99 pcs) / US$81.84 (100+); Xiamen F-Orchid US$86.00 (MOQ 50; bulky 0.122 CBM per piece); Dezhou Ranao US$80–85 per 'set' (unit ambiguous); Dezhou Eagle (trader) US$110–119. | BY14: Compact carton 0.13 CBM / 90 kg per pair (Jiai 58×37×30 cm = 0.0644 CBM, 45 kg per piece). F-Orchid's bulky carton (0.244 CBM per pair) cuts GP to ~A$27. | BZ14: No mandatory standard identified; no compliance cost. Flat A$5 handling. HS 9506.91 5% general / Free with CoO. | CA14: fitnessLAB 2×40 kg A$499; Cortex Revolock V2 80 kg A$699 (Lifespan). | CB14: verify_gym_pets.md Q2
A15: 11 | B15: Home gym | C15: Kettlebell set 8/12/16kg | D15: Cast-iron kettlebell set 8 + 12 + 16 kg (36 kg) | E15: REVISED | F15: 4 | G15: 3 | H15: 117 | I15: Kmart own-brand neoprene kettlebells 8 + 12 + 15 kg (A$29 + A$39 + A$49) | J15: Undated search snippets (Kmart returned 403) | K15: 99 | L15: =IF(H15>0,H15*(1-TARGET_DISC),"") -> 105.3 | M15: =IF(AND(PRICE_MODE="Rule",ISNUMBER(L15)),L15,K15) -> 99 | N15: =IF(AND(H15>0,M15>0),1-M15/H15,"") -> 0.15384615 | O15: Dingzhou Yunlingyu Sports Goods (Hebei) | P15: Manufacturer & trading | Q15: https://dingzhouyunlingyu.en.made-in-china.com/product/vFNfVkWwrgrJ/China-Manufacturer-Gym-Equipment-Sport-Competition-Kettle-Bell-Set-Lb-and-Kg-Body-Building-Fitness-Cast-Iron-Kettlebells.html | R15: 1.2 | S15: per kg (verify base) | T15: 36 | U15: =R15*T15 -> 43.2 | V15: 3 | W15: 0.035 | X15: 37.5 | Y15: 0 | Z15: 0 | AA15: 0 | AB15: 0 | AC15: No | AD15: Flat | AF15: 1 | AG15: 20GP | AH15: 581 | AI15: =U15*USD_TO_AUD -> 62.104658 | AJ15: =IF(W15>0,IF(X15>0,MIN(INT(CBM_20GP/W15+0.000001),INT(KG_20GP/X15+0.000001)),INT(CBM_20GP/W15+0.000001)),0) -> 581 | AK15: =IF(W15>0,IF(X15>0,MIN(INT(CBM_40HQ/W15+0.000001),INT(KG_40HQ/X15+0.000001)),INT(CBM_40HQ/W15+0.000001)),0) -> 586 | AL15: =IF(AG15="20GP",AJ15,IF(AG15="40HQ",AK15,"LCL")) -> 581 | AM15: =IF(AH15<=0,0,IF(AG15="20GP",IF(AJ15>0,ROUNDUP(AH15/AJ15,0),0),IF(AG15="40HQ",IF(AK15>0,ROUNDUP(AH15/AK15,0),0),0))) -> 1 | AN15: =IF(OR(AG15="LCL",AM15=0),"",AH15/(AM15*AL15)) -> 1 | AO15: =AH15*W15 -> 20.335 | AP15: =AH15*X15/1000 -> 21.7875 | AQ15: =IF(AH15<=0,0,IF(AG15="LCL",LCL_RATE*MAX(AO15,AP15)+LCL_FIXED,AM15*IF(AG15="20GP",COST_20GP,COST_40HQ))) -> 5908 | AR15: =IF(AH15>0,AQ15/AH15,0) -> 10.168675 | AS15: =IF(AG15="20GP",IF(AJ15>0,COST_20GP/AJ15,0),IF(AG15="40HQ",IF(AK15>0,COST_40HQ/AK15,0),AR15)) -> 10.168675 | AT15: =IF(AC15="Yes",0,DUTY_APPLIED) -> 0 | AU15: =AI15*AT15 -> 0 | AV15: =IF(AH15>0,INSPECTION*AF15/AH15,0) -> 0.68846816 | AW15: =IF(AH15>0,Y15/AH15,0)+Z15+AA15*USD_TO_AUD -> 0 | AX15: =IF(AH15>0,(AB15+OTHER_FIXED)/AH15,0) -> 0 | AY15: =AI15+AR15+AU15+AV15+AW15+AX15 -> 72.961801 | AZ15: =IF(ISNUMBER(AE15),AE15,DEFECT_PCT) -> 0.03 | BA15: =AY15*AZ15 -> 2.188854 | BB15: =IF(AD15="Flat",HANDLING_FLAT,STORAGE_PER_CBM*W15) -> 5 | BC15: =AY15+BA15+BB15 -> 80.150655 | BD15: =M15/(1+GST_RATE)*(1-MP_FEE) -> 90 | BE15: =BD15-BC15 -> 9.8493453 | BF15: =IF(BD15<>0,BE15/BD15,0) -> 0.10943717 | BG15: =BE15*AH15 -> 5722.4696 | BH15: =BC15*AH15 -> 46567.53 | BI15: =GST_RATE*(AI15+AU15+GST_TI_SHARE*AR15)*AH15 -> 3962.7606 | BJ15: =BH15+BI15 -> 50530.291 | BK15: =((BD15-BB15)/(1+AZ15)-(AR15+AV15+AW15+AX15))/(1+AT15)*FX_AUDUSD -> 49.851655 | BL15: =IF(T15>0,BK15/T15,0) -> 1.3847682 | BM15: =BC15*(1+GST_RATE)/(1-MP_FEE) -> 88.16572 | BN15: =IF(AH15<=0,0,INSPECTION*AF15+Y15+AB15+OTHER_FIXED+IF(AG15="LCL",LCL_FIXED,AQ15)) -> 6308 | BO15: =BD15-((AI15+AU15+Z15+AA15*USD_TO_AUD+IF(AND(AG15="LCL",AH15>0),LCL_RATE*MAX(AO15,AP15)/AH15,0))*(1+AZ15)+BB15) -> 21.032202 | BP15: =IF(AH15<=0,"",IF(BO15>0,ROUNDUP(BN15*(1+AZ15)/BO15,0),"Never")) -> 309 | BQ15: =IF(AH15<=0,"",IF(BD15>0,ROUNDUP(BH15/BD15,0),"Never")) -> 518 | BR15: =IF(AH15>0,LCL_RATE*MAX(AO15,AP15)+LCL_FIXED,0) -> 6216.15 | BS15: =IF(AND(AH15>0,AJ15>0),ROUNDUP(AH15/AJ15,0)*COST_20GP,0) -> 5908 | BT15: =IF(AND(AH15>0,AK15>0),ROUNDUP(AH15/AK15,0)*COST_40HQ,0) -> 10064 | BU15: =IF(AH15<=0,"",IF(BR15<=MIN(BS15,BT15),"LCL",IF(BS15<=BT15,"20GP","40HQ"))) -> 20GP | BV15: =TRIM(IF(AH15<V15,"Below MOQ. ","")&IF(AM15>1,"Needs "&AM15&" containers. ","")&IF(ISNUMBER(AN15),IF(AN15<0.85,"Box only "&TEXT(AN15,"0%")&" full – whole box charged. ",""),"")&IF(AND(BU15<>"",BU15<>AG15),"Cheaper freight at this qty: "&BU15&". ","")&IF(ISNUMBER(N15),IF(N15<0,"Price above price to beat. ",IF(N15<TARGET_DISC-0.0005,"Discount below target. ","")),"")&IF(U15<=0,"FOB missing. ","")&IF(N(X15)=0,"Carton kg missing. ","")&IF(BE15<0,"Loss-making. ","")&IF(ISNUMBER(BQ15),IF(BQ15>AH15,"Cash not recovered even if all units sell. ",""),"")) | BW15: Kmart's own-brand bells set the floor (A$117 for 8+12+15 kg), so the rule price is ~A$94–105. At A$99 a full 20GP makes ~A$10/set (11%); LCL is about zero; the manufacturer's own small-order US$1.40/kg wipes the margin out. Weight filler only. | BX15: US$1.20/kg × 36 kg = US$43.20/set (between traders' US$0.90–1.25/kg and Yunlingyu's US$1.40/kg for 100–9,999 kg; US$1.00/kg only above 10 t). Hebei Dili (trader) US$0.90–1.10/kg. | BY15: 0.035 CBM / 37.5 kg per set ESTIMATE (no per-kettlebell carton data). | BZ15: No mandatory standard identified; no compliance cost. Flat A$5 handling. Require ISPM 15 marks or plywood if wooden cases are used. | CA15: CORTEX 16 kg A$74.99 (Lifespan); Everfit 16 kg cast iron A$89.95–92.95 (Amazon); Rebel Celsius 8/12/16 kg A$290.97. | CB15: verify_gym_pets.md Q3
A16: 12 | B16: Pets | C16: 48in steel dog crate | D16: 48" (≈121×76×82 cm) folding steel wire dog crate with tray (Fuyuanxin FYX-PET-CRATE-48, 122×75.5×84 cm) | E16: BROKEN (as specified) | F16: 6 | G16: 3 | H16: 94.46 | I16: Bunnings Marketplace – i.Pet 48" 3-door crate (same crate A$104.95 on Amazon AU) | J16: Snippet (undated); Amazon A$104.95 verified 9 Oct 2026 | K16: 85 | L16: =IF(H16>0,H16*(1-TARGET_DISC),"") -> 85.014 | M16: =IF(AND(PRICE_MODE="Rule",ISNUMBER(L16)),L16,K16) -> 85 | N16: =IF(AND(H16>0,M16>0),1-M16/H16,"") -> 0.10014821 | O16: Shenzhen Fuyuanxin Technology Development | P16: Trading company | Q16: https://fyuanx.en.made-in-china.com/product/cOsGxqSlXefQ/China-Heavy-Duty-Pet-Cage-Foldable-Metal-Crate-48-Inch-122-75-5-84cm.html | R16: 28.5 | S16: per piece (10–499 tier) | T16: 1 | U16: =R16*T16 -> 28.5 | V16: 10 | W16: 0.097 | X16: 17 | Y16: 0 | Z16: 0 | AA16: 0 | AB16: 0 | AC16: No | AD16: Flat | AF16: 1 | AG16: 20GP | AH16: 288 | AI16: =U16*USD_TO_AUD -> 40.971823 | AJ16: =IF(W16>0,IF(X16>0,MIN(INT(CBM_20GP/W16+0.000001),INT(KG_20GP/X16+0.000001)),INT(CBM_20GP/W16+0.000001)),0) -> 288 | AK16: =IF(W16>0,IF(X16>0,MIN(INT(CBM_40HQ/W16+0.000001),INT(KG_40HQ/X16+0.000001)),INT(CBM_40HQ/W16+0.000001)),0) -> 701 | AL16: =IF(AG16="20GP",AJ16,IF(AG16="40HQ",AK16,"LCL")) -> 288 | AM16: =IF(AH16<=0,0,IF(AG16="20GP",IF(AJ16>0,ROUNDUP(AH16/AJ16,0),0),IF(AG16="40HQ",IF(AK16>0,ROUNDUP(AH16/AK16,0),0),0))) -> 1 | AN16: =IF(OR(AG16="LCL",AM16=0),"",AH16/(AM16*AL16)) -> 1 | AO16: =AH16*W16 -> 27.936 | AP16: =AH16*X16/1000 -> 4.896 | AQ16: =IF(AH16<=0,0,IF(AG16="LCL",LCL_RATE*MAX(AO16,AP16)+LCL_FIXED,AM16*IF(AG16="20GP",COST_20GP,COST_40HQ))) -> 5908 | AR16: =IF(AH16>0,AQ16/AH16,0) -> 20.513889 | AS16: =IF(AG16="20GP",IF(AJ16>0,COST_20GP/AJ16,0),IF(AG16="40HQ",IF(AK16>0,COST_40HQ/AK16,0),AR16)) -> 20.513889 | AT16: =IF(AC16="Yes",0,DUTY_APPLIED) -> 0 | AU16: =AI16*AT16 -> 0 | AV16: =IF(AH16>0,INSPECTION*AF16/AH16,0) -> 1.3888889 | AW16: =IF(AH16>0,Y16/AH16,0)+Z16+AA16*USD_TO_AUD -> 0 | AX16: =IF(AH16>0,(AB16+OTHER_FIXED)/AH16,0) -> 0 | AY16: =AI16+AR16+AU16+AV16+AW16+AX16 -> 62.874601 | AZ16: =IF(ISNUMBER(AE16),AE16,DEFECT_PCT) -> 0.03 | BA16: =AY16*AZ16 -> 1.886238 | BB16: =IF(AD16="Flat",HANDLING_FLAT,STORAGE_PER_CBM*W16) -> 5 | BC16: =AY16+BA16+BB16 -> 69.760839 | BD16: =M16/(1+GST_RATE)*(1-MP_FEE) -> 77.272727 | BE16: =BD16-BC16 -> 7.5118886 | BF16: =IF(BD16<>0,BE16/BD16,0) -> 0.097212676 | BG16: =BE16*AH16 -> 2163.4239 | BH16: =BC16*AH16 -> 20091.122 | BI16: =GST_RATE*(AI16+AU16+GST_TI_SHARE*AR16)*AH16 -> 1534.4685 | BJ16: =BH16+BI16 -> 21625.59 | BK16: =((BD16-BB16)/(1+AZ16)-(AR16+AV16+AW16+AX16))/(1+AT16)*FX_AUDUSD -> 33.573077 | BL16: =IF(T16>0,BK16/T16,0) -> 33.573077 | BM16: =BC16*(1+GST_RATE)/(1-MP_FEE) -> 76.736923 | BN16: =IF(AH16<=0,0,INSPECTION*AF16+Y16+AB16+OTHER_FIXED+IF(AG16="LCL",LCL_FIXED,AQ16)) -> 6308 | BO16: =BD16-((AI16+AU16+Z16+AA16*USD_TO_AUD+IF(AND(AG16="LCL",AH16>0),LCL_RATE*MAX(AO16,AP16)/AH16,0))*(1+AZ16)+BB16) -> 30.07175 | BP16: =IF(AH16<=0,"",IF(BO16>0,ROUNDUP(BN16*(1+AZ16)/BO16,0),"Never")) -> 217 | BQ16: =IF(AH16<=0,"",IF(BD16>0,ROUNDUP(BH16/BD16,0),"Never")) -> 261 | BR16: =IF(AH16>0,LCL_RATE*MAX(AO16,AP16)+LCL_FIXED,0) -> 7716.384 | BS16: =IF(AND(AH16>0,AJ16>0),ROUNDUP(AH16/AJ16,0)*COST_20GP,0) -> 5908 | BT16: =IF(AND(AH16>0,AK16>0),ROUNDUP(AH16/AK16,0)*COST_40HQ,0) -> 10064 | BU16: =IF(AH16<=0,"",IF(BR16<=MIN(BS16,BT16),"LCL",IF(BS16<=BT16,"20GP","40HQ"))) -> 20GP | BV16: =TRIM(IF(AH16<V16,"Below MOQ. ","")&IF(AM16>1,"Needs "&AM16&" containers. ","")&IF(ISNUMBER(AN16),IF(AN16<0.85,"Box only "&TEXT(AN16,"0%")&" full – whole box charged. ",""),"")&IF(AND(BU16<>"",BU16<>AG16),"Cheaper freight at this qty: "&BU16&". ","")&IF(ISNUMBER(N16),IF(N16<0,"Price above price to beat. ",IF(N16<TARGET_DISC-0.0005,"Discount below target. ","")),"")&IF(U16<=0,"FOB missing. ","")&IF(N(X16)=0,"Carton kg missing. ","")&IF(BE16<0,"Loss-making. ","")&IF(ISNUMBER(BQ16),IF(BQ16>AH16,"Cash not recovered even if all units sell. ",""),"")) | BW16: The rule price is ~A$85 (10% under Bunnings' A$94.46), not A$100. The only 48"-specific FOB is a trader at US$24.80–28.50, far above the ≤US$15 needed for 35% GM. ~A$7/crate (9%) in a 20GP; ~A$20 only in a 40HQ of ~700 crates at US$24.80. | BX16: Fuyuanxin US$28.50 (10–499) / US$24.80 (500–999) / US$23.70 (1,000–4,999) / US$22.80 (5,000+). Xingtai Senxin XXL US$9–20 (no per-size price); Suzhou Quanhao US$10–40. | BY16: 0.097 CBM / 17 kg ESTIMATE (124×78×10 cm around the 121×76×9 cm folded crate; no supplier carton data). | BZ16: No mandatory standard identified; no compliance cost. Flat A$5 handling. HS 7326.20/.90 – confirm with a broker against ADC case 692 (welded mesh, 7314). No timber. | CA16: Amazon i.Pet 48" A$104.95; Velocity i.Pet A$99.95; BEASTIE A$119.95; Advwin 120×60×70 panel crate A$99.90. | CB16: verify_gym_pets.md Q4
A17: 13 | B17: Outdoor living | C17: Wood/pellet pizza oven | D17: Portable wood/pellet pizza oven, 11" stone, folding legs (Otia OTIA-BG-0008); sold with NO gas burner | E17: REVISED | F17: 6 | G17: 4 | H17: 122.76 | I17: Amazon AU – Costway Portable Multi-Fuel pizza oven (B0C2CKMK31); Costway direct A$126.95–135.95 | J17: Undated search summary (Amazon buy box not visible) | K17: 125 | L17: =IF(H17>0,H17*(1-TARGET_DISC),"") -> 110.484 | M17: =IF(AND(PRICE_MODE="Rule",ISNUMBER(L17)),L17,K17) -> 125 | N17: =IF(AND(H17>0,M17>0),1-M17/H17,"") -> -0.018246986 | O17: Qingdao Otia Industry and Trade | P17: Unknown – not stated ('Industry and Trade' name) | Q17: https://qdotia.en.made-in-china.com/product/imFpKPLCglYa/China-Amazon-Portable-Rotating-Pizza-Oven-with-Pizza-Stone-Wooden-Pellet-Pizza-Oven-Folding-Outdoor-Pizza-Oven.html | R17: 44.5 | S17: per unit (100–499 tier) | T17: 1 | U17: =R17*T17 -> 44.5 | V17: 100 | W17: 0.077826 | X17: 11.3 | Y17: 1000 | Z17: 0 | AA17: 0 | AB17: 0 | AC17: No | AD17: Per CBM | AF17: 1 | AG17: LCL | AH17: 200 | AI17: =U17*USD_TO_AUD -> 63.973548 | AJ17: =IF(W17>0,IF(X17>0,MIN(INT(CBM_20GP/W17+0.000001),INT(KG_20GP/X17+0.000001)),INT(CBM_20GP/W17+0.000001)),0) -> 359 | AK17: =IF(W17>0,IF(X17>0,MIN(INT(CBM_40HQ/W17+0.000001),INT(KG_40HQ/X17+0.000001)),INT(CBM_40HQ/W17+0.000001)),0) -> 873 | AL17: =IF(AG17="20GP",AJ17,IF(AG17="40HQ",AK17,"LCL")) -> LCL | AM17: =IF(AH17<=0,0,IF(AG17="20GP",IF(AJ17>0,ROUNDUP(AH17/AJ17,0),0),IF(AG17="40HQ",IF(AK17>0,ROUNDUP(AH17/AK17,0),0),0))) -> 0 | AN17: =IF(OR(AG17="LCL",AM17=0),"",AH17/(AM17*AL17)) | AO17: =AH17*W17 -> 15.5652 | AP17: =AH17*X17/1000 -> 2.26 | AQ17: =IF(AH17<=0,0,IF(AG17="LCL",LCL_RATE*MAX(AO17,AP17)+LCL_FIXED,AM17*IF(AG17="20GP",COST_20GP,COST_40HQ))) -> 4697.9088 | AR17: =IF(AH17>0,AQ17/AH17,0) -> 23.489544 | AS17: =IF(AG17="20GP",IF(AJ17>0,COST_20GP/AJ17,0),IF(AG17="40HQ",IF(AK17>0,COST_40HQ/AK17,0),AR17)) -> 23.489544 | AT17: =IF(AC17="Yes",0,DUTY_APPLIED) -> 0 | AU17: =AI17*AT17 -> 0 | AV17: =IF(AH17>0,INSPECTION*AF17/AH17,0) -> 2 | AW17: =IF(AH17>0,Y17/AH17,0)+Z17+AA17*USD_TO_AUD -> 5 | AX17: =IF(AH17>0,(AB17+OTHER_FIXED)/AH17,0) -> 0 | AY17: =AI17+AR17+AU17+AV17+AW17+AX17 -> 94.463092 | AZ17: =IF(ISNUMBER(AE17),AE17,DEFECT_PCT) -> 0.03 | BA17: =AY17*AZ17 -> 2.8338928 | BB17: =IF(AD17="Flat",HANDLING_FLAT,STORAGE_PER_CBM*W17) -> 2.568258 | BC17: =AY17+BA17+BB17 -> 99.865243 | BD17: =M17/(1+GST_RATE)*(1-MP_FEE) -> 113.63636 | BE17: =BD17-BC17 -> 13.771121 | BF17: =IF(BD17<>0,BE17/BD17,0) -> 0.12118586 | BG17: =BE17*AH17 -> 2754.2242 | BH17: =BC17*AH17 -> 19973.049 | BI17: =GST_RATE*(AI17+AU17+GST_TI_SHARE*AR17)*AH17 -> 1561.3455 | BJ17: =BH17+BI17 -> 21534.394 | BK17: =((BD17-BB17)/(1+AZ17)-(AR17+AV17+AW17+AX17))/(1+AT17)*FX_AUDUSD -> 53.800186 | BL17: =IF(T17>0,BK17/T17,0) -> 53.800186 | BM17: =BC17*(1+GST_RATE)/(1-MP_FEE) -> 109.85177 | BN17: =IF(AH17<=0,0,INSPECTION*AF17+Y17+AB17+OTHER_FIXED+IF(AG17="LCL",LCL_FIXED,AQ17)) -> 2300 | BO17: =BD17-((AI17+AU17+Z17+AA17*USD_TO_AUD+IF(AND(AG17="LCL",AH17>0),LCL_RATE*MAX(AO17,AP17)/AH17,0))*(1+AZ17)+BB17) -> 25.616121 | BP17: =IF(AH17<=0,"",IF(BO17>0,ROUNDUP(BN17*(1+AZ17)/BO17,0),"Never")) -> 93 | BQ17: =IF(AH17<=0,"",IF(BD17>0,ROUNDUP(BH17/BD17,0),"Never")) -> 176 | BR17: =IF(AH17>0,LCL_RATE*MAX(AO17,AP17)+LCL_FIXED,0) -> 4697.9088 | BS17: =IF(AND(AH17>0,AJ17>0),ROUNDUP(AH17/AJ17,0)*COST_20GP,0) -> 5908 | BT17: =IF(AND(AH17>0,AK17>0),ROUNDUP(AH17/AK17,0)*COST_40HQ,0) -> 10064 | BU17: =IF(AH17<=0,"",IF(BR17<=MIN(BS17,BT17),"LCL",IF(BS17<=BT17,"20GP","40HQ"))) -> LCL | BV17: =TRIM(IF(AH17<V17,"Below MOQ. ","")&IF(AM17>1,"Needs "&AM17&" containers. ","")&IF(ISNUMBER(AN17),IF(AN17<0.85,"Box only "&TEXT(AN17,"0%")&" full – whole box charged. ",""),"")&IF(AND(BU17<>"",BU17<>AG17),"Cheaper freight at this qty: "&BU17&". ","")&IF(ISNUMBER(N17),IF(N17<0,"Price above price to beat. ",IF(N17<TARGET_DISC-0.0005,"Discount below target. ","")),"")&IF(U17<=0,"FOB missing. ","")&IF(N(X17)=0,"Carton kg missing. ","")&IF(BE17<0,"Loss-making. ","")&IF(ISNUMBER(BQ17),IF(BQ17>AH17,"Cash not recovered even if all units sell. ",""),"")) -> Price above price to beat. | BW17: Costway sells comparable wood/pellet ovens at ~A$123–136, so the original A$139 fails the rule and ~A$125 is the practical ceiling (still slightly above Costway's A$122.76). A 200-unit LCL makes ~A$14/unit (12%); A$24 on a full 20GP. The oven is 11" with a bamboo handle; gas-burner and fire-ban risks. | BX17: Otia US$44.50 (100–499) / US$44.00 (500–999) / US$43.50 (1,000+). Alts: Suzhou Rdit US$50–70 (MOQ 460); Jiangmen SHT 12" US$75–82 (MOQ 300). | BY17: 54.5×42×34 cm = 0.0778 CBM, G.W. 11.3 kg (cited). | BZ17: A$1,000 per order (EST): AU manual, CO / outdoor-only / fire-ban labels, and a non-bamboo handle spec or treatment certificate. Sell with no gas burner (otherwise a Type A gas appliance needing AU certification). 5% general. | CA17: Costway 4-in-1 A$122.95 (Amazon) / A$126.95 direct; Costway 30 cm A$135.95; Bunnings Jumbuck A$199. | CB17: verify_outdoor.md Q1
A18: 14 | B18: Outdoor living | C18: Double hammock + steel stand | D18: Double cotton-canvas hammock with space-saving steel stand and carry bag (Lounger model 3602), 260×100×107 cm open | E18: CONFIRMED | F18: 6 | G18: 6 | H18: 105.95 | I18: Costway direct – Portable Hammock with Stand (PriceHipster history); Amazon AU ~A$118.99 (MINYII, search summary) | J18: Price since 12 Jun 2026 (price history) | K18: 95 | L18: =IF(H18>0,H18*(1-TARGET_DISC),"") -> 95.355 | M18: =IF(AND(PRICE_MODE="Rule",ISNUMBER(L18)),L18,K18) -> 95 | N18: =IF(AND(H18>0,M18>0),1-M18/H18,"") -> 0.10335064 | O18: Ningbo Lounger Import & Export | P18: Unknown – not stated ('Import & Export' name; probable trader) | Q18: https://lounger2.en.made-in-china.com/product/zatrBMfGjmRi/China-Easy-Assemble-Folding-Double-Portable-Hammock-with-Stand.html | R18: 21 | S18: per set (first-order price) | T18: 1 | U18: =R18*T18 -> 21 | V18: 200 | W18: 0.061248 | X18: 11 | Y18: 500 | Z18: 0 | AA18: 0 | AB18: 0 | AC18: No | AD18: Per CBM | AF18: 1 | AG18: LCL | AH18: 200 | AI18: =U18*USD_TO_AUD -> 30.189764 | AJ18: =IF(W18>0,IF(X18>0,MIN(INT(CBM_20GP/W18+0.000001),INT(KG_20GP/X18+0.000001)),INT(CBM_20GP/W18+0.000001)),0) -> 457 | AK18: =IF(W18>0,IF(X18>0,MIN(INT(CBM_40HQ/W18+0.000001),INT(KG_40HQ/X18+0.000001)),INT(CBM_40HQ/W18+0.000001)),0) -> 1110 | AL18: =IF(AG18="20GP",AJ18,IF(AG18="40HQ",AK18,"LCL")) -> LCL | AM18: =IF(AH18<=0,0,IF(AG18="20GP",IF(AJ18>0,ROUNDUP(AH18/AJ18,0),0),IF(AG18="40HQ",IF(AK18>0,ROUNDUP(AH18/AK18,0),0),0))) -> 0 | AN18: =IF(OR(AG18="LCL",AM18=0),"",AH18/(AM18*AL18)) | AO18: =AH18*W18 -> 12.2496 | AP18: =AH18*X18/1000 -> 2.2 | AQ18: =IF(AH18<=0,0,IF(AG18="LCL",LCL_RATE*MAX(AO18,AP18)+LCL_FIXED,AM18*IF(AG18="20GP",COST_20GP,COST_40HQ))) -> 3888.9024 | AR18: =IF(AH18>0,AQ18/AH18,0) -> 19.444512 | AS18: =IF(AG18="20GP",IF(AJ18>0,COST_20GP/AJ18,0),IF(AG18="40HQ",IF(AK18>0,COST_40HQ/AK18,0),AR18)) -> 19.444512 | AT18: =IF(AC18="Yes",0,DUTY_APPLIED) -> 0 | AU18: =AI18*AT18 -> 0 | AV18: =IF(AH18>0,INSPECTION*AF18/AH18,0) -> 2 | AW18: =IF(AH18>0,Y18/AH18,0)+Z18+AA18*USD_TO_AUD -> 2.5 | AX18: =IF(AH18>0,(AB18+OTHER_FIXED)/AH18,0) -> 0 | AY18: =AI18+AR18+AU18+AV18+AW18+AX18 -> 54.134276 | AZ18: =IF(ISNUMBER(AE18),AE18,DEFECT_PCT) -> 0.03 | BA18: =AY18*AZ18 -> 1.6240283 | BB18: =IF(AD18="Flat",HANDLING_FLAT,STORAGE_PER_CBM*W18) -> 2.021184 | BC18: =AY18+BA18+BB18 -> 57.779489 | BD18: =M18/(1+GST_RATE)*(1-MP_FEE) -> 86.363636 | BE18: =BD18-BC18 -> 28.584148 | BF18: =IF(BD18<>0,BE18/BD18,0) -> 0.33097434 | BG18: =BE18*AH18 -> 5716.8296 | BH18: =BC18*AH18 -> 11555.898 | BI18: =GST_RATE*(AI18+AU18+GST_TI_SHARE*AR18)*AH18 -> 837.12943 | BJ18: =BH18+BI18 -> 12393.027 | BK18: =((BD18-BB18)/(1+AZ18)-(AR18+AV18+AW18+AX18))/(1+AT18)*FX_AUDUSD -> 40.304013 | BL18: =IF(T18>0,BK18/T18,0) -> 40.304013 | BM18: =BC18*(1+GST_RATE)/(1-MP_FEE) -> 63.557437 | BN18: =IF(AH18<=0,0,INSPECTION*AF18+Y18+AB18+OTHER_FIXED+IF(AG18="LCL",LCL_FIXED,AQ18)) -> 1800 | BO18: =BD18-((AI18+AU18+Z18+AA18*USD_TO_AUD+IF(AND(AG18="LCL",AH18>0),LCL_RATE*MAX(AO18,AP18)/AH18,0))*(1+AZ18)+BB18) -> 37.854148 | BP18: =IF(AH18<=0,"",IF(BO18>0,ROUNDUP(BN18*(1+AZ18)/BO18,0),"Never")) -> 49 | BQ18: =IF(AH18<=0,"",IF(BD18>0,ROUNDUP(BH18/BD18,0),"Never")) -> 134 | BR18: =IF(AH18>0,LCL_RATE*MAX(AO18,AP18)+LCL_FIXED,0) -> 3888.9024 | BS18: =IF(AND(AH18>0,AJ18>0),ROUNDUP(AH18/AJ18,0)*COST_20GP,0) -> 5908 | BT18: =IF(AND(AH18>0,AK18>0),ROUNDUP(AH18/AK18,0)*COST_40HQ,0) -> 10064 | BU18: =IF(AH18<=0,"",IF(BR18<=MIN(BS18,BT18),"LCL",IF(BS18<=BT18,"20GP","40HQ"))) -> LCL | BV18: =TRIM(IF(AH18<V18,"Below MOQ. ","")&IF(AM18>1,"Needs "&AM18&" containers. ","")&IF(ISNUMBER(AN18),IF(AN18<0.85,"Box only "&TEXT(AN18,"0%")&" full – whole box charged. ",""),"")&IF(AND(BU18<>"",BU18<>AG18),"Cheaper freight at this qty: "&BU18&". ","")&IF(ISNUMBER(N18),IF(N18<0,"Price above price to beat. ",IF(N18<TARGET_DISC-0.0005,"Discount below target. ","")),"")&IF(U18<=0,"FOB missing. ","")&IF(N(X18)=0,"Carton kg missing. ","")&IF(BE18<0,"Loss-making. ","")&IF(ISNUMBER(BQ18),IF(BQ18>AH18,"Cash not recovered even if all units sell. ",""),"")) | BW18: A$95 is ~10% under Costway's A$105.95 and ~20% under Amazon's ~A$119. FOB and carton verified (US$20–21, 0.061 CBM). Best economics of the outdoor three: ~A$28.58/unit (33%) on a ~A$10.8k first LCL. Seasonal; trader suppliers; Crazy Sales sold a comparable set at A$84.95–89.95 off-season. | BX18: Lounger US$20–21 at MOQ 200 (verify: US$21 first order, US$20.50 for a 20GP, US$20 for a 40HQ). Factory alt: Ningbo Xusheng US$27–35 (MOQ 560, 0.0497 CBM, 14 kg). | BY18: 116×22×24 cm = 0.0612 CBM, 11 kg (cited). | BZ18: Labels A$500 per order (EST). No gas, electrical or mandatory standard found; specify steel or no spreader bars, no bamboo/timber parts and non-timber packaging. 5% general. | CA18: Crazy Sales double hammock + stand A$129.96 (A$84.95–89.95 May–Aug 2026); Kmart Marketplace 2-in-1 A$115.99; Amazon SELFLA stand-only A$99.99. | CB18: verify_outdoor.md Q2
A19: 15 | B19: Outdoor living | C19: Foldable hanging egg chair | D19: Collapsible PE-rattan hanging egg chair with foldable steel stand (Fanpin LX0124), max 120 kg | E19: REVISED | F19: 5 | G19: 4 | H19: 173.95 | I19: Kmart Marketplace – Gardeon egg swing chair pod (Amazon AU Gardeon foldable A$209.95, search summary) | J19: Undated search summary | K19: 159 | L19: =IF(H19>0,H19*(1-TARGET_DISC),"") -> 156.555 | M19: =IF(AND(PRICE_MODE="Rule",ISNUMBER(L19)),L19,K19) -> 159 | N19: =IF(AND(H19>0,M19>0),1-M19/H19,"") -> 0.085944237 | O19: Shangqiu Fanpin Crafts (Henan) | P19: Manufacturer | Q19: https://fanpin.en.made-in-china.com/product/JTwUWsrvCKRc/China-Wholesale-Foldable-Steel-Outdoor-Furniture-Garden-Balcony-Patio-Swing-Egg-Hanging-Chair.html | R19: 50 | S19: per set (10–399 tier) | T19: 1 | U19: =R19*T19 -> 50 | V19: 10 | W19: 0.1426 | X19: 25 | Y19: 500 | Z19: 0 | AA19: 0 | AB19: 0 | AC19: No | AD19: Per CBM | AF19: 1 | AG19: 20GP | AH19: 196 | AI19: =U19*USD_TO_AUD -> 71.880391 | AJ19: =IF(W19>0,IF(X19>0,MIN(INT(CBM_20GP/W19+0.000001),INT(KG_20GP/X19+0.000001)),INT(CBM_20GP/W19+0.000001)),0) -> 196 | AK19: =IF(W19>0,IF(X19>0,MIN(INT(CBM_40HQ/W19+0.000001),INT(KG_40HQ/X19+0.000001)),INT(CBM_40HQ/W19+0.000001)),0) -> 476 | AL19: =IF(AG19="20GP",AJ19,IF(AG19="40HQ",AK19,"LCL")) -> 196 | AM19: =IF(AH19<=0,0,IF(AG19="20GP",IF(AJ19>0,ROUNDUP(AH19/AJ19,0),0),IF(AG19="40HQ",IF(AK19>0,ROUNDUP(AH19/AK19,0),0),0))) -> 1 | AN19: =IF(OR(AG19="LCL",AM19=0),"",AH19/(AM19*AL19)) -> 1 | AO19: =AH19*W19 -> 27.9496 | AP19: =AH19*X19/1000 -> 4.9 | AQ19: =IF(AH19<=0,0,IF(AG19="LCL",LCL_RATE*MAX(AO19,AP19)+LCL_FIXED,AM19*IF(AG19="20GP",COST_20GP,COST_40HQ))) -> 5908 | AR19: =IF(AH19>0,AQ19/AH19,0) -> 30.142857 | AS19: =IF(AG19="20GP",IF(AJ19>0,COST_20GP/AJ19,0),IF(AG19="40HQ",IF(AK19>0,COST_40HQ/AK19,0),AR19)) -> 30.142857 | AT19: =IF(AC19="Yes",0,DUTY_APPLIED) -> 0 | AU19: =AI19*AT19 -> 0 | AV19: =IF(AH19>0,INSPECTION*AF19/AH19,0) -> 2.0408163 | AW19: =IF(AH19>0,Y19/AH19,0)+Z19+AA19*USD_TO_AUD -> 2.5510204 | AX19: =IF(AH19>0,(AB19+OTHER_FIXED)/AH19,0) -> 0 | AY19: =AI19+AR19+AU19+AV19+AW19+AX19 -> 106.61508 | AZ19: =IF(ISNUMBER(AE19),AE19,DEFECT_PCT) -> 0.03 | BA19: =AY19*AZ19 -> 3.1984525 | BB19: =IF(AD19="Flat",HANDLING_FLAT,STORAGE_PER_CBM*W19) -> 4.7058 | BC19: =AY19+BA19+BB19 -> 114.51934 | BD19: =M19/(1+GST_RATE)*(1-MP_FEE) -> 144.54545 | BE19: =BD19-BC19 -> 30.026117 | BF19: =IF(BD19<>0,BE19/BD19,0) -> 0.20772785 | BG19: =BE19*AH19 -> 5885.1189 | BH19: =BC19*AH19 -> 22445.79 | BI19: =GST_RATE*(AI19+AU19+GST_TI_SHARE*AR19)*AH19 -> 1763.3357 | BJ19: =BH19+BI19 -> 24209.126 | BK19: =((BD19-BB19)/(1+AZ19)-(AR19+AV19+AW19+AX19))/(1+AT19)*FX_AUDUSD -> 70.277832 | BL19: =IF(T19>0,BK19/T19,0) -> 70.277832 | BM19: =BC19*(1+GST_RATE)/(1-MP_FEE) -> 125.97127 | BN19: =IF(AH19<=0,0,INSPECTION*AF19+Y19+AB19+OTHER_FIXED+IF(AG19="LCL",LCL_FIXED,AQ19)) -> 6808 | BO19: =BD19-((AI19+AU19+Z19+AA19*USD_TO_AUD+IF(AND(AG19="LCL",AH19>0),LCL_RATE*MAX(AO19,AP19)/AH19,0))*(1+AZ19)+BB19) -> 65.802852 | BP19: =IF(AH19<=0,"",IF(BO19>0,ROUNDUP(BN19*(1+AZ19)/BO19,0),"Never")) -> 107 | BQ19: =IF(AH19<=0,"",IF(BD19>0,ROUNDUP(BH19/BD19,0),"Never")) -> 156 | BR19: =IF(AH19>0,LCL_RATE*MAX(AO19,AP19)+LCL_FIXED,0) -> 7719.7024 | BS19: =IF(AND(AH19>0,AJ19>0),ROUNDUP(AH19/AJ19,0)*COST_20GP,0) -> 5908 | BT19: =IF(AND(AH19>0,AK19>0),ROUNDUP(AH19/AK19,0)*COST_40HQ,0) -> 10064 | BU19: =IF(AH19<=0,"",IF(BR19<=MIN(BS19,BT19),"LCL",IF(BS19<=BT19,"20GP","40HQ"))) -> 20GP | BV19: =TRIM(IF(AH19<V19,"Below MOQ. ","")&IF(AM19>1,"Needs "&AM19&" containers. ","")&IF(ISNUMBER(AN19),IF(AN19<0.85,"Box only "&TEXT(AN19,"0%")&" full – whole box charged. ",""),"")&IF(AND(BU19<>"",BU19<>AG19),"Cheaper freight at this qty: "&BU19&". ","")&IF(ISNUMBER(N19),IF(N19<0,"Price above price to beat. ",IF(N19<TARGET_DISC-0.0005,"Discount below target. ","")),"")&IF(U19<=0,"FOB missing. ","")&IF(N(X19)=0,"Carton kg missing. ","")&IF(BE19<0,"Loss-making. ","")&IF(ISNUMBER(BQ19),IF(BQ19>AH19,"Cash not recovered even if all units sell. ",""),"")) -> Discount below target. | BW19: Verified foldable cartons (0.143–0.204 CBM) make costs workable, but the realistic price is A$149–159 (Kmart Marketplace A$173.95, Crazy Sales A$139.95, Bunnings A$199) and the category is saturated. A first order only works as a full 20GP (~A$30/unit). | BX19: Fanpin foldable LX0124 US$50 (10–399) / US$48 (400+). Fanpin's US$37 listing (MOQ 100) is NOT described as foldable and has no carton data. Alt: Yongkang Dashing DS-FEC01 US$31.20–47.80 (0.204 CBM, 23 kg). | BY19: 115×62×20 cm = 0.1426 CBM (verify rounds to 0.143), 25 kg (cited). 0.1426 lets 196 chairs fit a 20GP, as in the verify note. | BZ19: Labels A$500 per order (EST). State 'synthetic PE rattan, powder-coated steel, no bamboo/cane/timber' on the PO and invoice; non-timber packaging. 5% general. | CA19: Bunnings Marquee collapsible A$199; Crazy Sales foldable frame chair A$139.95; Sydney Marketplace 'brand new' egg chairs ~A$200 and a A$90 clearance. | CB19: verify_outdoor.md Q3
A20: 16 | B20: Camping & 4WD | C20: 4WD recovery kit | D20: 4WD recovery kit, 8–11 piece (snatch strap, extension strap, tree protector, shackles, bag); straps labelled to the AU mandatory standard | E20: REVISED | F20: 6 | G20: 4 | H20: 119.99 | I20: BCF / Supercheap – XTM 7-piece recovery kit (PLU 600254), Club price (free sign-up); Amazon AU Kings Hercules kit + light A$148.95 | J20: 9 Oct 2026 | K20: 119 | L20: =IF(H20>0,H20*(1-TARGET_DISC),"") -> 107.991 | M20: =IF(AND(PRICE_MODE="Rule",ISNUMBER(L20)),L20,K20) -> 119 | N20: =IF(AND(H20>0,M20>0),1-M20/H20,"") -> 0.0082506876 | O20: Qingdao Thinkwell Hardware & Machinery | P20: Manufacturer & trading (self-described) | Q20: https://thinkwell.en.made-in-china.com/product/LoUEjqrvhwtf/China-4X4-off-Road-Recovery-Tow-Strap-Recovery-Kit.html | R20: 35 | S20: per set (100–499 tier) | T20: 1 | U20: =R20*T20 -> 35 | V20: 100 | W20: 0.025 | X20: 10 | Y20: 4000 | Z20: 0 | AA20: 1 | AB20: 0 | AC20: No | AD20: Flat | AF20: 1 | AG20: LCL | AH20: 200 | AI20: =U20*USD_TO_AUD -> 50.316274 | AJ20: =IF(W20>0,IF(X20>0,MIN(INT(CBM_20GP/W20+0.000001),INT(KG_20GP/X20+0.000001)),INT(CBM_20GP/W20+0.000001)),0) -> 1120 | AK20: =IF(W20>0,IF(X20>0,MIN(INT(CBM_40HQ/W20+0.000001),INT(KG_40HQ/X20+0.000001)),INT(CBM_40HQ/W20+0.000001)),0) -> 2200 | AL20: =IF(AG20="20GP",AJ20,IF(AG20="40HQ",AK20,"LCL")) -> LCL | AM20: =IF(AH20<=0,0,IF(AG20="20GP",IF(AJ20>0,ROUNDUP(AH20/AJ20,0),0),IF(AG20="40HQ",IF(AK20>0,ROUNDUP(AH20/AK20,0),0),0))) -> 0 | AN20: =IF(OR(AG20="LCL",AM20=0),"",AH20/(AM20*AL20)) | AO20: =AH20*W20 -> 5 | AP20: =AH20*X20/1000 -> 2 | AQ20: =IF(AH20<=0,0,IF(AG20="LCL",LCL_RATE*MAX(AO20,AP20)+LCL_FIXED,AM20*IF(AG20="20GP",COST_20GP,COST_40HQ))) -> 2120 | AR20: =IF(AH20>0,AQ20/AH20,0) -> 10.6 | AS20: =IF(AG20="20GP",IF(AJ20>0,COST_20GP/AJ20,0),IF(AG20="40HQ",IF(AK20>0,COST_40HQ/AK20,0),AR20)) -> 10.6 | AT20: =IF(AC20="Yes",0,DUTY_APPLIED) -> 0 | AU20: =AI20*AT20 -> 0 | AV20: =IF(AH20>0,INSPECTION*AF20/AH20,0) -> 2 | AW20: =IF(AH20>0,Y20/AH20,0)+Z20+AA20*USD_TO_AUD -> 21.437608 | AX20: =IF(AH20>0,(AB20+OTHER_FIXED)/AH20,0) -> 0 | AY20: =AI20+AR20+AU20+AV20+AW20+AX20 -> 84.353882 | AZ20: =IF(ISNUMBER(AE20),AE20,DEFECT_PCT) -> 0.03 | BA20: =AY20*AZ20 -> 2.5306164 | BB20: =IF(AD20="Flat",HANDLING_FLAT,STORAGE_PER_CBM*W20) -> 5 | BC20: =AY20+BA20+BB20 -> 91.884498 | BD20: =M20/(1+GST_RATE)*(1-MP_FEE) -> 108.18182 | BE20: =BD20-BC20 -> 16.29732 | BF20: =IF(BD20<>0,BE20/BD20,0) -> 0.1506475 | BG20: =BE20*AH20 -> 3259.464 | BH20: =BC20*AH20 -> 18376.9 | BI20: =GST_RATE*(AI20+AU20+GST_TI_SHARE*AR20)*AH20 -> 1133.5255 | BJ20: =BH20+BI20 -> 19510.425 | BK20: =((BD20-BB20)/(1+AZ20)-(AR20+AV20+AW20+AX20))/(1+AT20)*FX_AUDUSD -> 46.006229 | BL20: =IF(T20>0,BK20/T20,0) -> 46.006229 | BM20: =BC20*(1+GST_RATE)/(1-MP_FEE) -> 101.07295 | BN20: =IF(AH20<=0,0,INSPECTION*AF20+Y20+AB20+OTHER_FIXED+IF(AG20="LCL",LCL_FIXED,AQ20)) -> 5300 | BO20: =BD20-((AI20+AU20+Z20+AA20*USD_TO_AUD+IF(AND(AG20="LCL",AH20>0),LCL_RATE*MAX(AO20,AP20)/AH20,0))*(1+AZ20)+BB20) -> 43.59232 | BP20: =IF(AH20<=0,"",IF(BO20>0,ROUNDUP(BN20*(1+AZ20)/BO20,0),"Never")) -> 126 | BQ20: =IF(AH20<=0,"",IF(BD20>0,ROUNDUP(BH20/BD20,0),"Never")) -> 170 | BR20: =IF(AH20>0,LCL_RATE*MAX(AO20,AP20)+LCL_FIXED,0) -> 2120 | BS20: =IF(AND(AH20>0,AJ20>0),ROUNDUP(AH20/AJ20,0)*COST_20GP,0) -> 5908 | BT20: =IF(AND(AH20>0,AK20>0),ROUNDUP(AH20/AK20,0)*COST_40HQ,0) -> 10064 | BU20: =IF(AH20<=0,"",IF(BR20<=MIN(BS20,BT20),"LCL",IF(BS20<=BT20,"20GP","40HQ"))) -> LCL | BV20: =TRIM(IF(AH20<V20,"Below MOQ. ","")&IF(AM20>1,"Needs "&AM20&" containers. ","")&IF(ISNUMBER(AN20),IF(AN20<0.85,"Box only "&TEXT(AN20,"0%")&" full – whole box charged. ",""),"")&IF(AND(BU20<>"",BU20<>AG20),"Cheaper freight at this qty: "&BU20&". ","")&IF(ISNUMBER(N20),IF(N20<0,"Price above price to beat. ",IF(N20<TARGET_DISC-0.0005,"Discount below target. ","")),"")&IF(U20<=0,"FOB missing. ","")&IF(N(X20)=0,"Carton kg missing. ","")&IF(BE20<0,"Loss-making. ","")&IF(ISNUMBER(BQ20),IF(BQ20>AH20,"Cash not recovered even if all units sell. ",""),"")) -> Discount below target. | BW20: The binding floor is Super Retail Group's XTM 7-piece at A$119.99 Club (Amazon: Kings A$148.95), so A$119 barely undercuts it. A mandatory snatch-strap labelling standard, break tests and liability cover add ~A$4k fixed: 100 kits lose money, 200 kits make ~7–15%, a full 20GP ~30–41%. | BX20: Thinkwell US$35 (100–499) / US$32 (500+); contents NOT itemised (no snatch block listed). Itemised alt: Tianshun US$90 (100–999) / US$80 – loss-making. Plus US$1/unit AU strap labels and print (ASSUMPTION). | BY20: 0.025 CBM / 10 kg ESTIMATE from the X-BULL 11-pc Amazon package (0.0237 CBM, 11.92 kg); no kit supplier gives carton data. | BZ20: A$4,000 per order = A$2,500 independent break tests + A$1,500 product-liability cover (ASSUMPTIONS) + US$1/unit labels. Consumer Goods (Motor Vehicle Recovery Straps) Safety Standard 2017 (mandatory labelling). Flat A$5 handling. 5% general. | CA20: XTM 7-piece A$149.99 (BCF) / A$169.99 (Supercheap) non-member; Kings Hercules 11-piece A$199 direct; X-BULL 11-pc A$159 (Amazon). | CB20: verify_camping_appliance.md Q2–Q3
A21: 17 | B21: Camping & 4WD | C21: Alu camp kitchen + cupboards | D21: Aluminium folding camp kitchen 146×46×80 cm with windscreen + 3 storage cupboards, 30 kg load (Welfull CT016) | E21: REVISED (numbers) | F21: 5 | G21: 5 | H21: 129.99 | I21: BCF – Wanderer Premium Series Dual Cupboard Kitchen (PLU 520333), Club price; Supercheap clearance A$99 | J21: 9 Oct 2026 | K21: 99 | L21: =IF(H21>0,H21*(1-TARGET_DISC),"") -> 116.991 | M21: =IF(AND(PRICE_MODE="Rule",ISNUMBER(L21)),L21,K21) -> 99 | N21: =IF(AND(H21>0,M21>0),1-M21/H21,"") -> 0.23840295 | O21: Welfull Group (Hangzhou) | P21: Unknown – not stated (BV-audited) | Q21: https://welfull-outdoors.en.made-in-china.com/product/kfFpBKvoLRhH/China-Camping-Kitchen-Table-Aluminum-Portable-Outdoor-Cooking-Table-with-Windscreen-and-3-Storage-Cupboards-for-Outdoor-Activities.html | R21: 29.5 | S21: per unit (top of US$25–29.50, MOQ 500) | T21: 1 | U21: =R21*T21 -> 29.5 | V21: 500 | W21: 0.0547 | X21: 12 | Y21: 0 | Z21: 0 | AA21: 0 | AB21: 0 | AC21: No | AD21: Flat | AF21: 1 | AG21: 20GP | AH21: 500 | AI21: =U21*USD_TO_AUD -> 42.409431 | AJ21: =IF(W21>0,IF(X21>0,MIN(INT(CBM_20GP/W21+0.000001),INT(KG_20GP/X21+0.000001)),INT(CBM_20GP/W21+0.000001)),0) -> 511 | AK21: =IF(W21>0,IF(X21>0,MIN(INT(CBM_40HQ/W21+0.000001),INT(KG_40HQ/X21+0.000001)),INT(CBM_40HQ/W21+0.000001)),0) -> 1243 | AL21: =IF(AG21="20GP",AJ21,IF(AG21="40HQ",AK21,"LCL")) -> 511 | AM21: =IF(AH21<=0,0,IF(AG21="20GP",IF(AJ21>0,ROUNDUP(AH21/AJ21,0),0),IF(AG21="40HQ",IF(AK21>0,ROUNDUP(AH21/AK21,0),0),0))) -> 1 | AN21: =IF(OR(AG21="LCL",AM21=0),"",AH21/(AM21*AL21)) -> 0.97847358 | AO21: =AH21*W21 -> 27.35 | AP21: =AH21*X21/1000 -> 6 | AQ21: =IF(AH21<=0,0,IF(AG21="LCL",LCL_RATE*MAX(AO21,AP21)+LCL_FIXED,AM21*IF(AG21="20GP",COST_20GP,COST_40HQ))) -> 5908 | AR21: =IF(AH21>0,AQ21/AH21,0) -> 11.816 | AS21: =IF(AG21="20GP",IF(AJ21>0,COST_20GP/AJ21,0),IF(AG21="40HQ",IF(AK21>0,COST_40HQ/AK21,0),AR21)) -> 11.561644 | AT21: =IF(AC21="Yes",0,DUTY_APPLIED) -> 0 | AU21: =AI21*AT21 -> 0 | AV21: =IF(AH21>0,INSPECTION*AF21/AH21,0) -> 0.8 | AW21: =IF(AH21>0,Y21/AH21,0)+Z21+AA21*USD_TO_AUD -> 0 | AX21: =IF(AH21>0,(AB21+OTHER_FIXED)/AH21,0) -> 0 | AY21: =AI21+AR21+AU21+AV21+AW21+AX21 -> 55.025431 | AZ21: =IF(ISNUMBER(AE21),AE21,DEFECT_PCT) -> 0.03 | BA21: =AY21*AZ21 -> 1.6507629 | BB21: =IF(AD21="Flat",HANDLING_FLAT,STORAGE_PER_CBM*W21) -> 5 | BC21: =AY21+BA21+BB21 -> 61.676194 | BD21: =M21/(1+GST_RATE)*(1-MP_FEE) -> 90 | BE21: =BD21-BC21 -> 28.323806 | BF21: =IF(BD21<>0,BE21/BD21,0) -> 0.31470896 | BG21: =BE21*AH21 -> 14161.903 | BH21: =BC21*AH21 -> 30838.097 | BI21: =GST_RATE*(AI21+AU21+GST_TI_SHARE*AR21)*AH21 -> 2474.9515 | BJ21: =BH21+BI21 -> 33313.048 | BK21: =((BD21-BB21)/(1+AZ21)-(AR21+AV21+AW21+AX21))/(1+AT21)*FX_AUDUSD -> 48.628194 | BL21: =IF(T21>0,BK21/T21,0) -> 48.628194 | BM21: =BC21*(1+GST_RATE)/(1-MP_FEE) -> 67.843813 | BN21: =IF(AH21<=0,0,INSPECTION*AF21+Y21+AB21+OTHER_FIXED+IF(AG21="LCL",LCL_FIXED,AQ21)) -> 6308 | BO21: =BD21-((AI21+AU21+Z21+AA21*USD_TO_AUD+IF(AND(AG21="LCL",AH21>0),LCL_RATE*MAX(AO21,AP21)/AH21,0))*(1+AZ21)+BB21) -> 41.318286 | BP21: =IF(AH21<=0,"",IF(BO21>0,ROUNDUP(BN21*(1+AZ21)/BO21,0),"Never")) -> 158 | BQ21: =IF(AH21<=0,"",IF(BD21>0,ROUNDUP(BH21/BD21,0),"Never")) -> 343 | BR21: =IF(AH21>0,LCL_RATE*MAX(AO21,AP21)+LCL_FIXED,0) -> 7573.4 | BS21: =IF(AND(AH21>0,AJ21>0),ROUNDUP(AH21/AJ21,0)*COST_20GP,0) -> 5908 | BT21: =IF(AND(AH21>0,AK21>0),ROUNDUP(AH21/AK21,0)*COST_40HQ,0) -> 10064 | BU21: =IF(AH21<=0,"",IF(BR21<=MIN(BS21,BT21),"LCL",IF(BS21<=BT21,"20GP","40HQ"))) -> 20GP | BV21: =TRIM(IF(AH21<V21,"Below MOQ. ","")&IF(AM21>1,"Needs "&AM21&" containers. ","")&IF(ISNUMBER(AN21),IF(AN21<0.85,"Box only "&TEXT(AN21,"0%")&" full – whole box charged. ",""),"")&IF(AND(BU21<>"",BU21<>AG21),"Cheaper freight at this qty: "&BU21&". ","")&IF(ISNUMBER(N21),IF(N21<0,"Price above price to beat. ",IF(N21<TARGET_DISC-0.0005,"Discount below target. ","")),"")&IF(U21<=0,"FOB missing. ","")&IF(N(X21)=0,"Carton kg missing. ","")&IF(BE21<0,"Loss-making. ","")&IF(ISNUMBER(BQ21),IF(BQ21>AH21,"Cash not recovered even if all units sell. ",""),"")) | BW21: The MOQ-500 thesis holds: ~31% GP at A$99 in one 20GP (~A$27.5k cash). But the Wanderer is A$99 clearance / A$129.99 Club, so A$109 is upside only. The 100-unit fallback loses money; ~300 units by LCL works only if Ningbo Eto quotes ≤US$30. | BX21: Welfull CT016 US$25.00–29.50, MOQ 500 (verify base = top of range; US$25 → GP A$34.99). Alts: Ningbo Eto US$12–30 (MOQ 300, 0.055 CBM, 11 kg); Ningbo General Union (trader) US$41 (100–1,999) – loss-making. | BY21: 0.0547 CBM / 12 kg ESTIMATE from identical-spec Eto / Dashing packages (Welfull gives no carton size). | BZ21: No mandatory standard identified; no compliance cost. Flat A$5 handling. 5% general. | CA21: Wanderer Dual Cupboard A$99 clearance (Supercheap) / A$199.99 non-member (BCF); Kmart simpler camp kitchen A$70 RRP. | CB21: verify_camping_appliance.md Q4
A22: 18 | B22: Appliances | C22: 2000W pressure washer | D22: 2000W induction-motor electric pressure washer, 125 bar, 5.5 L/min, 7 m hose, auto-stop (TOLHIT); AU plug + RCM label | E22: REVISED | F22: 5 | G22: 3 | H22: 99 | I22: Bunnings – Ozito 1800W 2030 PSI (comparable spec); Aldi Ferrex 1600W and Supercheap ToolPRO A$89.99 | J22: Undated search summary (Bunnings returned 403) | K22: 99 | L22: =IF(H22>0,H22*(1-TARGET_DISC),"") -> 89.1 | M22: =IF(AND(PRICE_MODE="Rule",ISNUMBER(L22)),L22,K22) -> 99 | N22: =IF(AND(H22>0,M22>0),1-M22/H22,"") -> 0 | O22: Yuyao Goldsen International Trade (TOLHIT) | P22: Unknown – not stated ('International Trade' name; probable trader) | Q22: https://goldsen.en.made-in-china.com/product/OnRpWvrdEUcw/China-Tolhit-220V-125bar-2000W-Portable-Electric-Power-Adjustable-High-Pressure-Car-Washer.html | R22: 34 | S22: per unit (500–999 tier) | T22: 1 | U22: =R22*T22 -> 34 | V22: 500 | W22: 0.0214 | Y22: 739.74 | Z22: 0 | AA22: 1 | AB22: 0 | AC22: No | AD22: Flat | AE22: 0.05 | AF22: 1 | AG22: LCL | AH22: 500 | AI22: =U22*USD_TO_AUD -> 48.878666 | AJ22: =IF(W22>0,IF(X22>0,MIN(INT(CBM_20GP/W22+0.000001),INT(KG_20GP/X22+0.000001)),INT(CBM_20GP/W22+0.000001)),0) -> 1308 | AK22: =IF(W22>0,IF(X22>0,MIN(INT(CBM_40HQ/W22+0.000001),INT(KG_40HQ/X22+0.000001)),INT(CBM_40HQ/W22+0.000001)),0) -> 3177 | AL22: =IF(AG22="20GP",AJ22,IF(AG22="40HQ",AK22,"LCL")) -> LCL | AM22: =IF(AH22<=0,0,IF(AG22="20GP",IF(AJ22>0,ROUNDUP(AH22/AJ22,0),0),IF(AG22="40HQ",IF(AK22>0,ROUNDUP(AH22/AK22,0),0),0))) -> 0 | AN22: =IF(OR(AG22="LCL",AM22=0),"",AH22/(AM22*AL22)) | AO22: =AH22*W22 -> 10.7 | AP22: =AH22*X22/1000 -> 0 | AQ22: =IF(AH22<=0,0,IF(AG22="LCL",LCL_RATE*MAX(AO22,AP22)+LCL_FIXED,AM22*IF(AG22="20GP",COST_20GP,COST_40HQ))) -> 3510.8 | AR22: =IF(AH22>0,AQ22/AH22,0) -> 7.0216 | AS22: =IF(AG22="20GP",IF(AJ22>0,COST_20GP/AJ22,0),IF(AG22="40HQ",IF(AK22>0,COST_40HQ/AK22,0),AR22)) -> 7.0216 | AT22: =IF(AC22="Yes",0,DUTY_APPLIED) -> 0 | AU22: =AI22*AT22 -> 0 | AV22: =IF(AH22>0,INSPECTION*AF22/AH22,0) -> 0.8 | AW22: =IF(AH22>0,Y22/AH22,0)+Z22+AA22*USD_TO_AUD -> 2.9170878 | AX22: =IF(AH22>0,(AB22+OTHER_FIXED)/AH22,0) -> 0 | AY22: =AI22+AR22+AU22+AV22+AW22+AX22 -> 59.617354 | AZ22: =IF(ISNUMBER(AE22),AE22,DEFECT_PCT) -> 0.05 | BA22: =AY22*AZ22 -> 2.9808677 | BB22: =IF(AD22="Flat",HANDLING_FLAT,STORAGE_PER_CBM*W22) -> 5 | BC22: =AY22+BA22+BB22 -> 67.598221 | BD22: =M22/(1+GST_RATE)*(1-MP_FEE) -> 90 | BE22: =BD22-BC22 -> 22.401779 | BF22: =IF(BD22<>0,BE22/BD22,0) -> 0.24890865 | BG22: =BE22*AH22 -> 11200.889 | BH22: =BC22*AH22 -> 33799.111 | BI22: =GST_RATE*(AI22+AU22+GST_TI_SHARE*AR22)*AH22 -> 2654.5813 | BJ22: =BH22+BI22 -> 36453.692 | BK22: =((BD22-BB22)/(1+AZ22)-(AR22+AV22+AW22+AX22))/(1+AT22)*FX_AUDUSD -> 48.840645 | BL22: =IF(T22>0,BK22/T22,0) -> 48.840645 | BM22: =BC22*(1+GST_RATE)/(1-MP_FEE) -> 74.358044 | BN22: =IF(AH22<=0,0,INSPECTION*AF22+Y22+AB22+OTHER_FIXED+IF(AG22="LCL",LCL_FIXED,AQ22)) -> 2039.74 | BO22: =BD22-((AI22+AU22+Z22+AA22*USD_TO_AUD+IF(AND(AG22="LCL",AH22>0),LCL_RATE*MAX(AO22,AP22)/AH22,0))*(1+AZ22)+BB22) -> 26.685233 | BP22: =IF(AH22<=0,"",IF(BO22>0,ROUNDUP(BN22*(1+AZ22)/BO22,0),"Never")) -> 81 | BQ22: =IF(AH22<=0,"",IF(BD22>0,ROUNDUP(BH22/BD22,0),"Never")) -> 376 | BR22: =IF(AH22>0,LCL_RATE*MAX(AO22,AP22)+LCL_FIXED,0) -> 3510.8 | BS22: =IF(AND(AH22>0,AJ22>0),ROUNDUP(AH22/AJ22,0)*COST_20GP,0) -> 5908 | BT22: =IF(AND(AH22>0,AK22>0),ROUNDUP(AH22/AK22,0)*COST_40HQ,0) -> 10064 | BU22: =IF(AH22<=0,"",IF(BR22<=MIN(BS22,BT22),"LCL",IF(BS22<=BT22,"20GP","40HQ"))) -> LCL | BV22: =TRIM(IF(AH22<V22,"Below MOQ. ","")&IF(AM22>1,"Needs "&AM22&" containers. ","")&IF(ISNUMBER(AN22),IF(AN22<0.85,"Box only "&TEXT(AN22,"0%")&" full – whole box charged. ",""),"")&IF(AND(BU22<>"",BU22<>AG22),"Cheaper freight at this qty: "&BU22&". ","")&IF(ISNUMBER(N22),IF(N22<0,"Price above price to beat. ",IF(N22<TARGET_DISC-0.0005,"Discount below target. ","")),"")&IF(U22<=0,"FOB missing. ","")&IF(N(X22)=0,"Carton kg missing. ","")&IF(BE22<0,"Loss-making. ","")&IF(ISNUMBER(BQ22),IF(BQ22>AH22,"Cash not recovered even if all units sell. ",""),"")) -> Discount below target. Carton kg missing. | BW22: Bunnings, Aldi and Supercheap sell comparable branded units at A$89.99–99 with returns, so A$89–99 is the ceiling. Only a ~US$34 2000W induction unit at MOQ 500 clears ~25% at A$99, and only if the factory's CB/EMC reports can be reused (~13% with new AU testing). | BX22: TOLHIT US$34.00 (500–999) / US$33.50 (1,000–2,999) / US$32.90 (3,000+). Alts: Taizhou Ruiying Ry25s US$36.50–37.30 (90 bar); EBIC 2000W brush US$54.90 – loss-making. Plus US$1/unit AU plug, RCM label and manual (ASSUMPTION). | BY22: 38.5×18.5×30 cm = 0.0214 CBM (cited; listing says 1,350 per 20GP). Gross kg MISSING – left blank (weight caps and LCL W/M then use CBM only). | BZ22: Scenario A A$739.74 one-off = EESS Responsible Supplier A$239.74 + A$500 review of the factory's CB/EMC reports (ASSUMPTION), plus US$1/unit plug/label. Scenario B adds ~A$5,000 AS/NZS 60335.2.79 + CISPR 14-1 testing. EESS Level 1 (no CoC). Defect allowance 5% for electricals. | CA22: Ferrex 2000W A$149 (Aldi); Kmart 1600W A$55–89; Bosch 1500W A$169 (Amazon). | CB22: verify_camping_appliance.md Q5–Q6
A23: 19 | B23: Camping & 4WD | C23: Recovery kit + tracks bundle | D23: 4WD recovery kit + pair of recovery traction tracks (Thinkwell kit + Workercare tracks) – variant of SKU 16, two factories | E23: BROKEN at 100; marginal at 200 | G23: 3 | H23: 209 | I23: Amazon AU – generic 15-piece 'Recovery Tracks Kit … Tow Strap Winch Damper Folding Shovel' (Best Sellers 'Recovery Straps') | J23: 9 Oct 2026 (lowest listed offer) | K23: 179 | L23: =IF(H23>0,H23*(1-TARGET_DISC),"") -> 188.1 | M23: =IF(AND(PRICE_MODE="Rule",ISNUMBER(L23)),L23,K23) -> 179 | N23: =IF(AND(H23>0,M23>0),1-M23/H23,"") -> 0.14354067 | O23: Qingdao Thinkwell (kit) + Qingdao Workercare Tools (tracks) | P23: Manufacturer & trading (both) | Q23: https://thinkwell.en.made-in-china.com/product/LoUEjqrvhwtf/China-4X4-off-Road-Recovery-Tow-Strap-Recovery-Kit.html | R23: 54.7 | S23: per bundle (kit US$35 + tracks US$19.70) | T23: 1 | U23: =R23*T23 -> 54.7 | V23: 100 | W23: 0.072 | X23: 15.6 | Y23: 4000 | Z23: 0 | AA23: 1 | AB23: 0 | AC23: No | AD23: Flat | AF23: 2 | AG23: LCL | AH23: 100 | AI23: =U23*USD_TO_AUD -> 78.637148 | AJ23: =IF(W23>0,IF(X23>0,MIN(INT(CBM_20GP/W23+0.000001),INT(KG_20GP/X23+0.000001)),INT(CBM_20GP/W23+0.000001)),0) -> 388 | AK23: =IF(W23>0,IF(X23>0,MIN(INT(CBM_40HQ/W23+0.000001),INT(KG_40HQ/X23+0.000001)),INT(CBM_40HQ/W23+0.000001)),0) -> 944 | AL23: =IF(AG23="20GP",AJ23,IF(AG23="40HQ",AK23,"LCL")) -> LCL | AM23: =IF(AH23<=0,0,IF(AG23="20GP",IF(AJ23>0,ROUNDUP(AH23/AJ23,0),0),IF(AG23="40HQ",IF(AK23>0,ROUNDUP(AH23/AK23,0),0),0))) -> 0 | AN23: =IF(OR(AG23="LCL",AM23=0),"",AH23/(AM23*AL23)) | AO23: =AH23*W23 -> 7.2 | AP23: =AH23*X23/1000 -> 1.56 | AQ23: =IF(AH23<=0,0,IF(AG23="LCL",LCL_RATE*MAX(AO23,AP23)+LCL_FIXED,AM23*IF(AG23="20GP",COST_20GP,COST_40HQ))) -> 2656.8 | AR23: =IF(AH23>0,AQ23/AH23,0) -> 26.568 | AS23: =IF(AG23="20GP",IF(AJ23>0,COST_20GP/AJ23,0),IF(AG23="40HQ",IF(AK23>0,COST_40HQ/AK23,0),AR23)) -> 26.568 | AT23: =IF(AC23="Yes",0,DUTY_APPLIED) -> 0 | AU23: =AI23*AT23 -> 0 | AV23: =IF(AH23>0,INSPECTION*AF23/AH23,0) -> 8 | AW23: =IF(AH23>0,Y23/AH23,0)+Z23+AA23*USD_TO_AUD -> 41.437608 | AX23: =IF(AH23>0,(AB23+OTHER_FIXED)/AH23,0) -> 0 | AY23: =AI23+AR23+AU23+AV23+AW23+AX23 -> 154.64276 | AZ23: =IF(ISNUMBER(AE23),AE23,DEFECT_PCT) -> 0.03 | BA23: =AY23*AZ23 -> 4.6392827 | BB23: =IF(AD23="Flat",HANDLING_FLAT,STORAGE_PER_CBM*W23) -> 5 | BC23: =AY23+BA23+BB23 -> 164.28204 | BD23: =M23/(1+GST_RATE)*(1-MP_FEE) -> 162.72727 | BE23: =BD23-BC23 -> -1.5547655 | BF23: =IF(BD23<>0,BE23/BD23,0) -> -0.0095544252 | BG23: =BE23*AH23 -> -155.47655 | BH23: =BC23*AH23 -> 16428.204 | BI23: =GST_RATE*(AI23+AU23+GST_TI_SHARE*AR23)*AH23 -> 945.77948 | BJ23: =BH23+BI23 -> 17373.983 | BK23: =((BD23-BB23)/(1+AZ23)-(AR23+AV23+AW23+AX23))/(1+AT23)*FX_AUDUSD -> 53.650005 | BL23: =IF(T23>0,BK23/T23,0) -> 53.650005 | BM23: =BC23*(1+GST_RATE)/(1-MP_FEE) -> 180.71024 | BN23: =IF(AH23<=0,0,INSPECTION*AF23+Y23+AB23+OTHER_FIXED+IF(AG23="LCL",LCL_FIXED,AQ23)) -> 5700 | BO23: =BD23-((AI23+AU23+Z23+AA23*USD_TO_AUD+IF(AND(AG23="LCL",AH23>0),LCL_RATE*MAX(AO23,AP23)/AH23,0))*(1+AZ23)+BB23) -> 57.155234 | BP23: =IF(AH23<=0,"",IF(BO23>0,ROUNDUP(BN23*(1+AZ23)/BO23,0),"Never")) -> 103 | BQ23: =IF(AH23<=0,"",IF(BD23>0,ROUNDUP(BH23/BD23,0),"Never")) -> 101 | BR23: =IF(AH23>0,LCL_RATE*MAX(AO23,AP23)+LCL_FIXED,0) -> 2656.8 | BS23: =IF(AND(AH23>0,AJ23>0),ROUNDUP(AH23/AJ23,0)*COST_20GP,0) -> 5908 | BT23: =IF(AND(AH23>0,AK23>0),ROUNDUP(AH23/AK23,0)*COST_40HQ,0) -> 10064 | BU23: =IF(AH23<=0,"",IF(BR23<=MIN(BS23,BT23),"LCL",IF(BS23<=BT23,"20GP","40HQ"))) -> LCL | BV23: =TRIM(IF(AH23<V23,"Below MOQ. ","")&IF(AM23>1,"Needs "&AM23&" containers. ","")&IF(ISNUMBER(AN23),IF(AN23<0.85,"Box only "&TEXT(AN23,"0%")&" full – whole box charged. ",""),"")&IF(AND(BU23<>"",BU23<>AG23),"Cheaper freight at this qty: "&BU23&". ","")&IF(ISNUMBER(N23),IF(N23<0,"Price above price to beat. ",IF(N23<TARGET_DISC-0.0005,"Discount below target. ","")),"")&IF(U23<=0,"FOB missing. ","")&IF(N(X23)=0,"Carton kg missing. ","")&IF(BE23<0,"Loss-making. ","")&IF(ISNUMBER(BQ23),IF(BQ23>AH23,"Cash not recovered even if all units sell. ",""),"")) -> Loss-making. Cash not recovered even if all units sell. | BW23: Amazon's cheapest kit + tracks bundle is A$209, so the rule price is A$167–188 (BCF XTM kit + boards A$217.98 Club). 100 bundles lose money at A$179 (−1%); 200 bundles make 12–17%; a 387-bundle 20GP 24.5–28.7%. (Original score not stated in the notes.) | BX23: Thinkwell kit US$35 (100–499) + Workercare tracks US$19.70/pair (100–499; US$18.50 500–1,399) = US$54.70, plus US$1/unit labels (ASSUMPTION). | BY23: Kit 0.025 CBM / 10 kg (EST) + tracks 110×33×13 cm = 0.047 CBM / 5.6 kg (cited) = 0.072 CBM / 15.6 kg. | BZ23: Same A$4,000 fixed stack as the kit (break tests + liability cover, ASSUMPTIONS) + US$1/unit labels. Two factories → two A$400 inspections. Flat A$5 handling. | CA23: X-Bull 13-pc kit + tracks A$219 (Amazon); BCF XTM kit A$119.99 + XTM Black Recovery Boards A$97.99 = A$217.98 Club. | CB23: verify_camping_appliance.md Q2 & Q7
A25: Method
A26: FOB (A$) = FOB as listed × listed units per sellable unit ÷ AUD/USD. Freight: LCL = A$/W/M × max(order CBM, order tonnes) + fixed fee; 20GP/40HQ = whole boxes × box cost, where units per box = the lesser of usable CBM ÷ carton CBM and weight cap ÷ carton kg (a part-filled box costs the whole box).
A27: Duty = FOB (A$) × 0% with a ChAFTA CoO or the general rate without one (0% for SKUs that are Free at the general rate). Inspection = A$ per factory ÷ qty. Compliance = one-off cost ÷ qty + per-unit A$ + per-unit US$ converted.
A28: Defect allowance = % × (FOB + freight + duty + inspection + compliance + extras). Storage = A$/CBM/month × months × carton CBM, or the flat handling charge. Landed = subtotal + allowance + storage. Net revenue = price ÷ (1 + GST) × (1 − Marketplace fee). GP % = GP ÷ net revenue.
A29: Cash = landed × qty (ex-GST); import-GST float = GST × (FOB + duty + T&I share × freight) × qty. Break-even FOB solves GP = 0 for the FOB. Payback of fixed costs = fixed costs × (1 + allowance) ÷ contribution per unit.

Sheet Mixed container
A1: Mixed container – combine verified SKUs in one 20GP or 40HQ
A2: Pick SKUs from the list (blue) and enter quantities. Unit costs, prices and compliance come from 'Products'. The box cost is allocated to each line by its chargeable share – the larger of its share of the weight cap or of the usable CBM – then normalised (verify_gym_pets.md method; it reduces to A$ per loaded CBM when every line is volume-bound, as in verify_outdoor.md). One A$400 inspection per supplier line. Optional: a sale-price override (blank = Products price) and an extra cost per line, e.g. China inland consolidation to the loading port. Overfilled boxes are flagged red.
B4: Mix 1 – Home-gym 20GP (pre-filled from verify_gym_pets.md Q5, mix M4: 150 bumper sets + 70 dial-dumbbell pairs)
B5: Notes (M4): 21,750 kg / 24.10 CBM; total GP A$15,751 (22.4% of net revenue); bumper A$79.71/set, pair A$54.20; cash A$53,005 excluding the 3% allowance and ≈A$4,872 GST float.
B6: Container type | C6: 20GP | D6: Box cost (A$) | F6: =IF(C6="20GP",COST_20GP,COST_40HQ) -> 5908 | G6: Usable CBM | I6: =IF(C6="20GP",CBM_20GP,CBM_40HQ) -> 28 | J6: Weight cap (kg) | L6: =IF(C6="20GP",KG_20GP,KG_40HQ) -> 21800
B8: Units | C8: CBM loaded | D8: CBM used % | E8: kg loaded | F8: Weight used % | G8: Load status | J8: Cash required ex-GST (A$) | K8: Import-GST float (A$) | L8: Cash incl. GST float (A$) | M8: Net revenue (A$) | N8: Total GP (A$) | O8: GP % of net revenue | P8: Stock to sell to recover cash
B9: =C20 -> 220 | C9: =J20 -> 24.1 | D9: =IF($I$6>0,J20/$I$6,0) -> 0.86071429 | E9: =K20 -> 21750 | F9: =IF($L$6>0,K20/$L$6,0) -> 0.99770642 | G9: =IF(OR(D9>1,F9>1),"OVERFILL – exceeds the "&IF(D9>1,"volume","")&IF(AND(D9>1,F9>1)," and ","")&IF(F9>1,"weight","")&" cap: cut quantities or add a box",IF(MAX(D9,F9)<0.9,"OK – "&TEXT(1-MAX(D9,F9),"0%")&" of the binding cap spare","OK – box effectively full")) -> OK – box effectively full | J9: =Z20 -> 54504.352 | K9: =AA20 -> 4868.5686 | L9: =J9+K9 -> 59372.921 | M9: =X20 -> 70345.455 | N9: =Y20 -> 15841.102 | O9: =IF(M9>0,N9/M9,0) -> 0.22519014 | P9: =IF(M9>0,J9/M9,0) -> 0.77480986
B11: SKU (pick) | C11: Quantity | D11: Sale price override (A$) | E11: Extra cost per line (A$) | F11: Sale price used (A$) | G11: FOB (A$/unit) | H11: CBM / unit | I11: kg / unit | J11: Line CBM | K11: Line kg | L11: Chargeable share | M11: Freight (A$/unit) | N11: Duty (A$/unit) | O11: Inspection (A$/unit) | P11: Compliance (A$/unit) | Q11: Extras incl. line cost (A$/unit) | R11: Defect allowance (A$/unit) | S11: Storage / handling (A$/unit) | T11: Landed (A$/unit) | U11: Net revenue (A$/unit) | V11: GP (A$/unit) | W11: GP % | X11: Line net revenue (A$) | Y11: Line GP (A$) | Z11: Line cash ex-GST (A$) | AA11: Line import-GST float (A$) | AB11: Products row (helper)
B12: 100kg bumper plate set | C12: 150 | F12: =IF($AB12="","",IF(ISNUMBER($D12),$D12,INDEX(Products!$M$5:$M$23,$AB12))) -> 339 | G12: =IF($AB12="","",INDEX(Products!$AI$5:$AI$23,$AB12)) -> 186.88902 | H12: =IF($AB12="","",INDEX(Products!$W$5:$W$23,$AB12)) -> 0.1 | I12: =IF($AB12="","",INDEX(Products!$X$5:$X$23,$AB12)+0) -> 103 | J12: =IF($AB12="","",$C12*$H12) -> 15 | K12: =IF($AB12="","",$C12*$I12) -> 15450 | L12: =IF($AB12="","",MAX(IF($L$6>0,$K12/$L$6,0),IF($I$6>0,$J12/$I$6,0))) -> 0.7087156 | M12: =IF($AB12="","",IF(SUM($L$12:$L$19)>0,($F$6+OTHER_FIXED)*$L12/SUM($L$12:$L$19)/$C12,0)) -> 27.003506 | N12: =IF($AB12="","",$G12*INDEX(Products!$AT$5:$AT$23,$AB12)) -> 0 | O12: =IF($AB12="","",INSPECTION*INDEX(Products!$AF$5:$AF$23,$AB12)/$C12) -> 2.6666667 | P12: =IF($AB12="","",INDEX(Products!$Y$5:$Y$23,$AB12)/$C12+INDEX(Products!$Z$5:$Z$23,$AB12)+INDEX(Products!$AA$5:$AA$23,$AB12)*USD_TO_AUD) -> 0 | Q12: =IF($AB12="","",(INDEX(Products!$AB$5:$AB$23,$AB12)+N($E12))/$C12) -> 0 | R12: =IF($AB12="","",($G12+$M12+$N12+$O12+$P12+$Q12)*INDEX(Products!$AZ$5:$AZ$23,$AB12)) -> 6.4967757 | S12: =IF($AB12="","",INDEX(Products!$BB$5:$BB$23,$AB12)) -> 5 | T12: =IF($AB12="","",$G12+$M12+$N12+$O12+$P12+$Q12+$R12+$S12) -> 228.05596 | U12: =IF($AB12="","",$F12/(1+GST_RATE)*(1-MP_FEE)) -> 308.18182 | V12: =IF($AB12="","",$U12-$T12) -> 80.125854 | W12: =IF($AB12="","",IF($U12<>0,$V12/$U12,0)) -> 0.25999539 | X12: =IF($AB12="","",$U12*$C12) -> 46227.273 | Y12: =IF($AB12="","",$V12*$C12) -> 12018.878 | Z12: =IF($AB12="","",$T12*$C12) -> 34208.395 | AA12: =IF($AB12="","",GST_RATE*($G12+$N12+GST_TI_SHARE*$M12)*$C12) -> 3046.3668 | AB12: =IF(OR($B12="",N($C12)<=0),"",MATCH($B12,SKU_LIST,0)) -> 9
B13: 2x40kg dial dumbbell pair | C13: 70 | F13: =IF($AB13="","",IF(ISNUMBER($D13),$D13,INDEX(Products!$M$5:$M$23,$AB13))) -> 379 | G13: =IF($AB13="","",INDEX(Products!$AI$5:$AI$23,$AB13)) -> 244.39333 | H13: =IF($AB13="","",INDEX(Products!$W$5:$W$23,$AB13)) -> 0.13 | I13: =IF($AB13="","",INDEX(Products!$X$5:$X$23,$AB13)+0) -> 90 | J13: =IF($AB13="","",$C13*$H13) -> 9.1 | K13: =IF($AB13="","",$C13*$I13) -> 6300 | L13: =IF($AB13="","",MAX(IF($L$6>0,$K13/$L$6,0),IF($I$6>0,$J13/$I$6,0))) -> 0.325 | M13: =IF($AB13="","",IF(SUM($L$12:$L$19)>0,($F$6+OTHER_FIXED)*$L13/SUM($L$12:$L$19)/$C13,0)) -> 26.535345 | N13: =IF($AB13="","",$G13*INDEX(Products!$AT$5:$AT$23,$AB13)) -> 0 | O13: =IF($AB13="","",INSPECTION*INDEX(Products!$AF$5:$AF$23,$AB13)/$C13) -> 5.7142857 | P13: =IF($AB13="","",INDEX(Products!$Y$5:$Y$23,$AB13)/$C13+INDEX(Products!$Z$5:$Z$23,$AB13)+INDEX(Products!$AA$5:$AA$23,$AB13)*USD_TO_AUD) -> 0 | Q13: =IF($AB13="","",(INDEX(Products!$AB$5:$AB$23,$AB13)+N($E13))/$C13) -> 0 | R13: =IF($AB13="","",($G13+$M13+$N13+$O13+$P13+$Q13)*INDEX(Products!$AZ$5:$AZ$23,$AB13)) -> 8.2992888 | S13: =IF($AB13="","",INDEX(Products!$BB$5:$BB$23,$AB13)) -> 5 | T13: =IF($AB13="","",$G13+$M13+$N13+$O13+$P13+$Q13+$R13+$S13) -> 289.94225 | U13: =IF($AB13="","",$F13/(1+GST_RATE)*(1-MP_FEE)) -> 344.54545 | V13: =IF($AB13="","",$U13-$T13) -> 54.603206 | W13: =IF($AB13="","",IF($U13<>0,$V13/$U13,0)) -> 0.15847896 | X13: =IF($AB13="","",$U13*$C13) -> 24118.182 | Y13: =IF($AB13="","",$V13*$C13) -> 3822.2244 | Z13: =IF($AB13="","",$T13*$C13) -> 20295.957 | AA13: =IF($AB13="","",GST_RATE*($G13+$N13+GST_TI_SHARE*$M13)*$C13) -> 1822.2018 | AB13: =IF(OR($B13="",N($C13)<=0),"",MATCH($B13,SKU_LIST,0)) -> 10
F14: =IF($AB14="","",IF(ISNUMBER($D14),$D14,INDEX(Products!$M$5:$M$23,$AB14))) | G14: =IF($AB14="","",INDEX(Products!$AI$5:$AI$23,$AB14)) | H14: =IF($AB14="","",INDEX(Products!$W$5:$W$23,$AB14)) | I14: =IF($AB14="","",INDEX(Products!$X$5:$X$23,$AB14)+0) | J14: =IF($AB14="","",$C14*$H14) | K14: =IF($AB14="","",$C14*$I14) | L14: =IF($AB14="","",MAX(IF($L$6>0,$K14/$L$6,0),IF($I$6>0,$J14/$I$6,0))) | M14: =IF($AB14="","",IF(SUM($L$12:$L$19)>0,($F$6+OTHER_FIXED)*$L14/SUM($L$12:$L$19)/$C14,0)) | N14: =IF($AB14="","",$G14*INDEX(Products!$AT$5:$AT$23,$AB14)) | O14: =IF($AB14="","",INSPECTION*INDEX(Products!$AF$5:$AF$23,$AB14)/$C14) | P14: =IF($AB14="","",INDEX(Products!$Y$5:$Y$23,$AB14)/$C14+INDEX(Products!$Z$5:$Z$23,$AB14)+INDEX(Products!$AA$5:$AA$23,$AB14)*USD_TO_AUD) | Q14: =IF($AB14="","",(INDEX(Products!$AB$5:$AB$23,$AB14)+N($E14))/$C14) | R14: =IF($AB14="","",($G14+$M14+$N14+$O14+$P14+$Q14)*INDEX(Products!$AZ$5:$AZ$23,$AB14)) | S14: =IF($AB14="","",INDEX(Products!$BB$5:$BB$23,$AB14)) | T14: =IF($AB14="","",$G14+$M14+$N14+$O14+$P14+$Q14+$R14+$S14) | U14: =IF($AB14="","",$F14/(1+GST_RATE)*(1-MP_FEE)) | V14: =IF($AB14="","",$U14-$T14) | W14: =IF($AB14="","",IF($U14<>0,$V14/$U14,0)) | X14: =IF($AB14="","",$U14*$C14) | Y14: =IF($AB14="","",$V14*$C14) | Z14: =IF($AB14="","",$T14*$C14) | AA14: =IF($AB14="","",GST_RATE*($G14+$N14+GST_TI_SHARE*$M14)*$C14) | AB14: =IF(OR($B14="",N($C14)<=0),"",MATCH($B14,SKU_LIST,0))
F15: =IF($AB15="","",IF(ISNUMBER($D15),$D15,INDEX(Products!$M$5:$M$23,$AB15))) | G15: =IF($AB15="","",INDEX(Products!$AI$5:$AI$23,$AB15)) | H15: =IF($AB15="","",INDEX(Products!$W$5:$W$23,$AB15)) | I15: =IF($AB15="","",INDEX(Products!$X$5:$X$23,$AB15)+0) | J15: =IF($AB15="","",$C15*$H15) | K15: =IF($AB15="","",$C15*$I15) | L15: =IF($AB15="","",MAX(IF($L$6>0,$K15/$L$6,0),IF($I$6>0,$J15/$I$6,0))) | M15: =IF($AB15="","",IF(SUM($L$12:$L$19)>0,($F$6+OTHER_FIXED)*$L15/SUM($L$12:$L$19)/$C15,0)) | N15: =IF($AB15="","",$G15*INDEX(Products!$AT$5:$AT$23,$AB15)) | O15: =IF($AB15="","",INSPECTION*INDEX(Products!$AF$5:$AF$23,$AB15)/$C15) | P15: =IF($AB15="","",INDEX(Products!$Y$5:$Y$23,$AB15)/$C15+INDEX(Products!$Z$5:$Z$23,$AB15)+INDEX(Products!$AA$5:$AA$23,$AB15)*USD_TO_AUD) | Q15: =IF($AB15="","",(INDEX(Products!$AB$5:$AB$23,$AB15)+N($E15))/$C15) | R15: =IF($AB15="","",($G15+$M15+$N15+$O15+$P15+$Q15)*INDEX(Products!$AZ$5:$AZ$23,$AB15)) | S15: =IF($AB15="","",INDEX(Products!$BB$5:$BB$23,$AB15)) | T15: =IF($AB15="","",$G15+$M15+$N15+$O15+$P15+$Q15+$R15+$S15) | U15: =IF($AB15="","",$F15/(1+GST_RATE)*(1-MP_FEE)) | V15: =IF($AB15="","",$U15-$T15) | W15: =IF($AB15="","",IF($U15<>0,$V15/$U15,0)) | X15: =IF($AB15="","",$U15*$C15) | Y15: =IF($AB15="","",$V15*$C15) | Z15: =IF($AB15="","",$T15*$C15) | AA15: =IF($AB15="","",GST_RATE*($G15+$N15+GST_TI_SHARE*$M15)*$C15) | AB15: =IF(OR($B15="",N($C15)<=0),"",MATCH($B15,SKU_LIST,0))
F16: =IF($AB16="","",IF(ISNUMBER($D16),$D16,INDEX(Products!$M$5:$M$23,$AB16))) | G16: =IF($AB16="","",INDEX(Products!$AI$5:$AI$23,$AB16)) | H16: =IF($AB16="","",INDEX(Products!$W$5:$W$23,$AB16)) | I16: =IF($AB16="","",INDEX(Products!$X$5:$X$23,$AB16)+0) | J16: =IF($AB16="","",$C16*$H16) | K16: =IF($AB16="","",$C16*$I16) | L16: =IF($AB16="","",MAX(IF($L$6>0,$K16/$L$6,0),IF($I$6>0,$J16/$I$6,0))) | M16: =IF($AB16="","",IF(SUM($L$12:$L$19)>0,($F$6+OTHER_FIXED)*$L16/SUM($L$12:$L$19)/$C16,0)) | N16: =IF($AB16="","",$G16*INDEX(Products!$AT$5:$AT$23,$AB16)) | O16: =IF($AB16="","",INSPECTION*INDEX(Products!$AF$5:$AF$23,$AB16)/$C16) | P16: =IF($AB16="","",INDEX(Products!$Y$5:$Y$23,$AB16)/$C16+INDEX(Products!$Z$5:$Z$23,$AB16)+INDEX(Products!$AA$5:$AA$23,$AB16)*USD_TO_AUD) | Q16: =IF($AB16="","",(INDEX(Products!$AB$5:$AB$23,$AB16)+N($E16))/$C16) | R16: =IF($AB16="","",($G16+$M16+$N16+$O16+$P16+$Q16)*INDEX(Products!$AZ$5:$AZ$23,$AB16)) | S16: =IF($AB16="","",INDEX(Products!$BB$5:$BB$23,$AB16)) | T16: =IF($AB16="","",$G16+$M16+$N16+$O16+$P16+$Q16+$R16+$S16) | U16: =IF($AB16="","",$F16/(1+GST_RATE)*(1-MP_FEE)) | V16: =IF($AB16="","",$U16-$T16) | W16: =IF($AB16="","",IF($U16<>0,$V16/$U16,0)) | X16: =IF($AB16="","",$U16*$C16) | Y16: =IF($AB16="","",$V16*$C16) | Z16: =IF($AB16="","",$T16*$C16) | AA16: =IF($AB16="","",GST_RATE*($G16+$N16+GST_TI_SHARE*$M16)*$C16) | AB16: =IF(OR($B16="",N($C16)<=0),"",MATCH($B16,SKU_LIST,0))
F17: =IF($AB17="","",IF(ISNUMBER($D17),$D17,INDEX(Products!$M$5:$M$23,$AB17))) | G17: =IF($AB17="","",INDEX(Products!$AI$5:$AI$23,$AB17)) | H17: =IF($AB17="","",INDEX(Products!$W$5:$W$23,$AB17)) | I17: =IF($AB17="","",INDEX(Products!$X$5:$X$23,$AB17)+0) | J17: =IF($AB17="","",$C17*$H17) | K17: =IF($AB17="","",$C17*$I17) | L17: =IF($AB17="","",MAX(IF($L$6>0,$K17/$L$6,0),IF($I$6>0,$J17/$I$6,0))) | M17: =IF($AB17="","",IF(SUM($L$12:$L$19)>0,($F$6+OTHER_FIXED)*$L17/SUM($L$12:$L$19)/$C17,0)) | N17: =IF($AB17="","",$G17*INDEX(Products!$AT$5:$AT$23,$AB17)) | O17: =IF($AB17="","",INSPECTION*INDEX(Products!$AF$5:$AF$23,$AB17)/$C17) | P17: =IF($AB17="","",INDEX(Products!$Y$5:$Y$23,$AB17)/$C17+INDEX(Products!$Z$5:$Z$23,$AB17)+INDEX(Products!$AA$5:$AA$23,$AB17)*USD_TO_AUD) | Q17: =IF($AB17="","",(INDEX(Products!$AB$5:$AB$23,$AB17)+N($E17))/$C17) | R17: =IF($AB17="","",($G17+$M17+$N17+$O17+$P17+$Q17)*INDEX(Products!$AZ$5:$AZ$23,$AB17)) | S17: =IF($AB17="","",INDEX(Products!$BB$5:$BB$23,$AB17)) | T17: =IF($AB17="","",$G17+$M17+$N17+$O17+$P17+$Q17+$R17+$S17) | U17: =IF($AB17="","",$F17/(1+GST_RATE)*(1-MP_FEE)) | V17: =IF($AB17="","",$U17-$T17) | W17: =IF($AB17="","",IF($U17<>0,$V17/$U17,0)) | X17: =IF($AB17="","",$U17*$C17) | Y17: =IF($AB17="","",$V17*$C17) | Z17: =IF($AB17="","",$T17*$C17) | AA17: =IF($AB17="","",GST_RATE*($G17+$N17+GST_TI_SHARE*$M17)*$C17) | AB17: =IF(OR($B17="",N($C17)<=0),"",MATCH($B17,SKU_LIST,0))
F18: =IF($AB18="","",IF(ISNUMBER($D18),$D18,INDEX(Products!$M$5:$M$23,$AB18))) | G18: =IF($AB18="","",INDEX(Products!$AI$5:$AI$23,$AB18)) | H18: =IF($AB18="","",INDEX(Products!$W$5:$W$23,$AB18)) | I18: =IF($AB18="","",INDEX(Products!$X$5:$X$23,$AB18)+0) | J18: =IF($AB18="","",$C18*$H18) | K18: =IF($AB18="","",$C18*$I18) | L18: =IF($AB18="","",MAX(IF($L$6>0,$K18/$L$6,0),IF($I$6>0,$J18/$I$6,0))) | M18: =IF($AB18="","",IF(SUM($L$12:$L$19)>0,($F$6+OTHER_FIXED)*$L18/SUM($L$12:$L$19)/$C18,0)) | N18: =IF($AB18="","",$G18*INDEX(Products!$AT$5:$AT$23,$AB18)) | O18: =IF($AB18="","",INSPECTION*INDEX(Products!$AF$5:$AF$23,$AB18)/$C18) | P18: =IF($AB18="","",INDEX(Products!$Y$5:$Y$23,$AB18)/$C18+INDEX(Products!$Z$5:$Z$23,$AB18)+INDEX(Products!$AA$5:$AA$23,$AB18)*USD_TO_AUD) | Q18: =IF($AB18="","",(INDEX(Products!$AB$5:$AB$23,$AB18)+N($E18))/$C18) | R18: =IF($AB18="","",($G18+$M18+$N18+$O18+$P18+$Q18)*INDEX(Products!$AZ$5:$AZ$23,$AB18)) | S18: =IF($AB18="","",INDEX(Products!$BB$5:$BB$23,$AB18)) | T18: =IF($AB18="","",$G18+$M18+$N18+$O18+$P18+$Q18+$R18+$S18) | U18: =IF($AB18="","",$F18/(1+GST_RATE)*(1-MP_FEE)) | V18: =IF($AB18="","",$U18-$T18) | W18: =IF($AB18="","",IF($U18<>0,$V18/$U18,0)) | X18: =IF($AB18="","",$U18*$C18) | Y18: =IF($AB18="","",$V18*$C18) | Z18: =IF($AB18="","",$T18*$C18) | AA18: =IF($AB18="","",GST_RATE*($G18+$N18+GST_TI_SHARE*$M18)*$C18) | AB18: =IF(OR($B18="",N($C18)<=0),"",MATCH($B18,SKU_LIST,0))
F19: =IF($AB19="","",IF(ISNUMBER($D19),$D19,INDEX(Products!$M$5:$M$23,$AB19))) | G19: =IF($AB19="","",INDEX(Products!$AI$5:$AI$23,$AB19)) | H19: =IF($AB19="","",INDEX(Products!$W$5:$W$23,$AB19)) | I19: =IF($AB19="","",INDEX(Products!$X$5:$X$23,$AB19)+0) | J19: =IF($AB19="","",$C19*$H19) | K19: =IF($AB19="","",$C19*$I19) | L19: =IF($AB19="","",MAX(IF($L$6>0,$K19/$L$6,0),IF($I$6>0,$J19/$I$6,0))) | M19: =IF($AB19="","",IF(SUM($L$12:$L$19)>0,($F$6+OTHER_FIXED)*$L19/SUM($L$12:$L$19)/$C19,0)) | N19: =IF($AB19="","",$G19*INDEX(Products!$AT$5:$AT$23,$AB19)) | O19: =IF($AB19="","",INSPECTION*INDEX(Products!$AF$5:$AF$23,$AB19)/$C19) | P19: =IF($AB19="","",INDEX(Products!$Y$5:$Y$23,$AB19)/$C19+INDEX(Products!$Z$5:$Z$23,$AB19)+INDEX(Products!$AA$5:$AA$23,$AB19)*USD_TO_AUD) | Q19: =IF($AB19="","",(INDEX(Products!$AB$5:$AB$23,$AB19)+N($E19))/$C19) | R19: =IF($AB19="","",($G19+$M19+$N19+$O19+$P19+$Q19)*INDEX(Products!$AZ$5:$AZ$23,$AB19)) | S19: =IF($AB19="","",INDEX(Products!$BB$5:$BB$23,$AB19)) | T19: =IF($AB19="","",$G19+$M19+$N19+$O19+$P19+$Q19+$R19+$S19) | U19: =IF($AB19="","",$F19/(1+GST_RATE)*(1-MP_FEE)) | V19: =IF($AB19="","",$U19-$T19) | W19: =IF($AB19="","",IF($U19<>0,$V19/$U19,0)) | X19: =IF($AB19="","",$U19*$C19) | Y19: =IF($AB19="","",$V19*$C19) | Z19: =IF($AB19="","",$T19*$C19) | AA19: =IF($AB19="","",GST_RATE*($G19+$N19+GST_TI_SHARE*$M19)*$C19) | AB19: =IF(OR($B19="",N($C19)<=0),"",MATCH($B19,SKU_LIST,0))
B20: Total | C20: =SUM(C12:C19) -> 220 | J20: =SUM(J12:J19) -> 24.1 | K20: =SUM(K12:K19) -> 21750 | L20: =SUM(L12:L19) -> 1.0337156 | X20: =SUM(X12:X19) -> 70345.455 | Y20: =SUM(Y12:Y19) -> 15841.102 | Z20: =SUM(Z12:Z19) -> 54504.352 | AA20: =SUM(AA12:AA19) -> 4868.5686
B23: Mix 2 – Outdoor 40HQ (pre-filled from verify_outdoor.md Q4: 250 pizza ovens + 300 double hammocks + 200 foldable egg chairs)
B24: Notes (Q4): 66.35 CBM loaded; total GP A$25,119 at A$125 / A$95 / A$159; cash A$54,290 ex-GST (FOB + freight + inspection + compliance + consolidation) + ≈A$4,949 GST float. China inland consolidation A$800 per leg for the Qingdao (oven) and Henan (egg chair) suppliers is an ESTIMATE.
B25: Container type | C25: 40HQ | D25: Box cost (A$) | F25: =IF(C25="20GP",COST_20GP,COST_40HQ) -> 10064 | G25: Usable CBM | I25: =IF(C25="20GP",CBM_20GP,CBM_40HQ) -> 68 | J25: Weight cap (kg) | L25: =IF(C25="20GP",KG_20GP,KG_40HQ) -> 22000
B27: Units | C27: CBM loaded | D27: CBM used % | E27: kg loaded | F27: Weight used % | G27: Load status | J27: Cash required ex-GST (A$) | K27: Import-GST float (A$) | L27: Cash incl. GST float (A$) | M27: Net revenue (A$) | N27: Total GP (A$) | O27: GP % of net revenue | P27: Stock to sell to recover cash
B28: =C39 -> 750 | C28: =J39 -> 66.3509 | D28: =IF($I$25>0,J39/$I$25,0) -> 0.97574853 | E28: =K39 -> 11125 | F28: =IF($L$25>0,K39/$L$25,0) -> 0.50568182 | G28: =IF(OR(D28>1,F28>1),"OVERFILL – exceeds the "&IF(D28>1,"volume","")&IF(AND(D28>1,F28>1)," and ","")&IF(F28>1,"weight","")&" cap: cut quantities or add a box",IF(MAX(D28,F28)<0.9,"OK – "&TEXT(1-MAX(D28,F28),"0%")&" of the binding cap spare","OK – box effectively full")) -> OK – box effectively full | J28: =Z39 -> 58108.686 | K28: =AA39 -> 4546.4794 | L28: =J28+K28 -> 62655.165 | M28: =X39 -> 83227.273 | N28: =Y39 -> 25118.587 | O28: =IF(M28>0,N28/M28,0) -> 0.30180716 | P28: =IF(M28>0,J28/M28,0) -> 0.69819284
B30: SKU (pick) | C30: Quantity | D30: Sale price override (A$) | E30: Extra cost per line (A$) | F30: Sale price used (A$) | G30: FOB (A$/unit) | H30: CBM / unit | I30: kg / unit | J30: Line CBM | K30: Line kg | L30: Chargeable share | M30: Freight (A$/unit) | N30: Duty (A$/unit) | O30: Inspection (A$/unit) | P30: Compliance (A$/unit) | Q30: Extras incl. line cost (A$/unit) | R30: Defect allowance (A$/unit) | S30: Storage / handling (A$/unit) | T30: Landed (A$/unit) | U30: Net revenue (A$/unit) | V30: GP (A$/unit) | W30: GP % | X30: Line net revenue (A$) | Y30: Line GP (A$) | Z30: Line cash ex-GST (A$) | AA30: Line import-GST float (A$) | AB30: Products row (helper)
B31: Wood/pellet pizza oven | C31: 250 | E31: 800 | F31: =IF($AB31="","",IF(ISNUMBER($D31),$D31,INDEX(Products!$M$5:$M$23,$AB31))) -> 125 | G31: =IF($AB31="","",INDEX(Products!$AI$5:$AI$23,$AB31)) -> 63.973548 | H31: =IF($AB31="","",INDEX(Products!$W$5:$W$23,$AB31)) -> 0.077826 | I31: =IF($AB31="","",INDEX(Products!$X$5:$X$23,$AB31)+0) -> 11.3 | J31: =IF($AB31="","",$C31*$H31) -> 19.4565 | K31: =IF($AB31="","",$C31*$I31) -> 2825 | L31: =IF($AB31="","",MAX(IF($L$25>0,$K31/$L$25,0),IF($I$25>0,$J31/$I$25,0))) -> 0.286125 | M31: =IF($AB31="","",IF(SUM($L$31:$L$38)>0,($F$25+OTHER_FIXED)*$L31/SUM($L$31:$L$38)/$C31,0)) -> 11.804525 | N31: =IF($AB31="","",$G31*INDEX(Products!$AT$5:$AT$23,$AB31)) -> 0 | O31: =IF($AB31="","",INSPECTION*INDEX(Products!$AF$5:$AF$23,$AB31)/$C31) -> 1.6 | P31: =IF($AB31="","",INDEX(Products!$Y$5:$Y$23,$AB31)/$C31+INDEX(Products!$Z$5:$Z$23,$AB31)+INDEX(Products!$AA$5:$AA$23,$AB31)*USD_TO_AUD) -> 4 | Q31: =IF($AB31="","",(INDEX(Products!$AB$5:$AB$23,$AB31)+N($E31))/$C31) -> 3.2 | R31: =IF($AB31="","",($G31+$M31+$N31+$O31+$P31+$Q31)*INDEX(Products!$AZ$5:$AZ$23,$AB31)) -> 2.5373422 | S31: =IF($AB31="","",INDEX(Products!$BB$5:$BB$23,$AB31)) -> 2.568258 | T31: =IF($AB31="","",$G31+$M31+$N31+$O31+$P31+$Q31+$R31+$S31) -> 89.683673 | U31: =IF($AB31="","",$F31/(1+GST_RATE)*(1-MP_FEE)) -> 113.63636 | V31: =IF($AB31="","",$U31-$T31) -> 23.95269 | W31: =IF($AB31="","",IF($U31<>0,$V31/$U31,0)) -> 0.21078367 | X31: =IF($AB31="","",$U31*$C31) -> 28409.091 | Y31: =IF($AB31="","",$V31*$C31) -> 5988.1726 | Z31: =IF($AB31="","",$T31*$C31) -> 22420.918 | AA31: =IF($AB31="","",GST_RATE*($G31+$N31+GST_TI_SHARE*$M31)*$C31) -> 1776.4066 | AB31: =IF(OR($B31="",N($C31)<=0),"",MATCH($B31,SKU_LIST,0)) -> 13
B32: Double hammock + steel stand | C32: 300 | F32: =IF($AB32="","",IF(ISNUMBER($D32),$D32,INDEX(Products!$M$5:$M$23,$AB32))) -> 95 | G32: =IF($AB32="","",INDEX(Products!$AI$5:$AI$23,$AB32)) -> 30.189764 | H32: =IF($AB32="","",INDEX(Products!$W$5:$W$23,$AB32)) -> 0.061248 | I32: =IF($AB32="","",INDEX(Products!$X$5:$X$23,$AB32)+0) -> 11 | J32: =IF($AB32="","",$C32*$H32) -> 18.3744 | K32: =IF($AB32="","",$C32*$I32) -> 3300 | L32: =IF($AB32="","",MAX(IF($L$25>0,$K32/$L$25,0),IF($I$25>0,$J32/$I$25,0))) -> 0.27021176 | M32: =IF($AB32="","",IF(SUM($L$31:$L$38)>0,($F$25+OTHER_FIXED)*$L32/SUM($L$31:$L$38)/$C32,0)) -> 9.2900002 | N32: =IF($AB32="","",$G32*INDEX(Products!$AT$5:$AT$23,$AB32)) -> 0 | O32: =IF($AB32="","",INSPECTION*INDEX(Products!$AF$5:$AF$23,$AB32)/$C32) -> 1.3333333 | P32: =IF($AB32="","",INDEX(Products!$Y$5:$Y$23,$AB32)/$C32+INDEX(Products!$Z$5:$Z$23,$AB32)+INDEX(Products!$AA$5:$AA$23,$AB32)*USD_TO_AUD) -> 1.6666667 | Q32: =IF($AB32="","",(INDEX(Products!$AB$5:$AB$23,$AB32)+N($E32))/$C32) -> 0 | R32: =IF($AB32="","",($G32+$M32+$N32+$O32+$P32+$Q32)*INDEX(Products!$AZ$5:$AZ$23,$AB32)) -> 1.2743929 | S32: =IF($AB32="","",INDEX(Products!$BB$5:$BB$23,$AB32)) -> 2.021184 | T32: =IF($AB32="","",$G32+$M32+$N32+$O32+$P32+$Q32+$R32+$S32) -> 45.775341 | U32: =IF($AB32="","",$F32/(1+GST_RATE)*(1-MP_FEE)) -> 86.363636 | V32: =IF($AB32="","",$U32-$T32) -> 40.588295 | W32: =IF($AB32="","",IF($U32<>0,$V32/$U32,0)) -> 0.46996973 | X32: =IF($AB32="","",$U32*$C32) -> 25909.091 | Y32: =IF($AB32="","",$V32*$C32) -> 12176.489 | Z32: =IF($AB32="","",$T32*$C32) -> 13732.602 | AA32: =IF($AB32="","",GST_RATE*($G32+$N32+GST_TI_SHARE*$M32)*$C32) -> 1072.9129 | AB32: =IF(OR($B32="",N($C32)<=0),"",MATCH($B32,SKU_LIST,0)) -> 14
B33: Foldable hanging egg chair | C33: 200 | E33: 800 | F33: =IF($AB33="","",IF(ISNUMBER($D33),$D33,INDEX(Products!$M$5:$M$23,$AB33))) -> 159 | G33: =IF($AB33="","",INDEX(Products!$AI$5:$AI$23,$AB33)) -> 71.880391 | H33: =IF($AB33="","",INDEX(Products!$W$5:$W$23,$AB33)) -> 0.1426 | I33: =IF($AB33="","",INDEX(Products!$X$5:$X$23,$AB33)+0) -> 25 | J33: =IF($AB33="","",$C33*$H33) -> 28.52 | K33: =IF($AB33="","",$C33*$I33) -> 5000 | L33: =IF($AB33="","",MAX(IF($L$25>0,$K33/$L$25,0),IF($I$25>0,$J33/$I$25,0))) -> 0.41941176 | M33: =IF($AB33="","",IF(SUM($L$31:$L$38)>0,($F$25+OTHER_FIXED)*$L33/SUM($L$31:$L$38)/$C33,0)) -> 21.629343 | N33: =IF($AB33="","",$G33*INDEX(Products!$AT$5:$AT$23,$AB33)) -> 0 | O33: =IF($AB33="","",INSPECTION*INDEX(Products!$AF$5:$AF$23,$AB33)/$C33) -> 2 | P33: =IF($AB33="","",INDEX(Products!$Y$5:$Y$23,$AB33)/$C33+INDEX(Products!$Z$5:$Z$23,$AB33)+INDEX(Products!$AA$5:$AA$23,$AB33)*USD_TO_AUD) -> 2.5 | Q33: =IF($AB33="","",(INDEX(Products!$AB$5:$AB$23,$AB33)+N($E33))/$C33) -> 4 | R33: =IF($AB33="","",($G33+$M33+$N33+$O33+$P33+$Q33)*INDEX(Products!$AZ$5:$AZ$23,$AB33)) -> 3.060292 | S33: =IF($AB33="","",INDEX(Products!$BB$5:$BB$23,$AB33)) -> 4.7058 | T33: =IF($AB33="","",$G33+$M33+$N33+$O33+$P33+$Q33+$R33+$S33) -> 109.77583 | U33: =IF($AB33="","",$F33/(1+GST_RATE)*(1-MP_FEE)) -> 144.54545 | V33: =IF($AB33="","",$U33-$T33) -> 34.769628 | W33: =IF($AB33="","",IF($U33<>0,$V33/$U33,0)) -> 0.2405446 | X33: =IF($AB33="","",$U33*$C33) -> 28909.091 | Y33: =IF($AB33="","",$V33*$C33) -> 6953.9256 | Z33: =IF($AB33="","",$T33*$C33) -> 21955.165 | AA33: =IF($AB33="","",GST_RATE*($G33+$N33+GST_TI_SHARE*$M33)*$C33) -> 1697.1599 | AB33: =IF(OR($B33="",N($C33)<=0),"",MATCH($B33,SKU_LIST,0)) -> 15
F34: =IF($AB34="","",IF(ISNUMBER($D34),$D34,INDEX(Products!$M$5:$M$23,$AB34))) | G34: =IF($AB34="","",INDEX(Products!$AI$5:$AI$23,$AB34)) | H34: =IF($AB34="","",INDEX(Products!$W$5:$W$23,$AB34)) | I34: =IF($AB34="","",INDEX(Products!$X$5:$X$23,$AB34)+0) | J34: =IF($AB34="","",$C34*$H34) | K34: =IF($AB34="","",$C34*$I34) | L34: =IF($AB34="","",MAX(IF($L$25>0,$K34/$L$25,0),IF($I$25>0,$J34/$I$25,0))) | M34: =IF($AB34="","",IF(SUM($L$31:$L$38)>0,($F$25+OTHER_FIXED)*$L34/SUM($L$31:$L$38)/$C34,0)) | N34: =IF($AB34="","",$G34*INDEX(Products!$AT$5:$AT$23,$AB34)) | O34: =IF($AB34="","",INSPECTION*INDEX(Products!$AF$5:$AF$23,$AB34)/$C34) | P34: =IF($AB34="","",INDEX(Products!$Y$5:$Y$23,$AB34)/$C34+INDEX(Products!$Z$5:$Z$23,$AB34)+INDEX(Products!$AA$5:$AA$23,$AB34)*USD_TO_AUD) | Q34: =IF($AB34="","",(INDEX(Products!$AB$5:$AB$23,$AB34)+N($E34))/$C34) | R34: =IF($AB34="","",($G34+$M34+$N34+$O34+$P34+$Q34)*INDEX(Products!$AZ$5:$AZ$23,$AB34)) | S34: =IF($AB34="","",INDEX(Products!$BB$5:$BB$23,$AB34)) | T34: =IF($AB34="","",$G34+$M34+$N34+$O34+$P34+$Q34+$R34+$S34) | U34: =IF($AB34="","",$F34/(1+GST_RATE)*(1-MP_FEE)) | V34: =IF($AB34="","",$U34-$T34) | W34: =IF($AB34="","",IF($U34<>0,$V34/$U34,0)) | X34: =IF($AB34="","",$U34*$C34) | Y34: =IF($AB34="","",$V34*$C34) | Z34: =IF($AB34="","",$T34*$C34) | AA34: =IF($AB34="","",GST_RATE*($G34+$N34+GST_TI_SHARE*$M34)*$C34) | AB34: =IF(OR($B34="",N($C34)<=0),"",MATCH($B34,SKU_LIST,0))
F35: =IF($AB35="","",IF(ISNUMBER($D35),$D35,INDEX(Products!$M$5:$M$23,$AB35))) | G35: =IF($AB35="","",INDEX(Products!$AI$5:$AI$23,$AB35)) | H35: =IF($AB35="","",INDEX(Products!$W$5:$W$23,$AB35)) | I35: =IF($AB35="","",INDEX(Products!$X$5:$X$23,$AB35)+0) | J35: =IF($AB35="","",$C35*$H35) | K35: =IF($AB35="","",$C35*$I35) | L35: =IF($AB35="","",MAX(IF($L$25>0,$K35/$L$25,0),IF($I$25>0,$J35/$I$25,0))) | M35: =IF($AB35="","",IF(SUM($L$31:$L$38)>0,($F$25+OTHER_FIXED)*$L35/SUM($L$31:$L$38)/$C35,0)) | N35: =IF($AB35="","",$G35*INDEX(Products!$AT$5:$AT$23,$AB35)) | O35: =IF($AB35="","",INSPECTION*INDEX(Products!$AF$5:$AF$23,$AB35)/$C35) | P35: =IF($AB35="","",INDEX(Products!$Y$5:$Y$23,$AB35)/$C35+INDEX(Products!$Z$5:$Z$23,$AB35)+INDEX(Products!$AA$5:$AA$23,$AB35)*USD_TO_AUD) | Q35: =IF($AB35="","",(INDEX(Products!$AB$5:$AB$23,$AB35)+N($E35))/$C35) | R35: =IF($AB35="","",($G35+$M35+$N35+$O35+$P35+$Q35)*INDEX(Products!$AZ$5:$AZ$23,$AB35)) | S35: =IF($AB35="","",INDEX(Products!$BB$5:$BB$23,$AB35)) | T35: =IF($AB35="","",$G35+$M35+$N35+$O35+$P35+$Q35+$R35+$S35) | U35: =IF($AB35="","",$F35/(1+GST_RATE)*(1-MP_FEE)) | V35: =IF($AB35="","",$U35-$T35) | W35: =IF($AB35="","",IF($U35<>0,$V35/$U35,0)) | X35: =IF($AB35="","",$U35*$C35) | Y35: =IF($AB35="","",$V35*$C35) | Z35: =IF($AB35="","",$T35*$C35) | AA35: =IF($AB35="","",GST_RATE*($G35+$N35+GST_TI_SHARE*$M35)*$C35) | AB35: =IF(OR($B35="",N($C35)<=0),"",MATCH($B35,SKU_LIST,0))
F36: =IF($AB36="","",IF(ISNUMBER($D36),$D36,INDEX(Products!$M$5:$M$23,$AB36))) | G36: =IF($AB36="","",INDEX(Products!$AI$5:$AI$23,$AB36)) | H36: =IF($AB36="","",INDEX(Products!$W$5:$W$23,$AB36)) | I36: =IF($AB36="","",INDEX(Products!$X$5:$X$23,$AB36)+0) | J36: =IF($AB36="","",$C36*$H36) | K36: =IF($AB36="","",$C36*$I36) | L36: =IF($AB36="","",MAX(IF($L$25>0,$K36/$L$25,0),IF($I$25>0,$J36/$I$25,0))) | M36: =IF($AB36="","",IF(SUM($L$31:$L$38)>0,($F$25+OTHER_FIXED)*$L36/SUM($L$31:$L$38)/$C36,0)) | N36: =IF($AB36="","",$G36*INDEX(Products!$AT$5:$AT$23,$AB36)) | O36: =IF($AB36="","",INSPECTION*INDEX(Products!$AF$5:$AF$23,$AB36)/$C36) | P36: =IF($AB36="","",INDEX(Products!$Y$5:$Y$23,$AB36)/$C36+INDEX(Products!$Z$5:$Z$23,$AB36)+INDEX(Products!$AA$5:$AA$23,$AB36)*USD_TO_AUD) | Q36: =IF($AB36="","",(INDEX(Products!$AB$5:$AB$23,$AB36)+N($E36))/$C36) | R36: =IF($AB36="","",($G36+$M36+$N36+$O36+$P36+$Q36)*INDEX(Products!$AZ$5:$AZ$23,$AB36)) | S36: =IF($AB36="","",INDEX(Products!$BB$5:$BB$23,$AB36)) | T36: =IF($AB36="","",$G36+$M36+$N36+$O36+$P36+$Q36+$R36+$S36) | U36: =IF($AB36="","",$F36/(1+GST_RATE)*(1-MP_FEE)) | V36: =IF($AB36="","",$U36-$T36) | W36: =IF($AB36="","",IF($U36<>0,$V36/$U36,0)) | X36: =IF($AB36="","",$U36*$C36) | Y36: =IF($AB36="","",$V36*$C36) | Z36: =IF($AB36="","",$T36*$C36) | AA36: =IF($AB36="","",GST_RATE*($G36+$N36+GST_TI_SHARE*$M36)*$C36) | AB36: =IF(OR($B36="",N($C36)<=0),"",MATCH($B36,SKU_LIST,0))
F37: =IF($AB37="","",IF(ISNUMBER($D37),$D37,INDEX(Products!$M$5:$M$23,$AB37))) | G37: =IF($AB37="","",INDEX(Products!$AI$5:$AI$23,$AB37)) | H37: =IF($AB37="","",INDEX(Products!$W$5:$W$23,$AB37)) | I37: =IF($AB37="","",INDEX(Products!$X$5:$X$23,$AB37)+0) | J37: =IF($AB37="","",$C37*$H37) | K37: =IF($AB37="","",$C37*$I37) | L37: =IF($AB37="","",MAX(IF($L$25>0,$K37/$L$25,0),IF($I$25>0,$J37/$I$25,0))) | M37: =IF($AB37="","",IF(SUM($L$31:$L$38)>0,($F$25+OTHER_FIXED)*$L37/SUM($L$31:$L$38)/$C37,0)) | N37: =IF($AB37="","",$G37*INDEX(Products!$AT$5:$AT$23,$AB37)) | O37: =IF($AB37="","",INSPECTION*INDEX(Products!$AF$5:$AF$23,$AB37)/$C37) | P37: =IF($AB37="","",INDEX(Products!$Y$5:$Y$23,$AB37)/$C37+INDEX(Products!$Z$5:$Z$23,$AB37)+INDEX(Products!$AA$5:$AA$23,$AB37)*USD_TO_AUD) | Q37: =IF($AB37="","",(INDEX(Products!$AB$5:$AB$23,$AB37)+N($E37))/$C37) | R37: =IF($AB37="","",($G37+$M37+$N37+$O37+$P37+$Q37)*INDEX(Products!$AZ$5:$AZ$23,$AB37)) | S37: =IF($AB37="","",INDEX(Products!$BB$5:$BB$23,$AB37)) | T37: =IF($AB37="","",$G37+$M37+$N37+$O37+$P37+$Q37+$R37+$S37) | U37: =IF($AB37="","",$F37/(1+GST_RATE)*(1-MP_FEE)) | V37: =IF($AB37="","",$U37-$T37) | W37: =IF($AB37="","",IF($U37<>0,$V37/$U37,0)) | X37: =IF($AB37="","",$U37*$C37) | Y37: =IF($AB37="","",$V37*$C37) | Z37: =IF($AB37="","",$T37*$C37) | AA37: =IF($AB37="","",GST_RATE*($G37+$N37+GST_TI_SHARE*$M37)*$C37) | AB37: =IF(OR($B37="",N($C37)<=0),"",MATCH($B37,SKU_LIST,0))
F38: =IF($AB38="","",IF(ISNUMBER($D38),$D38,INDEX(Products!$M$5:$M$23,$AB38))) | G38: =IF($AB38="","",INDEX(Products!$AI$5:$AI$23,$AB38)) | H38: =IF($AB38="","",INDEX(Products!$W$5:$W$23,$AB38)) | I38: =IF($AB38="","",INDEX(Products!$X$5:$X$23,$AB38)+0) | J38: =IF($AB38="","",$C38*$H38) | K38: =IF($AB38="","",$C38*$I38) | L38: =IF($AB38="","",MAX(IF($L$25>0,$K38/$L$25,0),IF($I$25>0,$J38/$I$25,0))) | M38: =IF($AB38="","",IF(SUM($L$31:$L$38)>0,($F$25+OTHER_FIXED)*$L38/SUM($L$31:$L$38)/$C38,0)) | N38: =IF($AB38="","",$G38*INDEX(Products!$AT$5:$AT$23,$AB38)) | O38: =IF($AB38="","",INSPECTION*INDEX(Products!$AF$5:$AF$23,$AB38)/$C38) | P38: =IF($AB38="","",INDEX(Products!$Y$5:$Y$23,$AB38)/$C38+INDEX(Products!$Z$5:$Z$23,$AB38)+INDEX(Products!$AA$5:$AA$23,$AB38)*USD_TO_AUD) | Q38: =IF($AB38="","",(INDEX(Products!$AB$5:$AB$23,$AB38)+N($E38))/$C38) | R38: =IF($AB38="","",($G38+$M38+$N38+$O38+$P38+$Q38)*INDEX(Products!$AZ$5:$AZ$23,$AB38)) | S38: =IF($AB38="","",INDEX(Products!$BB$5:$BB$23,$AB38)) | T38: =IF($AB38="","",$G38+$M38+$N38+$O38+$P38+$Q38+$R38+$S38) | U38: =IF($AB38="","",$F38/(1+GST_RATE)*(1-MP_FEE)) | V38: =IF($AB38="","",$U38-$T38) | W38: =IF($AB38="","",IF($U38<>0,$V38/$U38,0)) | X38: =IF($AB38="","",$U38*$C38) | Y38: =IF($AB38="","",$V38*$C38) | Z38: =IF($AB38="","",$T38*$C38) | AA38: =IF($AB38="","",GST_RATE*($G38+$N38+GST_TI_SHARE*$M38)*$C38) | AB38: =IF(OR($B38="",N($C38)<=0),"",MATCH($B38,SKU_LIST,0))
B39: Total | C39: =SUM(C31:C38) -> 750 | J39: =SUM(J31:J38) -> 66.3509 | K39: =SUM(K31:K38) -> 11125 | L39: =SUM(L31:L38) -> 0.97574853 | X39: =SUM(X31:X38) -> 83227.273 | Y39: =SUM(Y31:Y38) -> 25118.587 | Z39: =SUM(Z31:Z38) -> 58108.686 | AA39: =SUM(AA31:AA38) -> 4546.4794

Sheet Sensitivity
A1: Sensitivity – GP per unit (A$) for the top-scored SKUs
A2: Each column changes one input from the base case (Assumptions plus each SKU's mode, quantity, price and costs on Products); the other inputs link to the Base column. Rows are pre-filled with the 7 SKUs whose revised research score is 5 or more – pick any SKU from the list. The check column confirms Base = Products GP.
B4: Scenario | C4: Base | D4: FX 0.65 | E4: FX 0.6956 | F4: FX 0.73 | G4: Freight −30% | H4: Freight +50% | I4: Duty 0% (CoO held) | J4: Duty 5% (no CoO) | K4: Sale price −10% | L4: FOB +15%
B5: AUD/USD (US$ per A$1) | C5: =FX_AUDUSD -> 0.6956 | D5: 0.65 | E5: 0.6956 | F5: 0.73 | G5: =$C$5 -> 0.6956 | H5: =$C$5 -> 0.6956 | I5: =$C$5 -> 0.6956 | J5: =$C$5 -> 0.6956 | K5: =$C$5 -> 0.6956 | L5: =$C$5 -> 0.6956
B6: Freight cost multiplier | C6: 1 | D6: =$C$6 -> 1 | E6: =$C$6 -> 1 | F6: =$C$6 -> 1 | G6: 0.7 | H6: 1.5 | I6: =$C$6 -> 1 | J6: =$C$6 -> 1 | K6: =$C$6 -> 1 | L6: =$C$6 -> 1
B7: Duty rate on dutiable SKUs | C7: =DUTY_APPLIED -> 0 | D7: =$C$7 -> 0 | E7: =$C$7 -> 0 | F7: =$C$7 -> 0 | G7: =$C$7 -> 0 | H7: =$C$7 -> 0 | I7: 0 | J7: 0.05 | K7: =$C$7 -> 0 | L7: =$C$7 -> 0
B8: Sale price multiplier | C8: 1 | D8: =$C$8 -> 1 | E8: =$C$8 -> 1 | F8: =$C$8 -> 1 | G8: =$C$8 -> 1 | H8: =$C$8 -> 1 | I8: =$C$8 -> 1 | J8: =$C$8 -> 1 | K8: 0.9 | L8: =$C$8 -> 1
B9: FOB multiplier | C9: 1 | D9: =$C$9 -> 1 | E9: =$C$9 -> 1 | F9: =$C$9 -> 1 | G9: =$C$9 -> 1 | H9: =$C$9 -> 1 | I9: =$C$9 -> 1 | J9: =$C$9 -> 1 | K9: =$C$9 -> 1 | L9: 1.15
O10: Inputs pulled from Products for each SKU (do not edit)
A11: # | B11: SKU (pick from list) | C11: =C$4 -> Base | D11: =D$4 -> FX 0.65 | E11: =E$4 -> FX 0.6956 | F11: =F$4 -> FX 0.73 | G11: =G$4 -> Freight −30% | H11: =H$4 -> Freight +50% | I11: =I$4 -> Duty 0% (CoO held) | J11: =J$4 -> Duty 5% (no CoO) | ... L11: =L$4 -> FOB +15% | M11: Check: Base − Products GP | O11: Products row | P11: Mode | Q11: Qty | R11: FOB US$ / unit | S11: Freight A$ / unit | T11: Inspection A$ / unit | U11: One-off compliance A$ / unit | V11: Per-unit compliance A$ | W11: Per-unit compliance US$ | X11: Extras A$ / unit | Y11: Storage A$ / unit | Z11: Defect % | AA11: Duty-free? | AB11: Sale price A$
A12: 1 | B12: Trampoline 14ft + enclosure | C12: =$AB12*C$8/(1+GST_RATE)*(1-MP_FEE)-(($R12*C$9/C$5*(1+IF($AA12="Yes",0,C$7))+$S12*C$6+$T12+$U12+$V12+$W12/C$5+$X12)*(1+$Z12)+$Y12) -> 97.064391 | D12: =$AB12*D$8/(1+GST_RATE)*(1-MP_FEE)-(($R12*D$9/D$5*(1+IF($AA12="Yes",0,D$7))+$S12*D$6+$T12+$U12+$V12+$W12/D$5+$X12)*(1+$Z12)+$Y12) -> 87.091975 | E12: =$AB12*E$8/(1+GST_RATE)*(1-MP_FEE)-(($R12*E$9/E$5*(1+IF($AA12="Yes",0,E$7))+$S12*E$6+$T12+$U12+$V12+$W12/E$5+$X12)*(1+$Z12)+$Y12) -> 97.064391 | F12: =$AB12*F$8/(1+GST_RATE)*(1-MP_FEE)-(($R12*F$9/F$5*(1+IF($AA12="Yes",0,F$7))+$S12*F$6+$T12+$U12+$V12+$W12/F$5+$X12)*(1+$Z12)+$Y12) -> 103.763 | G12: =$AB12*G$8/(1+GST_RATE)*(1-MP_FEE)-(($R12*G$9/G$5*(1+IF($AA12="Yes",0,G$7))+$S12*G$6+$T12+$U12+$V12+$W12/G$5+$X12)*(1+$Z12)+$Y12) -> 111.32667 | H12: =$AB12*H$8/(1+GST_RATE)*(1-MP_FEE)-(($R12*H$9/H$5*(1+IF($AA12="Yes",0,H$7))+$S12*H$6+$T12+$U12+$V12+$W12/H$5+$X12)*(1+$Z12)+$Y12) -> 73.293922 | I12: =$AB12*I$8/(1+GST_RATE)*(1-MP_FEE)-(($R12*I$9/I$5*(1+IF($AA12="Yes",0,I$7))+$S12*I$6+$T12+$U12+$V12+$W12/I$5+$X12)*(1+$Z12)+$Y12) -> 97.064391 | J12: =$AB12*J$8/(1+GST_RATE)*(1-MP_FEE)-(($R12*J$9/J$5*(1+IF($AA12="Yes",0,J$7))+$S12*J$6+$T12+$U12+$V12+$W12/J$5+$X12)*(1+$Z12)+$Y12) -> 89.956858 | ... L12: =$AB12*L$8/(1+GST_RATE)*(1-MP_FEE)-(($R12*L$9/L$5*(1+IF($AA12="Yes",0,L$7))+$S12*L$6+$T12+$U12+$V12+$W12/L$5+$X12)*(1+$Z12)+$Y12) -> 75.741792 | M12: =C12-INDEX(Products!$BE$5:$BE$23,$O12) -> 0 | O12: =MATCH($B12,SKU_LIST,0) -> 1 | P12: =INDEX(Products!$AG$5:$AG$23,$O12) -> 20GP | Q12: =INDEX(Products!$AH$5:$AH$23,$O12) -> 128 | R12: =INDEX(Products!$U$5:$U$23,$O12) -> 96 | S12: =INDEX(Products!$AR$5:$AR$23,$O12) -> 46.15625 | T12: =INDEX(Products!$AV$5:$AV$23,$O12) -> 3.125 | U12: =IF($Q12>0,INDEX(Products!$Y$5:$Y$23,$O12)/$Q12,0) -> 19.53125 | V12: =INDEX(Products!$Z$5:$Z$23,$O12) -> 0 | W12: =INDEX(Products!$AA$5:$AA$23,$O12) -> 0 | X12: =INDEX(Products!$AX$5:$AX$23,$O12) -> 0 | Y12: =INDEX(Products!$BB$5:$BB$23,$O12) -> 7.1808 | Z12: =INDEX(Products!$AZ$5:$AZ$23,$O12) -> 0.03 | AA12: =INDEX(Products!$AC$5:$AC$23,$O12) -> No | AB12: =INDEX(Products!$M$5:$M$23,$O12) -> 349
A13: 2 | B13: Dual-motor standing desk | C13: =$AB13*C$8/(1+GST_RATE)*(1-MP_FEE)-(($R13*C$9/C$5*(1+IF($AA13="Yes",0,C$7))+$S13*C$6+$T13+$U13+$V13+$W13/C$5+$X13)*(1+$Z13)+$Y13) -> 47.059159 | D13: =$AB13*D$8/(1+GST_RATE)*(1-MP_FEE)-(($R13*D$9/D$5*(1+IF($AA13="Yes",0,D$7))+$S13*D$6+$T13+$U13+$V13+$W13/D$5+$X13)*(1+$Z13)+$Y13) -> 36.671226 | E13: =$AB13*E$8/(1+GST_RATE)*(1-MP_FEE)-(($R13*E$9/E$5*(1+IF($AA13="Yes",0,E$7))+$S13*E$6+$T13+$U13+$V13+$W13/E$5+$X13)*(1+$Z13)+$Y13) -> 47.059159 | F13: =$AB13*F$8/(1+GST_RATE)*(1-MP_FEE)-(($R13*F$9/F$5*(1+IF($AA13="Yes",0,F$7))+$S13*F$6+$T13+$U13+$V13+$W13/F$5+$X13)*(1+$Z13)+$Y13) -> 54.036874 | G13: =$AB13*G$8/(1+GST_RATE)*(1-MP_FEE)-(($R13*G$9/G$5*(1+IF($AA13="Yes",0,G$7))+$S13*G$6+$T13+$U13+$V13+$W13/G$5+$X13)*(1+$Z13)+$Y13) -> 57.530551 | H13: =$AB13*H$8/(1+GST_RATE)*(1-MP_FEE)-(($R13*H$9/H$5*(1+IF($AA13="Yes",0,H$7))+$S13*H$6+$T13+$U13+$V13+$W13/H$5+$X13)*(1+$Z13)+$Y13) -> 29.606839 | I13: =$AB13*I$8/(1+GST_RATE)*(1-MP_FEE)-(($R13*I$9/I$5*(1+IF($AA13="Yes",0,I$7))+$S13*I$6+$T13+$U13+$V13+$W13/I$5+$X13)*(1+$Z13)+$Y13) -> 47.059159 | J13: =$AB13*J$8/(1+GST_RATE)*(1-MP_FEE)-(($R13*J$9/J$5*(1+IF($AA13="Yes",0,J$7))+$S13*J$6+$T13+$U13+$V13+$W13/J$5+$X13)*(1+$Z13)+$Y13) -> 39.655479 | ... L13: =$AB13*L$8/(1+GST_RATE)*(1-MP_FEE)-(($R13*L$9/L$5*(1+IF($AA13="Yes",0,L$7))+$S13*L$6+$T13+$U13+$V13+$W13/L$5+$X13)*(1+$Z13)+$Y13) -> 24.848118 | M13: =C13-INDEX(Products!$BE$5:$BE$23,$O13) -> 0 | O13: =MATCH($B13,SKU_LIST,0) -> 5 | P13: =INDEX(Products!$AG$5:$AG$23,$O13) -> LCL | Q13: =INDEX(Products!$AH$5:$AH$23,$O13) -> 100 | R13: =INDEX(Products!$U$5:$U$23,$O13) -> 100 | S13: =INDEX(Products!$AR$5:$AR$23,$O13) -> 33.888 | T13: =INDEX(Products!$AV$5:$AV$23,$O13) -> 4 | U13: =IF($Q13>0,INDEX(Products!$Y$5:$Y$23,$O13)/$Q13,0) -> 33.2959 | V13: =INDEX(Products!$Z$5:$Z$23,$O13) -> 0 | W13: =INDEX(Products!$AA$5:$AA$23,$O13) -> 0 | X13: =INDEX(Products!$AX$5:$AX$23,$O13) -> 0 | Y13: =INDEX(Products!$BB$5:$BB$23,$O13) -> 3.366 | Z13: =INDEX(Products!$AZ$5:$AZ$23,$O13) -> 0.03 | AA13: =INDEX(Products!$AC$5:$AC$23,$O13) -> No | AB13: =INDEX(Products!$M$5:$M$23,$O13) -> 299
A14: 3 | B14: 100kg bumper plate set | C14: =$AB14*C$8/(1+GST_RATE)*(1-MP_FEE)-(($R14*C$9/C$5*(1+IF($AA14="Yes",0,C$7))+$S14*C$6+$T14+$U14+$V14+$W14/C$5+$X14)*(1+$Z14)+$Y14) -> 79.893524 | D14: =$AB14*D$8/(1+GST_RATE)*(1-MP_FEE)-(($R14*D$9/D$5*(1+IF($AA14="Yes",0,D$7))+$S14*D$6+$T14+$U14+$V14+$W14/D$5+$X14)*(1+$Z14)+$Y14) -> 66.389212 | E14: =$AB14*E$8/(1+GST_RATE)*(1-MP_FEE)-(($R14*E$9/E$5*(1+IF($AA14="Yes",0,E$7))+$S14*E$6+$T14+$U14+$V14+$W14/E$5+$X14)*(1+$Z14)+$Y14) -> 79.893524 | F14: =$AB14*F$8/(1+GST_RATE)*(1-MP_FEE)-(($R14*F$9/F$5*(1+IF($AA14="Yes",0,F$7))+$S14*F$6+$T14+$U14+$V14+$W14/F$5+$X14)*(1+$Z14)+$Y14) -> 88.964554 | G14: =$AB14*G$8/(1+GST_RATE)*(1-MP_FEE)-(($R14*G$9/G$5*(1+IF($AA14="Yes",0,G$7))+$S14*G$6+$T14+$U14+$V14+$W14/G$5+$X14)*(1+$Z14)+$Y14) -> 88.545524 | H14: =$AB14*H$8/(1+GST_RATE)*(1-MP_FEE)-(($R14*H$9/H$5*(1+IF($AA14="Yes",0,H$7))+$S14*H$6+$T14+$U14+$V14+$W14/H$5+$X14)*(1+$Z14)+$Y14) -> 65.473524 | I14: =$AB14*I$8/(1+GST_RATE)*(1-MP_FEE)-(($R14*I$9/I$5*(1+IF($AA14="Yes",0,I$7))+$S14*I$6+$T14+$U14+$V14+$W14/I$5+$X14)*(1+$Z14)+$Y14) -> 79.893524 | J14: =$AB14*J$8/(1+GST_RATE)*(1-MP_FEE)-(($R14*J$9/J$5*(1+IF($AA14="Yes",0,J$7))+$S14*J$6+$T14+$U14+$V14+$W14/J$5+$X14)*(1+$Z14)+$Y14) -> 70.26874 | ... L14: =$AB14*L$8/(1+GST_RATE)*(1-MP_FEE)-(($R14*L$9/L$5*(1+IF($AA14="Yes",0,L$7))+$S14*L$6+$T14+$U14+$V14+$W14/L$5+$X14)*(1+$Z14)+$Y14) -> 51.019171 | M14: =C14-INDEX(Products!$BE$5:$BE$23,$O14) -> 0 | O14: =MATCH($B14,SKU_LIST,0) -> 9 | P14: =INDEX(Products!$AG$5:$AG$23,$O14) -> 20GP | Q14: =INDEX(Products!$AH$5:$AH$23,$O14) -> 211 | R14: =INDEX(Products!$U$5:$U$23,$O14) -> 130 | S14: =INDEX(Products!$AR$5:$AR$23,$O14) -> 28 | T14: =INDEX(Products!$AV$5:$AV$23,$O14) -> 1.8957346 | U14: =IF($Q14>0,INDEX(Products!$Y$5:$Y$23,$O14)/$Q14,0) -> 0 | V14: =INDEX(Products!$Z$5:$Z$23,$O14) -> 0 | W14: =INDEX(Products!$AA$5:$AA$23,$O14) -> 0 | X14: =INDEX(Products!$AX$5:$AX$23,$O14) -> 0 | Y14: =INDEX(Products!$BB$5:$BB$23,$O14) -> 5 | Z14: =INDEX(Products!$AZ$5:$AZ$23,$O14) -> 0.03 | AA14: =INDEX(Products!$AC$5:$AC$23,$O14) -> No | AB14: =INDEX(Products!$M$5:$M$23,$O14) -> 339
A15: 4 | B15: Double hammock + steel stand | C15: =$AB15*C$8/(1+GST_RATE)*(1-MP_FEE)-(($R15*C$9/C$5*(1+IF($AA15="Yes",0,C$7))+$S15*C$6+$T15+$U15+$V15+$W15/C$5+$X15)*(1+$Z15)+$Y15) -> 28.584148 | D15: =$AB15*D$8/(1+GST_RATE)*(1-MP_FEE)-(($R15*D$9/D$5*(1+IF($AA15="Yes",0,D$7))+$S15*D$6+$T15+$U15+$V15+$W15/D$5+$X15)*(1+$Z15)+$Y15) -> 26.402682 | E15: =$AB15*E$8/(1+GST_RATE)*(1-MP_FEE)-(($R15*E$9/E$5*(1+IF($AA15="Yes",0,E$7))+$S15*E$6+$T15+$U15+$V15+$W15/E$5+$X15)*(1+$Z15)+$Y15) -> 28.584148 | F15: =$AB15*F$8/(1+GST_RATE)*(1-MP_FEE)-(($R15*F$9/F$5*(1+IF($AA15="Yes",0,F$7))+$S15*F$6+$T15+$U15+$V15+$W15/F$5+$X15)*(1+$Z15)+$Y15) -> 30.049468 | G15: =$AB15*G$8/(1+GST_RATE)*(1-MP_FEE)-(($R15*G$9/G$5*(1+IF($AA15="Yes",0,G$7))+$S15*G$6+$T15+$U15+$V15+$W15/G$5+$X15)*(1+$Z15)+$Y15) -> 34.592502 | H15: =$AB15*H$8/(1+GST_RATE)*(1-MP_FEE)-(($R15*H$9/H$5*(1+IF($AA15="Yes",0,H$7))+$S15*H$6+$T15+$U15+$V15+$W15/H$5+$X15)*(1+$Z15)+$Y15) -> 18.570224 | I15: =$AB15*I$8/(1+GST_RATE)*(1-MP_FEE)-(($R15*I$9/I$5*(1+IF($AA15="Yes",0,I$7))+$S15*I$6+$T15+$U15+$V15+$W15/I$5+$X15)*(1+$Z15)+$Y15) -> 28.584148 | J15: =$AB15*J$8/(1+GST_RATE)*(1-MP_FEE)-(($R15*J$9/J$5*(1+IF($AA15="Yes",0,J$7))+$S15*J$6+$T15+$U15+$V15+$W15/J$5+$X15)*(1+$Z15)+$Y15) -> 27.029375 | ... L15: =$AB15*L$8/(1+GST_RATE)*(1-MP_FEE)-(($R15*L$9/L$5*(1+IF($AA15="Yes",0,L$7))+$S15*L$6+$T15+$U15+$V15+$W15/L$5+$X15)*(1+$Z15)+$Y15) -> 23.919829 | M15: =C15-INDEX(Products!$BE$5:$BE$23,$O15) -> 0 | O15: =MATCH($B15,SKU_LIST,0) -> 14 | P15: =INDEX(Products!$AG$5:$AG$23,$O15) -> LCL | Q15: =INDEX(Products!$AH$5:$AH$23,$O15) -> 200 | R15: =INDEX(Products!$U$5:$U$23,$O15) -> 21 | S15: =INDEX(Products!$AR$5:$AR$23,$O15) -> 19.444512 | T15: =INDEX(Products!$AV$5:$AV$23,$O15) -> 2 | U15: =IF($Q15>0,INDEX(Products!$Y$5:$Y$23,$O15)/$Q15,0) -> 2.5 | V15: =INDEX(Products!$Z$5:$Z$23,$O15) -> 0 | W15: =INDEX(Products!$AA$5:$AA$23,$O15) -> 0 | X15: =INDEX(Products!$AX$5:$AX$23,$O15) -> 0 | Y15: =INDEX(Products!$BB$5:$BB$23,$O15) -> 2.021184 | Z15: =INDEX(Products!$AZ$5:$AZ$23,$O15) -> 0.03 | AA15: =INDEX(Products!$AC$5:$AC$23,$O15) -> No | AB15: =INDEX(Products!$M$5:$M$23,$O15) -> 95
A16: 5 | B16: Timber cubby house | C16: =$AB16*C$8/(1+GST_RATE)*(1-MP_FEE)-(($R16*C$9/C$5*(1+IF($AA16="Yes",0,C$7))+$S16*C$6+$T16+$U16+$V16+$W16/C$5+$X16)*(1+$Z16)+$Y16) -> 67.887172 | D16: =$AB16*D$8/(1+GST_RATE)*(1-MP_FEE)-(($R16*D$9/D$5*(1+IF($AA16="Yes",0,D$7))+$S16*D$6+$T16+$U16+$V16+$W16/D$5+$X16)*(1+$Z16)+$Y16) -> 56.863497 | E16: =$AB16*E$8/(1+GST_RATE)*(1-MP_FEE)-(($R16*E$9/E$5*(1+IF($AA16="Yes",0,E$7))+$S16*E$6+$T16+$U16+$V16+$W16/E$5+$X16)*(1+$Z16)+$Y16) -> 67.887172 | F16: =$AB16*F$8/(1+GST_RATE)*(1-MP_FEE)-(($R16*F$9/F$5*(1+IF($AA16="Yes",0,F$7))+$S16*F$6+$T16+$U16+$V16+$W16/F$5+$X16)*(1+$Z16)+$Y16) -> 75.291923 | G16: =$AB16*G$8/(1+GST_RATE)*(1-MP_FEE)-(($R16*G$9/G$5*(1+IF($AA16="Yes",0,G$7))+$S16*G$6+$T16+$U16+$V16+$W16/G$5+$X16)*(1+$Z16)+$Y16) -> 78.253092 | H16: =$AB16*H$8/(1+GST_RATE)*(1-MP_FEE)-(($R16*H$9/H$5*(1+IF($AA16="Yes",0,H$7))+$S16*H$6+$T16+$U16+$V16+$W16/H$5+$X16)*(1+$Z16)+$Y16) -> 50.610638 | I16: =$AB16*I$8/(1+GST_RATE)*(1-MP_FEE)-(($R16*I$9/I$5*(1+IF($AA16="Yes",0,I$7))+$S16*I$6+$T16+$U16+$V16+$W16/I$5+$X16)*(1+$Z16)+$Y16) -> 67.887172 | J16: =$AB16*J$8/(1+GST_RATE)*(1-MP_FEE)-(($R16*J$9/J$5*(1+IF($AA16="Yes",0,J$7))+$S16*J$6+$T16+$U16+$V16+$W16/J$5+$X16)*(1+$Z16)+$Y16) -> 60.030386 | ... L16: =$AB16*L$8/(1+GST_RATE)*(1-MP_FEE)-(($R16*L$9/L$5*(1+IF($AA16="Yes",0,L$7))+$S16*L$6+$T16+$U16+$V16+$W16/L$5+$X16)*(1+$Z16)+$Y16) -> 44.316815 | M16: =C16-INDEX(Products!$BE$5:$BE$23,$O16) -> 0 | O16: =MATCH($B16,SKU_LIST,0) -> 3 | P16: =INDEX(Products!$AG$5:$AG$23,$O16) -> 40HQ | Q16: =INDEX(Products!$AH$5:$AH$23,$O16) -> 300 | R16: =INDEX(Products!$U$5:$U$23,$O16) -> 106.12 | S16: =INDEX(Products!$AR$5:$AR$23,$O16) -> 33.546667 | T16: =INDEX(Products!$AV$5:$AV$23,$O16) -> 1.3333333 | U16: =IF($Q16>0,INDEX(Products!$Y$5:$Y$23,$O16)/$Q16,0) -> 3.3333333 | V16: =INDEX(Products!$Z$5:$Z$23,$O16) -> 0 | W16: =INDEX(Products!$AA$5:$AA$23,$O16) -> 0 | X16: =INDEX(Products!$AX$5:$AX$23,$O16) -> 1.6666667 | Y16: =INDEX(Products!$BB$5:$BB$23,$O16) -> 5.7189 | Z16: =INDEX(Products!$AZ$5:$AZ$23,$O16) -> 0.03 | AA16: =INDEX(Products!$AC$5:$AC$23,$O16) -> No | AB16: =INDEX(Products!$M$5:$M$23,$O16) -> 299
A17: 6 | B17: Queen pocket-spring mattress | C17: =$AB17*C$8/(1+GST_RATE)*(1-MP_FEE)-(($R17*C$9/C$5*(1+IF($AA17="Yes",0,C$7))+$S17*C$6+$T17+$U17+$V17+$W17/C$5+$X17)*(1+$Z17)+$Y17) -> 2.8454927 | D17: =$AB17*D$8/(1+GST_RATE)*(1-MP_FEE)-(($R17*D$9/D$5*(1+IF($AA17="Yes",0,D$7))+$S17*D$6+$T17+$U17+$V17+$W17/D$5+$X17)*(1+$Z17)+$Y17) -> -3.2833877 | E17: =$AB17*E$8/(1+GST_RATE)*(1-MP_FEE)-(($R17*E$9/E$5*(1+IF($AA17="Yes",0,E$7))+$S17*E$6+$T17+$U17+$V17+$W17/E$5+$X17)*(1+$Z17)+$Y17) -> 2.8454927 | F17: =$AB17*F$8/(1+GST_RATE)*(1-MP_FEE)-(($R17*F$9/F$5*(1+IF($AA17="Yes",0,F$7))+$S17*F$6+$T17+$U17+$V17+$W17/F$5+$X17)*(1+$Z17)+$Y17) -> 6.9623447 | G17: =$AB17*G$8/(1+GST_RATE)*(1-MP_FEE)-(($R17*G$9/G$5*(1+IF($AA17="Yes",0,G$7))+$S17*G$6+$T17+$U17+$V17+$W17/G$5+$X17)*(1+$Z17)+$Y17) -> 16.483517 | H17: =$AB17*H$8/(1+GST_RATE)*(1-MP_FEE)-(($R17*H$9/H$5*(1+IF($AA17="Yes",0,H$7))+$S17*H$6+$T17+$U17+$V17+$W17/H$5+$X17)*(1+$Z17)+$Y17) -> -19.884547 | I17: =$AB17*I$8/(1+GST_RATE)*(1-MP_FEE)-(($R17*I$9/I$5*(1+IF($AA17="Yes",0,I$7))+$S17*I$6+$T17+$U17+$V17+$W17/I$5+$X17)*(1+$Z17)+$Y17) -> 2.8454927 | J17: =$AB17*J$8/(1+GST_RATE)*(1-MP_FEE)-(($R17*J$9/J$5*(1+IF($AA17="Yes",0,J$7))+$S17*J$6+$T17+$U17+$V17+$W17/J$5+$X17)*(1+$Z17)+$Y17) -> 2.8454927 | ... L17: =$AB17*L$8/(1+GST_RATE)*(1-MP_FEE)-(($R17*L$9/L$5*(1+IF($AA17="Yes",0,L$7))+$S17*L$6+$T17+$U17+$V17+$W17/L$5+$X17)*(1+$Z17)+$Y17) -> -10.259021 | M17: =C17-INDEX(Products!$BE$5:$BE$23,$O17) -> 0 | O17: =MATCH($B17,SKU_LIST,0) -> 8 | P17: =INDEX(Products!$AG$5:$AG$23,$O17) -> LCL | Q17: =INDEX(Products!$AH$5:$AH$23,$O17) -> 100 | R17: =INDEX(Products!$U$5:$U$23,$O17) -> 59 | S17: =INDEX(Products!$AR$5:$AR$23,$O17) -> 44.136 | T17: =INDEX(Products!$AV$5:$AV$23,$O17) -> 4 | U17: =IF($Q17>0,INDEX(Products!$Y$5:$Y$23,$O17)/$Q17,0) -> 5 | V17: =INDEX(Products!$Z$5:$Z$23,$O17) -> 0.3 | W17: =INDEX(Products!$AA$5:$AA$23,$O17) -> 0 | X17: =INDEX(Products!$AX$5:$AX$23,$O17) -> 0 | Y17: =INDEX(Products!$BB$5:$BB$23,$O17) -> 4.752 | Z17: =INDEX(Products!$AZ$5:$AZ$23,$O17) -> 0.03 | AA17: =INDEX(Products!$AC$5:$AC$23,$O17) -> Yes | AB17: =INDEX(Products!$M$5:$M$23,$O17) -> 165
A18: 7 | B18: Alu camp kitchen + cupboards | C18: =$AB18*C$8/(1+GST_RATE)*(1-MP_FEE)-(($R18*C$9/C$5*(1+IF($AA18="Yes",0,C$7))+$S18*C$6+$T18+$U18+$V18+$W18/C$5+$X18)*(1+$Z18)+$Y18) -> 28.323806 | D18: =$AB18*D$8/(1+GST_RATE)*(1-MP_FEE)-(($R18*D$9/D$5*(1+IF($AA18="Yes",0,D$7))+$S18*D$6+$T18+$U18+$V18+$W18/D$5+$X18)*(1+$Z18)+$Y18) -> 25.259366 | E18: =$AB18*E$8/(1+GST_RATE)*(1-MP_FEE)-(($R18*E$9/E$5*(1+IF($AA18="Yes",0,E$7))+$S18*E$6+$T18+$U18+$V18+$W18/E$5+$X18)*(1+$Z18)+$Y18) -> 28.323806 | F18: =$AB18*F$8/(1+GST_RATE)*(1-MP_FEE)-(($R18*F$9/F$5*(1+IF($AA18="Yes",0,F$7))+$S18*F$6+$T18+$U18+$V18+$W18/F$5+$X18)*(1+$Z18)+$Y18) -> 30.382232 | G18: =$AB18*G$8/(1+GST_RATE)*(1-MP_FEE)-(($R18*G$9/G$5*(1+IF($AA18="Yes",0,G$7))+$S18*G$6+$T18+$U18+$V18+$W18/G$5+$X18)*(1+$Z18)+$Y18) -> 31.97495 | H18: =$AB18*H$8/(1+GST_RATE)*(1-MP_FEE)-(($R18*H$9/H$5*(1+IF($AA18="Yes",0,H$7))+$S18*H$6+$T18+$U18+$V18+$W18/H$5+$X18)*(1+$Z18)+$Y18) -> 22.238566 | I18: =$AB18*I$8/(1+GST_RATE)*(1-MP_FEE)-(($R18*I$9/I$5*(1+IF($AA18="Yes",0,I$7))+$S18*I$6+$T18+$U18+$V18+$W18/I$5+$X18)*(1+$Z18)+$Y18) -> 28.323806 | J18: =$AB18*J$8/(1+GST_RATE)*(1-MP_FEE)-(($R18*J$9/J$5*(1+IF($AA18="Yes",0,J$7))+$S18*J$6+$T18+$U18+$V18+$W18/J$5+$X18)*(1+$Z18)+$Y18) -> 26.139721 | ... L18: =$AB18*L$8/(1+GST_RATE)*(1-MP_FEE)-(($R18*L$9/L$5*(1+IF($AA18="Yes",0,L$7))+$S18*L$6+$T18+$U18+$V18+$W18/L$5+$X18)*(1+$Z18)+$Y18) -> 21.771549 | M18: =C18-INDEX(Products!$BE$5:$BE$23,$O18) -> 0 | O18: =MATCH($B18,SKU_LIST,0) -> 17 | P18: =INDEX(Products!$AG$5:$AG$23,$O18) -> 20GP | Q18: =INDEX(Products!$AH$5:$AH$23,$O18) -> 500 | R18: =INDEX(Products!$U$5:$U$23,$O18) -> 29.5 | S18: =INDEX(Products!$AR$5:$AR$23,$O18) -> 11.816 | T18: =INDEX(Products!$AV$5:$AV$23,$O18) -> 0.8 | U18: =IF($Q18>0,INDEX(Products!$Y$5:$Y$23,$O18)/$Q18,0) -> 0 | V18: =INDEX(Products!$Z$5:$Z$23,$O18) -> 0 | W18: =INDEX(Products!$AA$5:$AA$23,$O18) -> 0 | X18: =INDEX(Products!$AX$5:$AX$23,$O18) -> 0 | Y18: =INDEX(Products!$BB$5:$BB$23,$O18) -> 5 | Z18: =INDEX(Products!$AZ$5:$AZ$23,$O18) -> 0.03 | AA18: =INDEX(Products!$AC$5:$AC$23,$O18) -> No | AB18: =INDEX(Products!$M$5:$M$23,$O18) -> 99
B20: Change vs base (A$ per unit)
A21: # | B21: SKU | C21: =C$4 -> Base | D21: =D$4 -> FX 0.65 | E21: =E$4 -> FX 0.6956 | F21: =F$4 -> FX 0.73 | G21: =G$4 -> Freight −30% | H21: =H$4 -> Freight +50% | I21: =I$4 -> Duty 0% (CoO held) | J21: =J$4 -> Duty 5% (no CoO) | ... L21: =L$4 -> FOB +15%
A22: 1 | B22: =$B12 -> Trampoline 14ft + enclosure | C22: =C12-$C12 -> 0 | D22: =D12-$C12 -> -9.9724156 | E22: =E12-$C12 -> 0 | F22: =F12-$C12 -> 6.6986065 | G22: =G12-$C12 -> 14.262281 | H22: =H12-$C12 -> -23.770469 | I22: =I12-$C12 -> 0 | J22: =J12-$C12 -> -7.1075331 | ... L22: =L12-$C12 -> -21.322599
A23: 2 | B23: =$B13 -> Dual-motor standing desk | C23: =C13-$C13 -> 0 | D23: =D13-$C13 -> -10.387933 | E23: =E13-$C13 -> 0 | F23: =F13-$C13 -> 6.9777151 | G23: =G13-$C13 -> 10.471392 | H23: =H13-$C13 -> -17.45232 | I23: =I13-$C13 -> 0 | J23: =J13-$C13 -> -7.4036803 | ... L23: =L13-$C13 -> -22.211041
A24: 3 | B24: =$B14 -> 100kg bumper plate set | C24: =C14-$C14 -> 0 | D24: =D14-$C14 -> -13.504313 | E24: =E14-$C14 -> 0 | F24: =F14-$C14 -> 9.0710296 | G24: =G14-$C14 -> 8.652 | H24: =H14-$C14 -> -14.42 | I24: =I14-$C14 -> 0 | J24: =J14-$C14 -> -9.6247844 | ... L24: =L14-$C14 -> -28.874353
A25: 4 | B25: =$B15 -> Double hammock + steel stand | C25: =C15-$C15 -> 0 | D25: =D15-$C15 -> -2.1814659 | E25: =E15-$C15 -> 0 | F25: =F15-$C15 -> 1.4653202 | G25: =G15-$C15 -> 6.0083542 | H25: =H15-$C15 -> -10.013924 | I25: =I15-$C15 -> 0 | J25: =J15-$C15 -> -1.5547729 | ... L25: =L15-$C15 -> -4.6643186
A26: 5 | B26: =$B16 -> Timber cubby house | C26: =C16-$C16 -> 0 | D26: =D16-$C16 -> -11.023674 | E26: =E16-$C16 -> 0 | F26: =F16-$C16 -> 7.4047513 | G26: =G16-$C16 -> 10.36592 | H26: =H16-$C16 -> -17.276533 | I26: =I16-$C16 -> 0 | J26: =J16-$C16 -> -7.8567855 | ... L26: =L16-$C16 -> -23.570357
A27: 6 | B27: =$B17 -> Queen pocket-spring mattress | C27: =C17-$C17 -> 0 | D27: =D17-$C17 -> -6.1288804 | E27: =E17-$C17 -> 0 | F27: =F17-$C17 -> 4.1168519 | G27: =G17-$C17 -> 13.638024 | H27: =H17-$C17 -> -22.73004 | I27: =I17-$C17 -> 0 | J27: =J17-$C17 -> 0 | ... L27: =L17-$C17 -> -13.104514
A28: 7 | B28: =$B18 -> Alu camp kitchen + cupboards | C28: =C18-$C18 -> 0 | D28: =D18-$C18 -> -3.0644402 | E28: =E18-$C18 -> 0 | F28: =F18-$C18 -> 2.058426 | G28: =G18-$C18 -> 3.651144 | H28: =H18-$C18 -> -6.08524 | I28: =I18-$C18 -> 0 | J28: =J18-$C18 -> -2.1840857 | ... L28: =L18-$C18 -> -6.552257
B30: GP % of net revenue
A31: # | B31: SKU | C31: =C$4 -> Base | D31: =D$4 -> FX 0.65 | E31: =E$4 -> FX 0.6956 | F31: =F$4 -> FX 0.73 | G31: =G$4 -> Freight −30% | H31: =H$4 -> Freight +50% | I31: =I$4 -> Duty 0% (CoO held) | J31: =J$4 -> Duty 5% (no CoO) | ... L31: =L$4 -> FOB +15%
A32: 1 | B32: =$B12 -> Trampoline 14ft + enclosure | C32: =IF($AB12*C$8>0,C12/($AB12*C$8/(1+GST_RATE)*(1-MP_FEE)),0) -> 0.30593361 | D32: =IF($AB12*D$8>0,D12/($AB12*D$8/(1+GST_RATE)*(1-MP_FEE)),0) -> 0.27450193 | E32: =IF($AB12*E$8>0,E12/($AB12*E$8/(1+GST_RATE)*(1-MP_FEE)),0) -> 0.30593361 | F32: =IF($AB12*F$8>0,F12/($AB12*F$8/(1+GST_RATE)*(1-MP_FEE)),0) -> 0.3270467 | G32: =IF($AB12*G$8>0,G12/($AB12*G$8/(1+GST_RATE)*(1-MP_FEE)),0) -> 0.35088636 | H32: =IF($AB12*H$8>0,H12/($AB12*H$8/(1+GST_RATE)*(1-MP_FEE)),0) -> 0.23101236 | I32: =IF($AB12*I$8>0,I12/($AB12*I$8/(1+GST_RATE)*(1-MP_FEE)),0) -> 0.30593361 | J32: =IF($AB12*J$8>0,J12/($AB12*J$8/(1+GST_RATE)*(1-MP_FEE)),0) -> 0.28353164 | ... L32: =IF($AB12*L$8>0,L12/($AB12*L$8/(1+GST_RATE)*(1-MP_FEE)),0) -> 0.23872771
A33: 2 | B33: =$B13 -> Dual-motor standing desk | C33: =IF($AB13*C$8>0,C13/($AB13*C$8/(1+GST_RATE)*(1-MP_FEE)),0) -> 0.17312734 | D33: =IF($AB13*D$8>0,D13/($AB13*D$8/(1+GST_RATE)*(1-MP_FEE)),0) -> 0.13491087 | E33: =IF($AB13*E$8>0,E13/($AB13*E$8/(1+GST_RATE)*(1-MP_FEE)),0) -> 0.17312734 | F33: =IF($AB13*F$8>0,F13/($AB13*F$8/(1+GST_RATE)*(1-MP_FEE)),0) -> 0.19879787 | G33: =IF($AB13*G$8>0,G13/($AB13*G$8/(1+GST_RATE)*(1-MP_FEE)),0) -> 0.21165086 | H33: =IF($AB13*H$8>0,H13/($AB13*H$8/(1+GST_RATE)*(1-MP_FEE)),0) -> 0.10892148 | I33: =IF($AB13*I$8>0,I13/($AB13*I$8/(1+GST_RATE)*(1-MP_FEE)),0) -> 0.17312734 | J33: =IF($AB13*J$8>0,J13/($AB13*J$8/(1+GST_RATE)*(1-MP_FEE)),0) -> 0.14588972 | ... L33: =IF($AB13*L$8>0,L13/($AB13*L$8/(1+GST_RATE)*(1-MP_FEE)),0) -> 0.091414483
A34: 3 | B34: =$B14 -> 100kg bumper plate set | C34: =IF($AB14*C$8>0,C14/($AB14*C$8/(1+GST_RATE)*(1-MP_FEE)),0) -> 0.25924152 | D34: =IF($AB14*D$8>0,D14/($AB14*D$8/(1+GST_RATE)*(1-MP_FEE)),0) -> 0.21542222 | E34: =IF($AB14*E$8>0,E14/($AB14*E$8/(1+GST_RATE)*(1-MP_FEE)),0) -> 0.25924152 | F34: =IF($AB14*F$8>0,F14/($AB14*F$8/(1+GST_RATE)*(1-MP_FEE)),0) -> 0.28867554 | G34: =IF($AB14*G$8>0,G14/($AB14*G$8/(1+GST_RATE)*(1-MP_FEE)),0) -> 0.28731586 | H34: =IF($AB14*H$8>0,H14/($AB14*H$8/(1+GST_RATE)*(1-MP_FEE)),0) -> 0.21245096 | I34: =IF($AB14*I$8>0,I14/($AB14*I$8/(1+GST_RATE)*(1-MP_FEE)),0) -> 0.25924152 | J34: =IF($AB14*J$8>0,J14/($AB14*J$8/(1+GST_RATE)*(1-MP_FEE)),0) -> 0.22801066 | ... L34: =IF($AB14*L$8>0,L14/($AB14*L$8/(1+GST_RATE)*(1-MP_FEE)),0) -> 0.16554893
A35: 4 | B35: =$B15 -> Double hammock + steel stand | C35: =IF($AB15*C$8>0,C15/($AB15*C$8/(1+GST_RATE)*(1-MP_FEE)),0) -> 0.33097434 | D35: =IF($AB15*D$8>0,D15/($AB15*D$8/(1+GST_RATE)*(1-MP_FEE)),0) -> 0.30571526 | E35: =IF($AB15*E$8>0,E15/($AB15*E$8/(1+GST_RATE)*(1-MP_FEE)),0) -> 0.33097434 | F35: =IF($AB15*F$8>0,F15/($AB15*F$8/(1+GST_RATE)*(1-MP_FEE)),0) -> 0.34794121 | G35: =IF($AB15*G$8>0,G15/($AB15*G$8/(1+GST_RATE)*(1-MP_FEE)),0) -> 0.40054476 | H35: =IF($AB15*H$8>0,H15/($AB15*H$8/(1+GST_RATE)*(1-MP_FEE)),0) -> 0.21502365 | I35: =IF($AB15*I$8>0,I15/($AB15*I$8/(1+GST_RATE)*(1-MP_FEE)),0) -> 0.33097434 | J35: =IF($AB15*J$8>0,J15/($AB15*J$8/(1+GST_RATE)*(1-MP_FEE)),0) -> 0.31297171 | ... L35: =IF($AB15*L$8>0,L15/($AB15*L$8/(1+GST_RATE)*(1-MP_FEE)),0) -> 0.27696644
A36: 5 | B36: =$B16 -> Timber cubby house | C36: =IF($AB16*C$8>0,C16/($AB16*C$8/(1+GST_RATE)*(1-MP_FEE)),0) -> 0.24975214 | D36: =IF($AB16*D$8>0,D16/($AB16*D$8/(1+GST_RATE)*(1-MP_FEE)),0) -> 0.20919681 | E36: =IF($AB16*E$8>0,E16/($AB16*E$8/(1+GST_RATE)*(1-MP_FEE)),0) -> 0.24975214 | F36: =IF($AB16*F$8>0,F16/($AB16*F$8/(1+GST_RATE)*(1-MP_FEE)),0) -> 0.2769937 | G36: =IF($AB16*G$8>0,G16/($AB16*G$8/(1+GST_RATE)*(1-MP_FEE)),0) -> 0.28788763 | H36: =IF($AB16*H$8>0,H16/($AB16*H$8/(1+GST_RATE)*(1-MP_FEE)),0) -> 0.18619298 | I36: =IF($AB16*I$8>0,I16/($AB16*I$8/(1+GST_RATE)*(1-MP_FEE)),0) -> 0.24975214 | J36: =IF($AB16*J$8>0,J16/($AB16*J$8/(1+GST_RATE)*(1-MP_FEE)),0) -> 0.22084757 | ... L36: =IF($AB16*L$8>0,L16/($AB16*L$8/(1+GST_RATE)*(1-MP_FEE)),0) -> 0.16303845
A37: 6 | B37: =$B17 -> Queen pocket-spring mattress | C37: =IF($AB17*C$8>0,C17/($AB17*C$8/(1+GST_RATE)*(1-MP_FEE)),0) -> 0.018969952 | D37: =IF($AB17*D$8>0,D17/($AB17*D$8/(1+GST_RATE)*(1-MP_FEE)),0) -> -0.021889251 | E37: =IF($AB17*E$8>0,E17/($AB17*E$8/(1+GST_RATE)*(1-MP_FEE)),0) -> 0.018969952 | F37: =IF($AB17*F$8>0,F17/($AB17*F$8/(1+GST_RATE)*(1-MP_FEE)),0) -> 0.046415631 | G37: =IF($AB17*G$8>0,G17/($AB17*G$8/(1+GST_RATE)*(1-MP_FEE)),0) -> 0.10989011 | H37: =IF($AB17*H$8>0,H17/($AB17*H$8/(1+GST_RATE)*(1-MP_FEE)),0) -> -0.13256365 | I37: =IF($AB17*I$8>0,I17/($AB17*I$8/(1+GST_RATE)*(1-MP_FEE)),0) -> 0.018969952 | J37: =IF($AB17*J$8>0,J17/($AB17*J$8/(1+GST_RATE)*(1-MP_FEE)),0) -> 0.018969952 | ... L37: =IF($AB17*L$8>0,L17/($AB17*L$8/(1+GST_RATE)*(1-MP_FEE)),0) -> -0.068393476
A38: 7 | B38: =$B18 -> Alu camp kitchen + cupboards | C38: =IF($AB18*C$8>0,C18/($AB18*C$8/(1+GST_RATE)*(1-MP_FEE)),0) -> 0.31470896 | D38: =IF($AB18*D$8>0,D18/($AB18*D$8/(1+GST_RATE)*(1-MP_FEE)),0) -> 0.28065962 | E38: =IF($AB18*E$8>0,E18/($AB18*E$8/(1+GST_RATE)*(1-MP_FEE)),0) -> 0.31470896 | F38: =IF($AB18*F$8>0,F18/($AB18*F$8/(1+GST_RATE)*(1-MP_FEE)),0) -> 0.33758036 | G38: =IF($AB18*G$8>0,G18/($AB18*G$8/(1+GST_RATE)*(1-MP_FEE)),0) -> 0.35527723 | H38: =IF($AB18*H$8>0,H18/($AB18*H$8/(1+GST_RATE)*(1-MP_FEE)),0) -> 0.24709518 | I38: =IF($AB18*I$8>0,I18/($AB18*I$8/(1+GST_RATE)*(1-MP_FEE)),0) -> 0.31470896 | J38: =IF($AB18*J$8>0,J18/($AB18*J$8/(1+GST_RATE)*(1-MP_FEE)),0) -> 0.29044134 | ... L38: =IF($AB18*L$8>0,L18/($AB18*L$8/(1+GST_RATE)*(1-MP_FEE)),0) -> 0.2419061

Sheet Sources
A1: Sources – URLs behind each price, supplier and compliance figure (copied from the notes)
A2: One row per URL per SKU, de-duplicated. 'Used in Products' marks the price-to-beat and supplier listing behind each Products row. Context is the note's own bullet text (trimmed). Several retailer figures are search-engine snippets or undated (see each note); supplier prices are public listing prices, not quotes.
A4: SKU # | B4: SKU / topic | C4: Role | D4: Link text in the note | E4: What the note says (context) | F4: URL | G4: Note file and section
A5: 1 | B5: Trampoline 14ft + enclosure | C5: Price to beat – used in Products | D5: Amazon B08FWVCRG1 | E5: Amazon BS Trampolines; Amazon B08FWVCRG1 | F5: https://www.amazon.com.au/dp/B08FWVCRG1 | G5: verify_kids.md Q1 – Price to beat (AU, 9 Oct 2026)
A6: 1 | B6: Trampoline 14ft + enclosure | C6: Supplier listing – used in Products | D6: Lingsha 14FT | E6: Lingsha 14FT; Lingsha Economy 14FT; Lingsha 6–16ft | F6: https://lsfunjump.en.made-in-china.com/product/uphRrGWYIgci/China-Funjump-14FT-Outdoor-Indoor-Fitness-Kid-Child-Mini-Bungee-Jumping-Trampoline-with-Safety-Enclosure.html | G6: verify_kids.md Q1 – Factories (Made-in-China listings, 9 Oct 2026)
A7: 1 | B7: Trampoline 14ft + enclosure | C7: Price evidence | D7: Amazon BS Trampolines | E7: Amazon BS Trampolines; Amazon B08FWVCRG1 | F7: https://www.amazon.com.au/gp/bestsellers/sporting-goods/5044230051 | G7: verify_kids.md Q1 – Price to beat (AU, 9 Oct 2026)
A8: 1 | B8: Trampoline 14ft + enclosure | C8: Price evidence | D8: OzBargain | E8: Indicative Amazon delivery charge on big trampolines. New Aim's 16ft Everfit on Amazon AU was posted as "$43 (RRP $722) + Delivery (e.g. $120 to Metro Brisbane)" on 25 Jun 2026. The $43 was a pricing-error deal; the $120 delivery is the … | F8: https://www.ozbargain.com.au/node/965103 | G8: verify_kids.md Q1 – Price to beat (AU, 9 Oct 2026)
A9: 1 | B9: Trampoline 14ft + enclosure | C9: Price evidence | D9: TRU Bestway 14ft | E9: TRU Bestway 14ft; TRU Everfit 14FT; TRU Everfit 12FT | F9: https://www.toysrus.com.au/products/bestway-14ft-trampoline-kids-rebounder-safety-net-enclosure-outdoor-fitness-4-27m-for-ages | G9: verify_kids.md Q1 – Price to beat (AU, 9 Oct 2026)
A10: 1 | B10: Trampoline 14ft + enclosure | C10: Price evidence | D10: TRU Everfit 14FT | E10: TRU Bestway 14ft; TRU Everfit 14FT; TRU Everfit 12FT | F10: https://www.toysrus.com.au/products/everfit-14ft-kids-trampoline-rebounder-with-enclosure-net-storage-bag | G10: verify_kids.md Q1 – Price to beat (AU, 9 Oct 2026)
A11: 1 | B11: Trampoline 14ft + enclosure | C11: Price evidence | D11: TRU Everfit 12FT | E11: TRU Bestway 14ft; TRU Everfit 14FT; TRU Everfit 12FT | F11: https://www.toysrus.com.au/products/everfit-12ft-kids-trampoline-rectangle-rebounder-with-basketball-set-blue | G11: verify_kids.md Q1 – Price to beat (AU, 9 Oct 2026)
A12: 1 | B12: Trampoline 14ft + enclosure | C12: Price evidence | D12: Everfit 14FT | E12: Everfit: 10ft $582.99; 12ft $666.99; 14FT $666.99–$719.99; 16ft $842.99–$852.99. — Everfit 14FT; Everfit 12FT | F12: https://www.everfit.com.au/products/everfit-14ft-trampoline-round-trampolines-with-basketball-hoop-kids-present-gift-enclosure | G12: verify_kids.md Q1 – Price to beat (AU, 9 Oct 2026)
A13: 1 | B13: Trampoline 14ft + enclosure | C13: Price evidence | D13: Everfit 12FT | E13: Everfit: 10ft $582.99; 12ft $666.99; 14FT $666.99–$719.99; 16ft $842.99–$852.99. — Everfit 14FT; Everfit 12FT | F13: https://www.everfit.com.au/products/everfit-12ft-trampoline-round-trampolines-with-basketball-hoop-kids-present-gift-enclosure | G13: verify_kids.md Q1 – Price to beat (AU, 9 Oct 2026)
A14: 1 | B14: Trampoline 14ft + enclosure | C14: Price evidence | D14: Lifespan Kids 14ft | E14: Lifespan Kids BounceZone: 10ft $649; 12ft $769; 14ft $869. — Lifespan Kids 14ft | F14: https://www.lifespankids.com.au/products/bouncezone-round-spring-trampoline-xl | G14: verify_kids.md Q1 – Price to beat (AU, 9 Oct 2026)
A15: 1 | B15: Trampoline 14ft + enclosure | C15: Price evidence | D15: Advwin | E15: Advwin 10ft with sprinkler: $329.90 (was $639.90). — Advwin | F15: https://www.advwin.com.au/products/advwin-10ft-outdoor-trampoline-w-sprinkler-330502111-330502121 | G15: verify_kids.md Q1 – Price to beat (AU, 9 Oct 2026)
A16: 1 | B16: Trampoline 14ft + enclosure | C16: Price evidence | D16: Kmart snippet | E16: 12ft Springless Trampoline $299, rated 4.7 from 199 reviews, max 100 kg. — Kmart snippet | F16: https://www.kmart.com.au/product/12-foot-springless-trampoline-42836155/ | G16: verify_kids.md Q1 – Price to beat (AU, 9 Oct 2026)
... A497: 19 | B497: Recovery kit + tracks bundle | C497: Supplier listing – used in Products | D497: Workercare tracks | E497: Manufacturer/Factory & Trading; Diamond since 2014; Audited Supplier. — Workercare tracks | F497: https://workercare.en.made-in-china.com/product/FAWpjcSHnJYX/China-Recovery-Traction-Tracks-Tire-Ladder-for-Sand-Snow-Mud-4WD.html | G497: verify_camping_appliance.md Q2 – Factories (Made-in-China.com, fetched 2026-10-09; listed pri
A498: – | B498: Mixed 20GP (gym) – container limits | C498: Compliance, duty & freight | D498: ICE Cargo | E498: Container cargo limits: 20GP 21.8 t (QLD/SA/WA/TAS), 23.8 t (VIC), 24.3 t (NSW) — ICE Cargo (as cited in vertical_home_gym.md). | F498: https://icecargo.com.au/transport-options/ | G498: verify_gym_pets.md Q5
A499: – | B499: Mixed 40HQ (outdoor) | C499: Supplier evidence | D499: MIC | E499: All inputs are the verified supplier data and floors cited in Q1–Q3: Otia US$44.50 (100–499 tier), 0.0778 CBM (MIC); Ningbo Lounger US$20–21, 0.0612 CBM (MIC); Fanpin foldable US$50 (10–399), 0.143 CBM (MIC). | F499: https://qdotia.en.made-in-china.com/product/imFpKPLCglYa/China-Amazon-Portable-Rotating-Pizza-Oven-with-Pizza-Stone-Wooden-Pellet-Pizza-Oven-Folding-Outdoor-Pizza-Oven.html | G499: verify_outdoor.md Q4
A500: – | B500: Mixed 40HQ (outdoor) | C500: Supplier evidence | D500: MIC | E500: All inputs are the verified supplier data and floors cited in Q1–Q3: Otia US$44.50 (100–499 tier), 0.0778 CBM (MIC); Ningbo Lounger US$20–21, 0.0612 CBM (MIC); Fanpin foldable US$50 (10–399), 0.143 CBM (MIC). | F500: https://lounger2.en.made-in-china.com/product/zatrBMfGjmRi/China-Easy-Assemble-Folding-Double-Portable-Hammock-with-Stand.html | G500: verify_outdoor.md Q4
A501: – | B501: Mixed 40HQ (outdoor) | C501: Supplier evidence | D501: MIC | E501: All inputs are the verified supplier data and floors cited in Q1–Q3: Otia US$44.50 (100–499 tier), 0.0778 CBM (MIC); Ningbo Lounger US$20–21, 0.0612 CBM (MIC); Fanpin foldable US$50 (10–399), 0.143 CBM (MIC). | F501: https://fanpin.en.made-in-china.com/product/JTwUWsrvCKRc/China-Wholesale-Foldable-Steel-Outdoor-Furniture-Garden-Balcony-Patio-Swing-Egg-Hanging-Chair.html | G501: verify_outdoor.md Q4
A502: – | B502: Mixed 40HQ (outdoor) | C502: Supplier evidence | D502: Max Garden | E502: Suppliers sit in three provinces (Qingdao, Shandong; Ningbo, Zhejiang; Shangqiu, Henan), and SKU-mix limits appear on some listings ("40HQ container with no more than 4 items" — Max Garden; "1*40HQ container with no more than 5 items" — … | F502: https://green-tide.en.made-in-china.com/product/HdNtBSJPlLcF/China-Outdoor-Garden-Furniture-Wicker-Egg-Hanging-Chair-with-Metal-Stand.html | G502: verify_outdoor.md Q4
A503: – | B503: Mixed 40HQ (outdoor) | C503: Supplier evidence | D503: Xusheng | E503: Suppliers sit in three provinces (Qingdao, Shandong; Ningbo, Zhejiang; Shangqiu, Henan), and SKU-mix limits appear on some listings ("40HQ container with no more than 4 items" — Max Garden; "1*40HQ container with no more than 5 items" — … | F503: https://xushengcompany.en.made-in-china.com/product/tZsAeqGordRV/China-Outdoor-Patio-Double-Hammock-with-Space-Saving-Steel-Stand.html | G503: verify_outdoor.md Q4
A504: – | B504: Mixed 40HQ (outdoor) | C504: Compliance, duty & freight | D504: KLN Sept 2026 outlook | E504: Timing (from the original outdoor notes, not re-verified): PO to sellable stock ~10–13 weeks, so an October PO lands about January 2027, after Black Friday and Christmas — KLN Sept 2026 outlook (via vertical_outdoor_living.md). | F504: https://info.oceania.kln.com/customer-advisory/fcl-shipping-rates-from-china-to-australia-september-2026-outlook | G504: verify_outdoor.md Q4
A505: – | B505: Kids cross-check (trampoline / ride-on benchmarks) | C505: Price evidence | D505: Kmart 10ft (snippet) | E505: local file `au_retail_price_benchmarks.md`; Kmart 10ft (snippet); Advwin; OzBargain Can-Am | F505: https://www.kmart.com.au/product/10-foot-trampoline-with-enclosure-42912026 | G505: verify_kids.md Q5
A506: – | B506: Kids cross-check (trampoline / ride-on benchmarks) | C506: Price evidence | D506: Advwin | E506: local file `au_retail_price_benchmarks.md`; Kmart 10ft (snippet); Advwin; OzBargain Can-Am | F506: https://www.advwin.com.au/products/advwin-trampoline-10ft-outdoor-trampoline-330502110-330502120 | G506: verify_kids.md Q5
A507: – | B507: Kids cross-check (trampoline / ride-on benchmarks) | C507: Price evidence | D507: OzBargain Can-Am | E507: local file `au_retail_price_benchmarks.md`; Kmart 10ft (snippet); Advwin; OzBargain Can-Am | F507: https://www.ozbargain.com.au/node/955078 | G507: verify_kids.md Q5
A508: – | B508: Kids cross-check (trampoline / ride-on benchmarks) | C508: Price evidence | D508: Amazon B08FWVCRG1 | E508: Amazon B08FWVCRG1 is the 14FT variant, which resolves the benchmark file's "size unspecified". — Amazon B08FWVCRG1 | F508: https://www.amazon.com.au/dp/B08FWVCRG1 | G508: verify_kids.md Q5
A509: – | B509: Kids cross-check (trampoline / ride-on benchmarks) | C509: Price evidence | D509: Kmart 12ft springless | E509: Kmart 12ft springless $299 and 12ft rectangular $399 (snippets). — Kmart 12ft springless | F509: https://www.kmart.com.au/product/12-foot-springless-trampoline-42836155/ | G509: verify_kids.md Q5
... A549: – | B549: General – FX, freight, duty, GST, EESS, Marketplace fees | C549: Compliance, duty & freight | D549: EFTM | E549: eBay Australia (May 2026): no transaction fees for "casual sellers" with under AUD 25,000 in annual sales. — EFTM | F549: https://eftm.com/2026/05/ebay-australia-has-dropped-fees-for-casual-sellers-clean-out-and-clean-up-without-any-fees-275988 | G549: au_landed_cost_compliance.md §8
